Workbook
Name actionlist: #REF!
Name actionlist: #REF!
Name Adopted_Value: [4]DCF_Approach!$F$9
Name Adopted_Value: #REF!
Name Block.5Yr: '[5]sino-p35'!$J$36:$O$41
Name Block.5Yr: #REF!
Name block.Assumptions.blue: #REF!
Name block.Assumptions.blue: #REF!
Name block.Author.blue: #REF!
Name block.Author.blue: #REF!
Name Block.BalSheet: '[5]sino-p35'!$B$27:$G$58
Name Block.BalSheet: #REF!
Name Block.Cashflow: '[5]sino-p35'!$J$7:$O$25
Name Block.Cashflow: #REF!
Name Block.CorpStruct: '[5]sino-p35'!$J$60:$O$67
Name Block.CorpStruct: #REF!
Name block.Expansion.blue: #REF!
Name block.Expansion.blue: #REF!
Name block.Forecasts.blue: #REF!
Name block.Forecasts.blue: #REF!
Name Block.Free: '[5]sino-p35'!$J$26:$O$41
Name Block.Free: #REF!
Name block.IncomeStatement.blue: #REF!
Name block.IncomeStatement.blue: #REF!
Name block.KeyData.blue: #REF!
Name block.KeyData.blue: #REF!
Name block.Miscellaneous.blue: #REF!
Name block.Miscellaneous.blue: #REF!
Name block.Miscellaneous.none: #REF!
Name block.Miscellaneous.none: #REF!
Name Block.Profit: '[5]sino-p35'!$B$7:$G$22
Name Block.Profit: #REF!
Name Block.Ratios: '[5]sino-p35'!$J$27:$O$32
Name Block.Ratios: #REF!
Name block.SalesBreakdown.blue: #REF!
Name block.SalesBreakdown.blue: #REF!
Name block.Subsidiaries.blue: #REF!
Name block.Subsidiaries.blue: #REF!
Name Bot_Tenant: '[7]Tenancy Analysis'!$B$475
Name Bot_Tenant: #REF!
Name Building_Description: [4]Model!$F$17
Name Building_Description: #REF!
Name CC: [8]Summaries!$A$2:$B$181
Name CC: #REF!
Name churn1: #REF!
Name churn1: [9]!churn1
Name churn1: #REF!
Name churn1: #REF!
Name churn1: #REF!
Name churn1: #REF!
Name churn1: #REF!
Name churn1: #REF!
Name churn1: #REF!
Name churn1: #REF!
Name churn1: #REF!
Name Co_Name: '[10]Key data'!$A$1
Name Co_Name: #REF!
Name Core_Cap: [4]Model!$F$41
Name Core_Cap: #REF!
Name COSCO_Capacity_Growth: #REF!

Sheet Title
A1: Mapletree Quarterly Market Research Study
A6: Seoul Office
A9: Prepared by: Colliers
D11: [INSERT PICTURE OF THE MARKET]

Sheet Map
A1: Seoul Map of Grade A Office Building Submarkets

Sheet Map_II
A1: Seoul Map of Grade A Office Building Submarkets_II

Sheet Macro Econ>>

Sheet Macro
A1: Supporting Docs 2a: Key Macroeconomic Highlights - For Each Market | N1: Note from Colliers: Section will be further updated with release of 2Q 2025 data.
A3: As requested, please find the latest economic highlights for the various markets.
A5: Singapore Retail
A7: 1. GDP Forecast
A8: - Based on advance estimates, Singapore’s GDP grew by 4.1% in 3Q 2024, extending the 2.9% growth in 2Q 2024.
A9: - For whole of 2023, GDP grew by 1.1%. Singapore's economy is forecasted to grow by 2% to 3% in 2024.
A10: 2. Retail Sales
A11: - Retail sales (excluding motor vehicles) in August 2024 declined 1.5% yoy, overall retail sales in 2Q 2024 down 2.7% yoy.
A12: - 2023 vs 2022 an increase of 1.7%.
A13: 3. Recent notable events
A14: - From Jan. 1, 2024, GST rate has increased from 8% to 9%.
A15: - Tourist arrivals recorded 12.5 million in 9M 2024, about 87.8% of the same period in 2019 before COVID. The return of mainland visitors in 9M 2024 is about 87.1% of the same period in 2019 before COVID.
A16: - STB forecasts overall international visitor arrivals in 2024 to reach around 15 to 16 million.
... A81: - Grade A prime office buildings in the core area of Teheran-ro within the GBD continues to remain popular among end-users and financial investors.

Sheet Headlines
A1: Headlines
B2: Table: Real GDP Growth Rate, Unemployment Rate, Inflation Rate and their Forecast
B3: Indicator | C3: 2017 | D3: 2018 | E3: 2019 | F3: 2020 | G3: 2021 | H3: 2022 | I3: 2023 | J3: 2024 | K3: 1Q 2025 | L3: 2Q 2025 | M3: 3Q 2025 | N3: 4Q 2025 | O3: 2025 (F) | P3: 2026 (F)
B4: Real GDP Growth Rate | C4: 0.032 | D4: 0.029 | E4: 0.022 | F4: -0.007 | G4: 0.041 | H4: 0.026 | I4: 0.014 | J4: 0.02 | K4: -0.001 | L4: 0.003 | M4: 0.013 | N4: 0.015 | O4: 0.009 | P4: 0.018
B5: YoY/QoQ | D5: =D4-C4 -> -0.003 | E5: =E4-D4 -> -0.007 | F5: =F4-E4 -> -0.029 | G5: =G4-F4 -> 0.048 | H5: =H4-G4 -> -0.015 | I5: =I4-H4 -> -0.012 | J5: =J4-I4 -> 0.006 | L5: =L4-K4 -> 0.004 | M5: =M4-L4 -> 0.01 | N5: =N4-M4 -> 0.002 | O5: =O4-J4 -> -0.011 | P5: =P4-O4 -> 0.009
B6: Inflation Rate | C6: 0.0194 | D6: 0.0148 | E6: 0.0038 | F6: 0.0054 | G6: 0.025 | H6: 0.051 | I6: 0.036 | J6: 0.023 | K6: 0.021 | L6: 0.02 | M6: 0.019 | N6: 0.021 | O6: 0.021 | P6: 0.02
B7: YoY/QoQ | D7: =D6-C6 -> -0.0046 | E7: =E6-D6 -> -0.011 | F7: =F6-E6 -> 0.0016 | G7: =G6-F6 -> 0.0196 | H7: =H6-G6 -> 0.026 | I7: =I6-H6 -> -0.015 | J7: =J6-I6 -> -0.013 | L7: =L6-K6 -> -0.001 | M7: =M6-L6 -> -0.001 | N7: =N6-M6 -> 0.002 | O7: =O6-J6 -> -0.002 | P7: =P6-O6 -> -0.001
B8: Unemployment Rate | C8: 0.037 | D8: 0.039 | E8: 0.038 | F8: 0.04 | G8: 0.037 | H8: 0.029 | I8: 0.027 | J8: 0.028 | K8: 0.034 | L8: 0.033 | M8: 0.025 | N8: 0.025 | O8: 0.028 | P8: 0.028
B9: YoY/QoQ | D9: =D8-C8 -> 0.002 | E9: =E8-D8 -> -0.001 | F9: =F8-E8 -> 0.002 | G9: =G8-F8 -> -0.003 | H9: =H8-G8 -> -0.008 | I9: =I8-H8 -> -0.002 | J9: =J8-I8 -> 0.001 | L9: =L8-K8 -> -0.001 | M9: =M8-L8 -> -0.008 | N9: =N8-M8 -> 0 | O9: =O8-J8 -> 0 | P9: =P8-O8 -> 0
B10: Source(s): KOSIS, Bank Of Korea, National Assembly, KDI | E10: =E9-D9 -> -0.003 | F10: =F9-E9 -> 0.003 | G10: =G9-F9 -> -0.005 | H10: =H9-G9 -> -0.005 | I10: =I9-H9 -> 0.006 | J10: =J9-I9 -> 0.003 | L10: =L9-K9 -> -0.001 | M10: =M9-L9 -> -0.007 | N10: =N9-M9 -> 0.008
B13: Recently, the Korean economy has continued to experience weakness in the construction sector; however, a gradual economic recovery led by consumption has been maintained. GDP increased by 0.2pp quarter-on-quarter, supported by improvements in consumption and exports, and recorded a higher year-on-year growth rate compared to the previous quarter. While domestic demand remains constrained by weak construction investment, the downturn has been partially offset by improving consumption. Facility investment continues to underperform outside the semiconductor sector, and despite an increase in construction orders, construction investment has continued to decline as orders have not translated smoothly into actual development activity. In contrast, private consumption has expanded, supported by declining market interest rates and government support measures, while government consumption has also recorded strong growth, contributing to the overall economic recovery. Employment has shown a moderate increase, mainly in the service sector, which is significantly influenced by government job programs. In 2026, Korea’s economy is expected to grow by approximately 1.8%, as domestic demand recovers despite a moderation in exports. Consumer prices are projected to rise by around 2.0%, broadly in line with this year’s 2.1%, as recovering domestic demand is offset by declining international oil prices. Employment conditions are expected to improve gradually in line with the domestic recovery; however, due to demographic structural changes, the total number of employed persons is projected to decline compared to this year.

Sheet Visitor Arrivals
A1: Seoul Tourist Arrivals
A3: Table: Number of Tourist Arrivals ('000) (Yearly)
B4: Tourist Arrivals
A5: Year | B5: Total visitor | C5: YoY Change in All Visitors
A7: 2009 | B7: 7817.533 | C7: -
A8: 2010 | B8: 8797.658 | C8: =B8/B7-1 -> 0.12537523 | E8: =B8/B7-1 -> 0.12537523
A9: 2011 | B9: 9794.796 | C9: =B9/B8-1 -> 0.1133413 | E9: =B9/B8-1 -> 0.1133413
A10: 2012 | B10: 11140.028 | C10: =B10/B9-1 -> 0.1373415 | E10: =B10/B9-1 -> 0.1373415
A11: 2013 | B11: 12175.55 | C11: =B11/B10-1 -> 0.092955063 | E11: =B11/B10-1 -> 0.092955063
A12: 2014 | B12: 14201.516 | C12: =B12/B11-1 -> 0.16639626 | E12: =B12/B11-1 -> 0.16639626
A13: 2015 | B13: 13231.651 | C13: =B13/B12-1 -> -0.068293061 | E13: =B13/B12-1 -> -0.068293061
A14: 2016 | B14: 17241.823 | C14: =B14/B13-1 -> 0.3030742 | E14: =B14/B13-1 -> 0.3030742
A15: 2017 | B15: 13335.758 | C15: =B15/B14-1 -> -0.22654594 | E15: =B15/B14-1 -> -0.22654594
A16: 2018 | B16: 15346.879 | C16: =B16/B15-1 -> 0.15080665 | E16: =B16/B15-1 -> 0.15080665
A17: 2019 | B17: 17502.756 | C17: =B17/B16-1 -> 0.14047658 | E17: =B17/B16-1 -> 0.14047658
A18: 2020 | B18: 2519.118 | C18: =B18/B17-1 -> -0.85607307 | E18: =B18/B17-1 -> -0.85607307
A19: 2021 | B19: 967.003 | C19: =B19/B18-1 -> -0.6161343 | E19: =B19/B18-1 -> -0.6161343
A20: 2022 | B20: =C177/1000 -> 3198.017 | C20: =B20/B19-1 -> 2.3071428 | E20: =B20/B19-1 -> 2.3071428
A21: 2023 | B21: =(J138/1000) -> 11031.665 | C21: =B21/B20-1 -> 2.4495329
A22: 2024 | B22: =SUM(J139:J150)/1000 -> 16369.609 | C22: =B22/B21-1 -> 0.48387474
A23: 2025 (Oct) | B23: =(SUM(J152:J163)/1000) -> 15821.331 | C23: =B23/B22-1 -> -0.033493653
A24: Source: VisitKorea Data Lab
A26: In 2025, South Korea’s inbound tourism continued its recovery trajectory, supported by the normalization of international travel, expanded flight capacity, and the gradual return of key source markets. While Chinese visitor volumes recovered at a slower pace compared to pre-pandemic levels, growth was led by travelers from Japan, Southeast Asia, and North America, driven by favorable exchange rates, improved air connectivity, and sustained interest in Korean culture and entertainment. The rebound in inbound tourism supported improvements in hotel occupancy and RevPAR, particularly in Seoul and major metropolitan areas, with demand concentrated in leisure-oriented districts and well-connected urban locations. Looking ahead, inbound tourism is expected to remain on a gradual growth path, underpinned by visa facilitation measures, major international events, and continued expansion of low-cost and full-service airline routes.
A42: Table: Number of Tourist Arrivals (Monthly)
C43: Tourist Arrivals | J43: Tourist Arrivals
A44: Year | B44: Month | C44: Total visitor | D44: YoY Change in All Visitors | H44: Year | I44: Month | J44: Total visitor | K44: YoY Change in All Visitors
A46: 2009 | B46: 1 | C46: 607659 | H46: 2015 | I46: 1 | J46: 917054
B47: 2 | C47: 666928 | I47: 2 | J47: 1050706
B48: 3 | C48: 724117 | I48: 3 | J48: 1238144
B49: 4 | C49: 688586 | I49: 4 | J49: 1384567
B50: 5 | C50: 574559 | I50: 5 | J50: 1334212
B51: 6 | C51: 530506 | I51: 6 | J51: 750925
B52: 7 | C52: 609258 | I52: 7 | J52: 629737
B53: 8 | C53: 695880 | I53: 8 | J53: 1069314
B54: 9 | C54: 678691 | I54: 9 | J54: 1206764
B55: 10 | C55: 737373 | I55: 10 | J55: 1383704
B56: 11 | C56: 642672 | I56: 11 | J56: 1150074
B57: 12 | C57: 661304 | I57: 12 | J57: 1116450
B58: Total | C58: 7817533 | D58: - | I58: Total | J58: 13231651 | K58: =(J58-C123)/C123 -> -0.068293061
A59: 2010 | B59: 1 | C59: 569453 | H59: 2016 | I59: 1 | J59: 1077431
B60: 2 | C60: 638911 | I60: 2 | J60: 1126250
B61: 3 | C61: 769894 | I61: 3 | J61: 1389399
B62: 4 | C62: 730265 | I62: 4 | J62: 1469674
B63: 5 | C63: 729450 | I63: 5 | J63: 1492680
B64: 6 | C64: 718440 | I64: 6 | J64: 1554413
B65: 7 | C65: 754672 | I65: 7 | J65: 1703495
B66: 8 | C66: 833693 | I66: 8 | J66: 1664303
B67: 9 | C67: 764693 | I67: 9 | J67: 1523928
B68: 10 | C68: 872550 | I68: 10 | J68: 1587797
B69: 11 | C69: 738271 | I69: 11 | J69: 1309055
B70: 12 | C70: 677366 | I70: 12 | J70: 1343398
B71: Total | C71: 8797658 | D71: =(C71-C58)/C58 -> 0.12537523 | I71: Total | J71: 17241823 | K71: =(J71-J58)/J58 -> 0.3030742
A72: 2011 | B72: 1 | C72: 586152 | H72: 2017 | I72: 1 | J72: 1220695
B73: 2 | C73: 667089 | I73: 2 | J73: 1252080
B74: 3 | C74: 781286 | I74: 3 | J74: 1233640
B75: 4 | C75: 754458 | I75: 4 | J75: 1075899
B76: 5 | C76: 743464 | I76: 5 | J76: 977889
B77: 6 | C77: 795850 | I77: 6 | J77: 991802
B78: 7 | C78: 881809 | I78: 7 | J78: 1008671
B79: 8 | C79: 977296 | I79: 8 | J79: 1103506
B80: 9 | C80: 906813 | I80: 9 | J80: 1078653
B81: 10 | C81: 988320 | I81: 10 | J81: 1165638
B82: 11 | C82: 869876 | I82: 11 | J82: 1093217
B83: 12 | C83: 842383 | I83: 12 | J83: 1134068
B84: Total | C84: 9794796 | D84: =(C84-C71)/C71 -> 0.1133413 | I84: Total | J84: 13335758 | K84: =(J84-J71)/J71 -> -0.22654594
A85: 2012 | B85: 1 | C85: 753793 | H85: 2018 | I85: 1 | J85: 956036
B86: 2 | C86: 810967 | I86: 2 | J86: 1045415
B87: 3 | C87: 916357 | I87: 3 | J87: 1366100
B88: 4 | C88: 967593 | I88: 4 | J88: 1331709
B89: 5 | C89: 942602 | I89: 5 | J89: 1238021 | U89: =SUM(J139:J143) -> 6284113
B90: 6 | C90: 946333 | I90: 6 | J90: 1282093
B91: 7 | C91: 1009225 | I91: 7 | J91: 1254833
B92: 8 | C92: 1103311 | I92: 8 | J92: 1391727
B93: 9 | C93: 986961 | I93: 9 | J93: 1278604
B94: 10 | C94: 1025705 | I94: 10 | J94: 1527832
B95: 11 | C95: 842189 | I95: 11 | J95: 1350390
B96: 12 | C96: 834992 | I96: 12 | J96: 1324119
B97: Total | C97: 11140028 | D97: =(C97-C84)/C84 -> 0.1373415 | I97: Total | J97: 15346879 | K97: =(J97-J84)/J84 -> 0.15080665
A98: 2013 | B98: 1 | C98: 753655
B99: 2 | C99: 815037
B100: 3 | C100: 1010809
B101: 4 | C101: 972164
B102: 5 | C102: 919355 | U102: =SUM(J152:J156) -> 7206747 | V102: =U102/U89-1 -> 0.14682008
B103: 6 | C103: 1059082
B104: 7 | C104: 1205152
B105: 8 | C105: 1358909
B106: 9 | C106: 1156913
B107: 10 | C107: 1087974
B108: 11 | C108: 907901
B109: 12 | C109: 928599
B110: Total | C110: 12175550 | D110: =(C110-C97)/C97 -> 0.092955063
A111: 2014 | B111: 1 | C111: 842671
B112: 2 | C112: 886026
B113: 3 | C113: 1132155
B114: 4 | C114: 1251374
B115: 5 | C115: 1239606
B116: 6 | C116: 1273627
B117: 7 | C117: 1354753
B118: 8 | C118: 1454078
B119: 9 | C119: 1245777
...

Sheet Retail Sales Trend
A1: Seoul Retail Sales Trend
A3: Table: Retail Sales & Proportion of Online Sales
B4: FOREX: respective KRW/USD by month used for caluation
A5: Month-Year | B5: Monthly Total Retail Sales ($ Billion) | C5: Monthly Online Sales ($ Billion) | D5: Monthly Physical Sales ($ Billion) | E5: Proportion of Online Retail Sales | G5: MoM | H5: YoY
B6: Retail Total | C6: Online Retail Sales | D6: Physical Retail Sales | E6: % of Online Retail Sales
A7: 43739 | B7: 30.392561 | C7: 8.9772974 | D7: =B7-C7 -> 21.415264 | E7: =C7/B7 -> 0.29537811
A8: 43770 | B8: 31.360099 | C8: 9.7126234 | D8: =B8-C8 -> 21.647475 | E8: =C8/B8 -> 0.30971278 | G8: =C8/C7-1 -> 0.081909502
A9: 43800 | B9: 31.80501 | C9: 9.6020858 | D9: =B9-C9 -> 22.202925 | E9: =C9/B9 -> 0.30190482 | G9: =C9/C8-1 -> -0.011380811
A10: 43831 | B10: 29.555722 | C10: 9.0506355 | D10: =B10-C10 -> 20.505087 | E10: =C10/B10 -> 0.30622278 | G10: =C10/C9-1 -> -0.057430268
A11: 43862 | B11: 25.859803 | C11: 8.8117285 | D11: =B11-C11 -> 17.048074 | E11: =C11/B11 -> 0.34075003 | G11: =C11/C10-1 -> -0.02639671
A12: 43891 | B12: 28.009406 | C12: 9.2667516 | D12: =B12-C12 -> 18.742655 | E12: =C12/B12 -> 0.33084427 | G12: =C12/C11-1 -> 0.051638356
A13: 43922 | B13: 28.203891 | C13: 8.8703686 | D13: =B13-C13 -> 19.333523 | E13: =C13/B13 -> 0.31450868 | G13: =C13/C12-1 -> -0.04277476
A14: 43952 | B14: 30.618291 | C14: 9.3542158 | D14: =B14-C14 -> 21.264075 | E14: =C14/B14 -> 0.30551071 | G14: =C14/C13-1 -> 0.054546458
A15: 43983 | B15: 30.322935 | C15: 9.2877826 | D15: =B15-C15 -> 21.035153 | E15: =C15/B15 -> 0.30629563 | G15: =C15/C14-1 -> -0.0071019491
A16: 44013 | B16: 28.978743 | C16: 9.5440573 | D16: =B16-C16 -> 19.434685 | E16: =C16/B16 -> 0.32934684 | G16: =C16/C15-1 -> 0.027592665
A17: 44044 | B17: 29.342496 | C17: 9.9497989 | D17: =B17-C17 -> 19.392697 | E17: =C17/B17 -> 0.33909177 | G17: =C17/C16-1 -> 0.042512489
A18: 44075 | B18: 31.413343 | C18: 10.237086 | D18: =B18-C18 -> 21.176257 | E18: =C18/B18 -> 0.32588336 | G18: =C18/C17-1 -> 0.028873642
A19: 44105 | B19: 30.548737 | C19: 10.275361 | D19: =B19-C19 -> 20.273375 | E19: =C19/B19 -> 0.33635961 | G19: =C19/C18-1 -> 0.0037388833
A20: 44136 | B20: 31.100866 | C20: 11.125837 | D20: =B20-C20 -> 19.975028 | E20: =C20/B20 -> 0.35773401 | G20: =C20/C19-1 -> 0.0827685 | H20: =C20/C7-1 -> 0.23933037
A21: 44166 | B21: 31.329763 | C21: 11.839817 | D21: =B21-C21 -> 19.489946 | E21: =C21/B21 -> 0.37790956 | G21: =C21/C20-1 -> 0.064173104 | H21: =C21/C8-1 -> 0.21901328
A22: 44197 | B22: 29.797374 | C22: 11.092331 | D22: =B22-C22 -> 18.705043 | E22: =C22/B22 -> 0.37225867 | G22: =C22/C21-1 -> -0.063133223 | H22: =C22/C9-1 -> 0.15520016
A23: 44228 | B23: 28.435613 | C23: 10.15084 | D23: =B23-C23 -> 18.284773 | E23: =C23/B23 -> 0.35697629 | G23: =C23/C22-1 -> -0.084877694 | H23: =C23/C10-1 -> 0.12156098
A24: 44256 | B24: 31.951087 | C24: 11.597094 | D24: =B24-C24 -> 20.353993 | E24: =C24/B24 -> 0.36296399 | G24: =C24/C23-1 -> 0.14247634 | H24: =C24/C11-1 -> 0.31609753
A25: 44287 | B25: 31.848787 | C25: 10.990535 | D25: =B25-C25 -> 20.858252 | E25: =C25/B25 -> 0.34508489 | G25: =C25/C24-1 -> -0.052302651 | H25: =C25/C12-1 -> 0.18601811
A26: 44317 | B26: 32.890612 | C26: 11.697276 | D26: =B26-C26 -> 21.193336 | E26: =C26/B26 -> 0.35564178 | G26: =C26/C25-1 -> 0.064304459 | H26: =C26/C13-1 -> 0.31869106
A27: 44348 | B27: 31.944905 | C27: 11.36299 | D27: =B27-C27 -> 20.581915 | E27: =C27/B27 -> 0.35570585 | G27: =C27/C26-1 -> -0.02857811 | H27: =C27/C14-1 -> 0.21474531
A28: 44378 | B28: 32.332824 | C28: 11.699274 | D28: =B28-C28 -> 20.63355 | E28: =C28/B28 -> 0.36183891 | G28: =C28/C27-1 -> 0.02959471 | H28: =C28/C15-1 -> 0.25964125
A29: 44409 | B29: 31.585139 | C29: 11.420135 | D29: =B29-C29 -> 20.165004 | E29: =C29/B29 -> 0.3615667 | G29: =C29/C28-1 -> -0.023859558 | H29: =C29/C16-1 -> 0.19657021
A30: 44440 | B30: 33.526114 | C30: 11.671983 | D30: =B30-C30 -> 21.854131 | E30: =C30/B30 -> 0.34814603 | G30: =C30/C29-1 -> 0.022053053 | H30: =C30/C17-1 -> 0.17308737
A31: 44470 | B31: 34.093825 | C31: 12.23674 | D31: =B31-C31 -> 21.857085 | E31: =C31/B31 -> 0.35891367 | G31: =C31/C30-1 -> 0.048385631 | H31: =C31/C18-1 -> 0.19533429
... A41: 44774 | B41: 34.629107 | C41: 13.246175 | D41: =B41-C41 -> 21.382932 | E41: =C41/B41 -> 0.38251564 | G41: =C41/C40-1 -> 0.040329273 | H41: =C41/C28-1 -> 0.13222198
A42: 44805 | B42: 34.473464 | C42: 12.732676 | D42: =B42-C42 -> 21.740788 | E42: =C42/B42 -> 0.36934715 | G42: =C42/C41-1 -> -0.038765873 | H42: =C42/C29-1 -> 0.11493219 | J42: In October 2025, South Korea’s online retail sales totaled USD 15.96 billion, accounting for 40.8% of total retail sales (USD 39.10 billion), while physical retail sales reached USD 23.14 billion. On a month-on-month basis, online sales declined by 6.3%, while year-on-year growth remained positive at 8.7%. Overall, the data indicates that online penetration remains structurally high, despite short-term volatility in monthly sales performance. Year-on-year growth was driven by food services, automobiles and auto-related products, and food and beverages, while culture and leisure services declined. Specialized online malls outperformed general malls in annual growth, and omnichannel platforms recorded stronger year-on-year growth than online-only platforms, despite month-on-month declines across all segments.
A43: 44835 | B43: 33.715313 | C43: 12.435231 | D43: =B43-C43 -> 21.280082 | E43: =C43/B43 -> 0.36883036 | G43: =C43/C42-1 -> -0.02336071 | H43: =C43/C30-1 -> 0.065391452
A44: 44866 | B44: 35.934167 | C44: 13.739839 | D44: 22.194327 | E44: =C44/B44 -> 0.38236143 | G44: =C44/C43-1 -> 0.10491223 | H44: =C44/C31-1 -> 0.12283497
A45: 44896 | B45: 41.84276 | C45: 14.578981 | D45: 27.263779 | E45: =C45/B45 -> 0.34842303 | G45: =C45/C44-1 -> 0.061073636 | H45: =C45/C32-1 -> 0.15459856
A46: 44927 | B46: 42.608848 | C46: 14.38913 | D46: 28.219718 | E46: =C46/B46 -> 0.33770287 | G46: =C46/C45-1 -> -0.01302222 | H46: =C46/C33-1 -> 0.080654994
A47: 44958 | B47: 38.019641 | C47: 13.411078 | D47: 24.608564 | E47: =C47/B47 -> 0.35274078 | G47: =C47/C46-1 -> -0.067971633 | H47: =C47/C34-1 -> 0.088400752
A48: 44986 | B48: 41.617458 | C48: 14.289077 | D48: 27.32838 | E48: =C48/B48 -> 0.34334335 | G48: =C48/C47-1 -> 0.065468234 | H48: =C48/C35-1 -> 0.24014306
A49: 45017 | B49: 39.759989 | C49: 13.531354 | D49: 26.228635 | E49: =C49/B49 -> 0.34032591 | G49: =C49/C48-1 -> -0.053028131 | H49: =C49/C36-1 -> 0.050548364
A50: 45047 | B50: 41.189318 | C50: 14.491768 | D50: 26.69755 | E50: =C50/B50 -> 0.35183316 | G50: =C50/C49-1 -> 0.070976898 | H50: =C50/C37-1 -> 0.17730126
A51: 45078 | B51: 40.67695 | C51: 14.244205 | D51: 26.432745 | E51: =C51/B51 -> 0.35017878 | G51: =C51/C50-1 -> -0.017083003 | H51: =C51/C38-1 -> 0.098370368
A52: 45108 | B52: 39.951624 | C52: 14.697082 | D52: 25.254542 | E52: =C52/B52 -> 0.36787196 | G52: =C52/C51-1 -> 0.031793798 | H52: =C52/C39-1 -> 0.17325938
A53: 45139 | B53: 39.088809 | C53: 14.468808 | D53: 24.620001 | E53: =C53/B53 -> 0.37015218 | G53: =C53/C52-1 -> -0.015531963 | H53: =C53/C40-1 -> 0.13635249
A54: 45170 | B54: 40.9525 | C54: 14.307996 | D54: 26.644504 | E54: =C54/B54 -> 0.34938028 | G54: =C54/C53-1 -> -0.0111144 | H54: =C54/C41-1 -> 0.08016053
A55: 45200 | B55: 39.872399 | C55: 14.874266 | D55: 24.998132 | E55: =C55/B55 -> 0.37304669 | G55: =C55/C54-1 -> 0.039577229 | H55: =C55/C42-1 -> 0.16819645
... A74: 45778 | B74: 39.605171 | C74: 16.12559 | D74: 23.479581 | E74: =C74/B74 -> 0.4071587 | G74: =C74/C73-1 -> 0.070739601 | H74: =C74/C61-1 -> 0.11383897
A75: 45809 | B75: 39.068239 | C75: 16.084628 | D75: 22.983611 | E75: 0.412 | G75: =C75/C74-1 -> -0.0025401973 | H75: =C75/C62-1 -> 0.053513196
A76: 45839 | B76: 39.692608 | C76: 16.828387 | D76: 22.864222 | E76: 0.424 | G76: =C76/C75-1 -> 0.046240356 | H76: =C76/C63-1 -> 0.15827318
A77: 45870 | B77: 38.191499 | C77: 16.077658 | D77: 22.113841 | E77: 0.421 | G77: =C77/C76-1 -> -0.044610865 | H77: =C77/C64-1 -> 0.11677861
A78: 45901 | B78: 40.801516 | C78: 17.027518 | D78: 23.773998 | E78: 0.417 | G78: =C78/C77-1 -> 0.059079494 | H78: =C78/C65-1 -> 0.17783147
A79: 45931 | B79: 39.096718 | C79: 15.95543 | D79: 23.141288 | E79: 0.408 | G79: =C79/C78-1 -> -0.062962062 | H79: =C79/C66-1 -> 0.086586081
A81: Source: KOSIS

Sheet Retail Sales Index
A1: Seoul Retail Sales Index
A3: Table: Retail Sales Index
A4: Month-Year | B4: Retail Sales Index - YoY % change
A5: 44409 | B5: 0.173
A6: 44440 | B6: 0.236
A7: 44470 | B7: 0.274
A8: 44501 | B8: 0.285
A9: 44531 | B9: 0.313
A10: 44562 | B10: 0.221
A11: 44593 | B11: 0.112
A12: 44621 | B12: 0.275
A13: 44652 | B13: 0.29 | D13: Consumer spending has shown a gradual improvement, supported by accumulated policy rate cuts and government stimulus measures. Although retail sales growth moderated in October due to the delayed Chuseok holiday, average growth over September–October remained positive. Seasonally adjusted retail sales rose month-on-month, driven by consumption stimulus policies, while increased activity in accommodation, food services, and leisure sectors indicated a recovery in services consumption. With consumer sentiment remaining elevated, the improving consumption trend is expected to continue in the near term despite short-term fluctuations.
A14: 44682 | B14: 0.365
A15: 44713 | B15: 0.32
A16: 44743 | B16: 0.347
A17: 44774 | B17: 0.346
A18: 44805 | B18: 0.35
A19: 44835 | B19: 0.384
A20: 44866 | B20: 0.356
A21: 44896 | B21: 0.396
A22: 44927 | B22: 0.331
A23: 44958 | B23: 0.32555673
A24: 44986 | B24: 0.219
A25: 45017 | B25: 0.183
... A46: 45658 | B46: 0.253
A47: 45689 | B47: =B46+'[22]Macro_Key Financials'!$DU$794 -> 0.27242568
A48: 45717 | B48: =B47+'[22]Macro_Key Financials'!$DU$794 -> 0.29185135
A49: 45748 | B49: =B48+'[22]Macro_Key Financials'!$DV$794 -> 0.30225898
A50: 45778 | B50: =B49+'[22]Macro_Key Financials'!$DW$794 -> 0.30893121
A51: 45809 | B51: =B50+'[22]Macro_Key Financials'!$DX$794 -> 0.32458338
A52: 45839 | B52: =B51+'[22]Macro_Key Financials'!$DY$794 -> 0.36465307
A53: 45870 | B53: =B52+'[22]Macro_Key Financials'!$DZ$794 -> 0.37951321
A54: 45901 | B54: =B53+'[22]Macro_Key Financials'!$EA$794 -> 0.42058614
A55: 45931 | B55: =B54+'[22]Macro_Key Financials'!$EB$794 -> 0.44585994
A56: Source: KOSIS

Sheet Unemployment Rate
A1: Seoul Unemployment Rate
A3: Table: Unemployment Rate
A4: Year | B4: Unemployment Rate | C4: QoQ | E4: Employment conditions in South Korea continue to face delays in recovery due to prolonged weakness in the construction and manufacturing sectors. While overall job growth moderated in October, with the increase in employment narrowing from 312,000 to 193,000 month-on-month following a normalization of temporary daily employment, labor market conditions remain uneven. Employment in manufacturing and construction continued to decline, while growth in the services sector moderated as strong gains in health and welfare eased and employment in professional and scientific services turned negative. Nevertheless, employment trends in consumption-related sectors—including wholesale and retail, accommodation and food services, and arts and entertainment—showed signs of stabilization, reflecting a gradual improvement in consumer-driven demand. Overall employment and labor force participation rates remain below early-year levels, indicating a delayed labor market recovery. Employment rates declined among workers in their 20s and 30s, while those in their 40s and 50s continued to improve, and the unemployment rate remained broadly stable at 2.6%.
A5: 2006 | B5: 0.035
A6: 2007 | B6: 0.032 | C6: =B6-B5 -> -0.003
A7: 2008 | B7: 0.032 | C7: =B7-B6 -> 0
A8: 2009 | B8: 0.036 | C8: =B8-B7 -> 0.004
A9: 2010 | B9: 0.037 | C9: =B9-B8 -> 0.001
A10: 2011 | B10: 0.034 | C10: =B10-B9 -> -0.003
A11: 2012 | B11: 0.032 | C11: =B11-B10 -> -0.002
A12: 2013 | B12: 0.031 | C12: =B12-B11 -> -0.001
A13: 2014 | B13: 0.035 | C13: =B13-B12 -> 0.004
A14: 2015 | B14: 0.036 | C14: =B14-B13 -> 0.001
A15: 2016 | B15: 0.037 | C15: =B15-B14 -> 0.001
A16: 2017 | B16: 0.037 | C16: =B16-B15 -> 0
A17: 2018 | B17: 0.038 | C17: =B17-B16 -> 0.001
... A22: 2023 | B22: 0.027 | C22: =B22-B21 -> -0.002
A23: 1Q 2024 | B23: 0.028 | C23: =B23-B22 -> 0.001
A24: 2Q 2024 | B24: 0.028 | C24: =B24-B23 -> 0
A25: 3Q 2024 | B25: 0.025 | C25: =B25-B24 -> -0.003
A26: 4Q 2024 | B26: 0.024 | C26: =B26-B25 -> -0.001
A27: 1Q 2025 | B27: 0.037 | C27: =B27-B26 -> 0.013
A28: 2Q 2025 | B28: =Headlines!L8 -> 0.033 | C28: =B28-B27 -> -0.004
A29: 3Q 2025 | B29: =Headlines!M8 -> 0.025 | C29: =B29-B28 -> -0.008
A30: 4Q 2025 | B30: 0.026 | C30: =B30-B29 -> 0.001
A31: Source: KOSIS, National Assembly

Sheet Office Market>>

Sheet Office Outlook
A1: Seoul Office Outlook
A2: Outlook | B2: The Seoul office market remains resilient entering year-end 2025, supported by firm rental growth, low vacancy, and the absence of new supply in the second half of the year. However, the outlook is increasingly shaped by the contrast between tight near-term market conditions and a substantial supply pipeline from 2026 onward, which will be the key driver of market performance over the medium term. In 2025, new office supply was limited to approximately 28,437 pyeong, all delivered in the first half of the year. While Q4 2025 recorded negative net absorption, full-year absorption remained marginally positive, with the quarterly reversal reflecting year-end tenant consolidation rather than a structural weakening in demand. The ongoing Flight to Quality continues to support prime assets, sustaining low vacancy in the GBD and YBD, while the CBD faces relatively higher vacancy risk due to tenant relocations and future supply exposure. From 2026, the market will enter a period of elevated new supply, concentrated in the CBD and GBD and peaking in 2028–2029, which is expected to place upward pressure on vacancy rates and moderate rental growth. Despite these risks, investment demand remains solid, as evidenced by increased transaction activity in Q4 2025 and the growing use of share-deal structures, while cap rates have remained broadly stable. Overall, near-term rental conditions are expected to remain supportive, though medium-term performance will increasingly depend on the market’s ability to absorb the upcoming supply wave.
A8: Source: Colliers Database

Sheet Existing Supply
A1: Seoul Grade A Office Building Existing Stock
A3: Table: Distribution of existing Grade A Office Building stock by end of current quarter
A4: Grade A Office Building Stock | B4: Net (pyeong) | C4: Gross (x1.25) | D4: Completions (New Supply) | E4: Check
A5: Grade A Office Building Stock at 2021 Q4 (Net) | B5: 2701427.2 | C5: =Table24[[#This Row],[Net (pyeong)]]*1.25 -> 3376784
A6: Grade A Office Building Stock at 2022 Q4 (Net) | B6: 2701427.2 | C6: =Table24[[#This Row],[Net (pyeong)]]*1.25 -> 3376784 | D6: =Table24[[#This Row],[Net (pyeong)]]-B5 -> 0
A7: Grade A Office Building Stock at 2023 Q1 (Net) | B7: 2687094.7 | C7: =Table24[[#This Row],[Net (pyeong)]]*1.25 -> 3358868.3 | D7: =Table24[[#This Row],[Net (pyeong)]]-B6 -> -14332.494
A8: Grade A Office Building Stock at 2023 Q2 (Net) | B8: 2687094.7 | C8: =Table24[[#This Row],[Net (pyeong)]]*1.25 -> 3358868.3 | D8: =Table24[[#This Row],[Net (pyeong)]]-B7 -> 0
A9: Grade A Office Building Stock at 2023 Q3 (Net) | B9: 2704553.8 | C9: =Table24[[#This Row],[Net (pyeong)]]*1.25 -> 3380692.2 | D9: =Table24[[#This Row],[Net (pyeong)]]-B8 -> 17459.09
A10: Grade A Office Building Stock at 2023 Q4 (Net) | B10: =B11-'Future Supply'!H26*1000000 -> 2704553.8 | C10: =Table24[[#This Row],[Net (pyeong)]]*1.25 -> 3380692.2 | D10: =Table24[[#This Row],[Net (pyeong)]]-B9 -> 0
A11: Grade A Office Building Stock at 2024 Q1 (Net) | B11: =B12-'Future Supply'!H27*1000000 -> 2747415.3 | C11: =Table24[[#This Row],[Net (pyeong)]]*1.25 -> 3434269.1 | D11: =Table24[[#This Row],[Net (pyeong)]]-B10 -> 42861.521
A12: Grade A Office Building Stock at 2024 Q2 (Net) | B12: 2760162.2 | C12: 3450366.4 | D12: =Table24[[#This Row],[Net (pyeong)]]-B11 -> 12746.886
A13: Grade A Office Building Stock at 2024 Q3 (Net) | B13: =B14-('Future Supply'!H28*1000000) -> 2760162.2 | C13: =Table24[[#This Row],[Net (pyeong)]]*1.25 -> 3450202.7 | D13: =Table24[[#This Row],[Net (pyeong)]]-B12 -> 0
A14: Grade A Office Building Stock at 2024 Q4 (Net) | B14: 2768343.6 | C14: 3460429.5 | D14: =Table24[[#This Row],[Net (pyeong)]]-B13 -> 8181.3969
A15: Grade A Office Building Stock at 2025 Q1 (Net) | B15: 2780097.8 | C15: =Table24[[#This Row],[Net (pyeong)]]*1.25 -> 3475122.2 | D15: =Table24[[#This Row],[Net (pyeong)]]-B14 -> 11754.218
A16: Grade A Office Building Stock at 2025 Q2 (Net) | B16: 2808534.5 | C16: 3510668.1 | D16: =Table24[[#This Row],[Net (pyeong)]]-B15 -> 28436.674
A17: Grade A Office Building Stock at 2025 Q3 (Net) | B17: =E27 -> 2808534.5 | C17: =Table24[[#This Row],[Net (pyeong)]]*1.25 -> 3510668.1 | D17: =Table24[[#This Row],[Net (pyeong)]]-B16 -> 0
A18: Grade A Office Building Stock at 2025 Q4 (Net) | B18: =E27 -> 2808534.5 | C18: =Table24[[#This Row],[Net (pyeong)]]*1.25 -> 3510668.1 | D18: =Table24[[#This Row],[Net (pyeong)]]-B17 -> 0 | E18: =Table24[[#This Row],[Completions (New Supply)]]=D27 -> TRUE
A19: Source: Colliers Database
A21: Table: Distribution of Grade A Office Building existing stock by submarkets by end of current quarter
A23: Submarket | B23: Previous Quarter GFA (pyeong) | C23: Pecentage of Stock | D23: New Supply (pyeong) | E23: Current Quarter GFA (pyeong) | F23: Percentage of Stock
A24: CBD | B24: 1223518 | C24: =B24/$B$27 -> 0.43564285 | E24: =SUM(D24,B24) -> 1223518 | F24: =E24/$E$27 -> 0.43564285
A25: GBD | B25: 931242.62 | C25: =B25/$B$27 -> 0.331576 | E25: =SUM(D25,B25) -> 931242.62 | F25: =E25/$E$27 -> 0.331576
A26: YBD | B26: 653773.89 | C26: =B26/$B$27 -> 0.23278115 | E26: =SUM(D26,B26) -> 653773.89 | F26: =E26/$E$27 -> 0.23278115
A27: Total | B27: =SUM(B24:B26) -> 2808534.5 | C27: =SUM(C24:C26) -> 1 | D27: =SUM(D24:D26) -> 0 | E27: =SUM(E24:E26) -> 2808534.5 | F27: =SUM(F24:F26) -> 1 | H27: In 2025, all new office supply in Seoul was completed in the first half of the year, with no new office completions scheduled in the second half of year 2025. A total of 28,436.67 pyeong (GFA basis) of new office space was delivered during the year, comprising two projects in the CBD and one project in the GBD. | U27: =SUM('Future Supply'!H29:H31)*1000000 -> 28436.674
A28: Source: Colliers Database

Sheet Future Supply
A1: Seoul Future Supply
A3: Table: Future Supply (2024-2026) | E3: Table: Future Supply by Submarkets (2025-2032) | I3: Unit: pyeong | P3: Table: Future Supply Breakdown in next 5 years (2025-2030)
B4: GFA (Million pyeong) | C4: GFA (Million pyeong) including 2025 YTD | E4: Submarket | F4: 2025F | G4: 2026F | H4: 2027F | I4: 2028F | J4: 2029F | K4: 2030F | L4: 2031F | M4: 2032F | P4: Supply Breakdown (2025 -2030) | Q4: Area (Million pyeong) | R4: % of Total Supply
A5: =F4 -> 2025F | B5: =SUM(F5:F7)/1000000 -> 0 | C5: =B5+SUM(H26:H30) -> 0.071972731 | E5: CBD | F5: =1000000*SUMIFS($H$36:$H$70,$G$36:$G$70,$E5,$A$36:$A$70,LEFT(F$4,4)) -> 0 | G5: =1000000*SUMIFS($H$36:$H$70,$G$36:$G$70,$E5,$A$36:$A$70,LEFT(G$4,4)) -> 89805.21 | H5: =1000000*SUMIFS($H$36:$H$70,$G$36:$G$70,$E5,$A$36:$A$70,LEFT(H$4,4)) -> 86697.826 | I5: =1000000*SUMIFS($H$36:$H$70,$G$36:$G$70,$E5,$A$36:$A$70,LEFT(I$4,4)) -> 177686.55 | J5: =1000000*SUMIFS($H$36:$H$70,$G$36:$G$70,$E5,$A$36:$A$70,LEFT(J$4,4)) -> 318098.3 | K5: =1000000*SUMIFS($H$36:$H$70,$G$36:$G$70,$E5,$A$36:$A$70,LEFT(K$4,4)) -> 40528.345 | L5: =1000000*SUMIFS($H$36:$H$70,$G$36:$G$70,$E5,$A$36:$A$70,LEFT(L$4,4)) -> 66493.947 | M5: =1000000*SUMIFS($H$36:$H$70,$G$36:$G$70,$E5,$A$36:$A$70,LEFT(M$4,4)) -> 0 | P5: CBD | Q5: =(SUM(F5:K5)/1000000) -> 0.71281624 | R5: =Q5/$Q$8 -> 0.79758109
A6: =G4 -> 2026F | B6: =SUM(G5:G7)/1000000 -> 0.08980521 | C6: =C5+B6 -> 0.16177794 | E6: GBD | F6: =1000000*SUMIFS($H$36:$H$70,$G$36:$G$70,$E6,$A$36:$A$70,LEFT(F$4,4)) -> 0 | G6: =1000000*SUMIFS($H$36:$H$70,$G$36:$G$70,$E6,$A$36:$A$70,LEFT(G$4,4)) -> 0 | H6: =1000000*SUMIFS($H$36:$H$70,$G$36:$G$70,$E6,$A$36:$A$70,LEFT(H$4,4)) -> 0 | I6: =1000000*SUMIFS($H$36:$H$70,$G$36:$G$70,$E6,$A$36:$A$70,LEFT(I$4,4)) -> 115248.26 | J6: =1000000*SUMIFS($H$36:$H$70,$G$36:$G$70,$E6,$A$36:$A$70,LEFT(J$4,4)) -> 0 | K6: =1000000*SUMIFS($H$36:$H$70,$G$36:$G$70,$E6,$A$36:$A$70,LEFT(K$4,4)) -> 40282.412 | L6: =1000000*SUMIFS($H$36:$H$70,$G$36:$G$70,$E6,$A$36:$A$70,LEFT(L$4,4)) -> 280988.32 | M6: =1000000*SUMIFS($H$36:$H$70,$G$36:$G$70,$E6,$A$36:$A$70,LEFT(M$4,4)) -> 0 | P6: GBD | Q6: =(SUM(F6:K6)/1000000) -> 0.15553068 | R6: =Q6/$Q$8 -> 0.17402568
A7: =H4 -> 2027F | B7: =SUM(H5:H7)/1000000 -> 0.086697826 | C7: =C6+B7 -> 0.24847577 | E7: YBD | F7: =1000000*SUMIFS($H$36:$H$70,$G$36:$G$70,$E7,$A$36:$A$70,LEFT(F$4,4)) -> 0 | G7: =1000000*SUMIFS($H$36:$H$70,$G$36:$G$70,$E7,$A$36:$A$70,LEFT(G$4,4)) -> 0 | H7: =1000000*SUMIFS($H$36:$H$70,$G$36:$G$70,$E7,$A$36:$A$70,LEFT(H$4,4)) -> 0 | I7: =1000000*SUMIFS($H$36:$H$70,$G$36:$G$70,$E7,$A$36:$A$70,LEFT(I$4,4)) -> 25375.678 | J7: =1000000*SUMIFS($H$36:$H$70,$G$36:$G$70,$E7,$A$36:$A$70,LEFT(J$4,4)) -> 0 | K7: =1000000*SUMIFS($H$36:$H$70,$G$36:$G$70,$E7,$A$36:$A$70,LEFT(K$4,4)) -> 0 | L7: =1000000*SUMIFS($H$36:$H$70,$G$36:$G$70,$E7,$A$36:$A$70,LEFT(L$4,4)) -> 24897.565 | M7: =1000000*SUMIFS($H$36:$H$70,$G$36:$G$70,$E7,$A$36:$A$70,LEFT(M$4,4)) -> 25000 | P7: YBD | Q7: =(SUM(F7:K7)/1000000) -> 0.025375678 | R7: =Q7/$Q$8 -> 0.028393238
A8: =I4 -> 2028F | B8: =SUM(I5:I7)/1000000 -> 0.3183105 | C8: =C7+B8 -> 0.56678626 | D8: =B11=I70 -> FALSE | E8: Overall | F8: =SUM(F5:F7) -> 0 | G8: =SUM(G5:G7) -> 89805.21 | H8: =SUM(H5:H7) -> 86697.826 | I8: =SUM(I5:I7) -> 318310.5 | J8: =SUM(J5:J7) -> 318098.3 | K8: =SUM(K5:K7) -> 80810.758 | L8: =SUM(L5:L7) -> 372379.83 | M8: =SUM(M5:M7) -> 25000 | P8: Total | Q8: =SUM(Q5:Q7) -> 0.89372259 | R8: =SUM(R5:R7) -> 1
A9: =J4 -> 2029F | B9: =SUM(J5:J7)/1000000 -> 0.3180983 | C9: =C8+B9 -> 0.88488457 | E9: Source: Colliers Database | P9: Source: Colliers International
A10: =K4 -> 2030F | B10: =SUM(K5:K7)/1000000 -> 0.080810758 | C10: =C9+B10 -> 0.96569532 | E10: Table: Future Supply by Submarkets by area (2025-2032)
A11: TOTAL | B11: =SUM(B5:B10) -> 0.89372259 | E11: Submarket | F11: 2025F | G11: 2026F | H11: 2027F | I11: 2028F | J11: 2029F | K11: 2030F | L11: 2031F | M11: 2032F | P11: Table: Future Supply Breakdown in next 3 years (2026-2028)
A12: Source: Colliers Database | E12: CBD | F12: =IFERROR(F5/F$8,) -> 0 | G12: =G5/G$8 -> 1 | H12: =H5/H$8 -> 1 | I12: =I5/I$8 -> 0.5582177 | J12: =J5/J$8 -> 1 | K12: =K5/K$8 -> 0.50152166 | L12: =L5/L$8 -> 0.17856485 | M12: =M5/M$8 -> 0 | P12: Supply Breakdown (2026 - 2028) | Q12: Area (Million pyeong) | R12: % of Total Supply
E13: GBD | F13: =IFERROR(F6/F$8,) -> 0 | G13: =G6/G$8 -> 0 | H13: =H6/H$8 -> 0 | I13: =I6/I$8 -> 0.36206241 | J13: =J6/J$8 -> 0 | K13: =K6/K$8 -> 0.49847834 | L13: =L6/L$8 -> 0.75457448 | M13: =M6/M$8 -> 0 | P13: CBD | Q13: {=SUM(G5:I5/1000000)} -> 0.35418959 | R13: =Q13/$Q$16 -> 0.71580417
E14: YBD | F14: =IFERROR(F7/F$8,) -> 0 | G14: =G7/G$8 -> 0 | H14: =H7/H$8 -> 0 | I14: =I7/I$8 -> 0.079719892 | J14: =J7/J$8 -> 0 | K14: =K7/K$8 -> 0 | L14: =L7/L$8 -> 0.06686067 | M14: =M7/M$8 -> 1 | P14: GBD | Q14: {=SUM(G6:I6/1000000)} -> 0.11524826 | R14: =Q14/$Q$16 -> 0.23291252
E15: Overall | F15: =IFERROR(F8/F$8,) -> 0 | G15: =G8/G$8 -> 1 | H15: =H8/H$8 -> 1 | I15: =I8/I$8 -> 1 | J15: =J8/J$8 -> 1 | K15: =K8/K$8 -> 1 | L15: =L8/L$8 -> 1 | M15: =M8/M$8 -> 1 | P15: YBD | Q15: {=SUM(G7:I7/1000000)} -> 0.025375678 | R15: =Q15/$Q$16 -> 0.051283315
P16: Total | Q16: =SUM(Q13:Q15) -> 0.49481353 | R16: =SUM(R13:R15) -> 1
E17: Table: Number of Future Projects by Submarkets (2025-2032) | P17: Source: Colliers International
E18: Submarket | F18: 2025F | G18: 2026F | H18: 2027F | I18: 2028F | J18: 2029F | K18: 2030F | L18: 2031F | M18: 2032F
E19: CBD | F19: =COUNTIFS($A$36:$A$69,LEFT(F$18,4),$G$36:$G$69,$E19) -> 0 | G19: =COUNTIFS($A$36:$A$69,LEFT(G$18,4),$G$36:$G$69,$E19) -> 4 | H19: =COUNTIFS($A$36:$A$69,LEFT(H$18,4),$G$36:$G$69,$E19) -> 6 | I19: =COUNTIFS($A$36:$A$69,LEFT(I$18,4),$G$36:$G$69,$E19) -> 6 | J19: =COUNTIFS($A$36:$A$69,LEFT(J$18,4),$G$36:$G$69,$E19) -> 6 | K19: =COUNTIFS($A$36:$A$69,LEFT(K$18,4),$G$36:$G$69,$E19) -> 1 | L19: =COUNTIFS($A$36:$A$69,LEFT(L$18,4),$G$36:$G$69,$E19) -> 3 | M19: =COUNTIFS($A$36:$A$69,LEFT(M$18,4),$G$36:$G$69,$E19) -> 0
E20: GBD | F20: =COUNTIFS($A$36:$A$69,LEFT(F$18,4),$G$36:$G$69,$E20) -> 0 | G20: =COUNTIFS($A$36:$A$69,LEFT(G$18,4),$G$36:$G$69,$E20) -> 0 | H20: =COUNTIFS($A$36:$A$69,LEFT(H$18,4),$G$36:$G$69,$E20) -> 0 | I20: =COUNTIFS($A$36:$A$69,LEFT(I$18,4),$G$36:$G$69,$E20) -> 2 | J20: =COUNTIFS($A$36:$A$69,LEFT(J$18,4),$G$36:$G$69,$E20) -> 0 | K20: =COUNTIFS($A$36:$A$69,LEFT(K$18,4),$G$36:$G$69,$E20) -> 1 | L20: =COUNTIFS($A$36:$A$69,LEFT(L$18,4),$G$36:$G$69,$E20) -> 1 | M20: =COUNTIFS($A$36:$A$69,LEFT(M$18,4),$G$36:$G$69,$E20) -> 0
E21: YBD | F21: =COUNTIFS($A$36:$A$69,LEFT(F$18,4),$G$36:$G$69,$E21) -> 0 | G21: =COUNTIFS($A$36:$A$69,LEFT(G$18,4),$G$36:$G$69,$E21) -> 0 | H21: =COUNTIFS($A$36:$A$69,LEFT(H$18,4),$G$36:$G$69,$E21) -> 0 | I21: =COUNTIFS($A$36:$A$69,LEFT(I$18,4),$G$36:$G$69,$E21) -> 2 | J21: =COUNTIFS($A$36:$A$69,LEFT(J$18,4),$G$36:$G$69,$E21) -> 0 | K21: =COUNTIFS($A$36:$A$69,LEFT(K$18,4),$G$36:$G$69,$E21) -> 0 | L21: =COUNTIFS($A$36:$A$69,LEFT(L$18,4),$G$36:$G$69,$E21) -> 1 | M21: =COUNTIFS($A$36:$A$69,LEFT(M$18,4),$G$36:$G$69,$E21) -> 1
E22: Overall | F22: =SUM(F19:F21) -> 0 | G22: =SUM(G19:G21) -> 4 | H22: =SUM(H19:H21) -> 6 | I22: =SUM(I19:I21) -> 10 | J22: =SUM(J19:J21) -> 6 | K22: =SUM(K19:K21) -> 2 | L22: =SUM(L19:L21) -> 5 | M22: =SUM(M19:M21) -> 1
A24: Table: Completed Projects
A25: Year | B25: Quarter | C25: Status | D25: Project | E25: Developer | F25: Location | G25: Submarket | H25: GFA (Million pyeong)
A26: 2024 | B26: 1Q | C26: Completed | D26: TP Tower | E26: Samsung C&T | F26: Yeoido | G26: YBD | H26: 0.042861521 | J26: S
A27: 2024 | B27: 2Q | C27: Completed | D27: Meritz Bongrae | E27: Doosan Construction | F27: Bongrae | G27: CBD | H27: 0.012746886
A28: 2024 | B28: 4Q | C28: Completed | D28: Centrepoint Gangnam | E28: Mastern | F28: Gangnam | G28: GBD | H28: 0.0081813968
A29: 2025 | B29: 1Q | C29: Completed | D29: Jung-gu Cho-dong (Project 107) | E29: MPLUS AMC | F29: Junggu | G29: CBD | H29: ='Existing Supply'!D24/1000000 -> 0
A30: 2025 | B30: 2Q | C30: Completed | D30: Baekam Building (OPUS 459) | E30: Taeyoung Group | F30: Seocho | G30: GBD | H30: 0.0081829275
A31: 2025 | B31: 2Q | C31: Completed | D31: KT Gwanghwamun Bld (WEST) | E31: Gunwon Engineering | F31: Junggu | G31: CBD | H31: 0.020253747
A32: Source: Colliers Database
A34: Table: Proposed Projects Information (2026-2032)
A35: Year | B35: Quarter | C35: Status | D35: Proposed Project | E35: Developer | F35: Location | G35: Submarket | H35: Estimated GFA (Million pyeong) | I35: Remark (Changes) | P35: [Summary]
A36: 2026 | B36: 3Q | C36: U/C | D36: Gongpyeong District 15, 16 | E36: Hyundai Engineering | F36: Jongro-gu | G36: CBD | H36: 0.03509605 | P36: Between 2025 and 2032, Seoul’s major business districts are expected to see a substantial pipeline of new office supply, with notable concentration in the CBD and GBD. From 2026 onward, the CBD will lead with steady deliveries, accounting for over half of the new supply in most years and peaking at more than 318,000 pyeong in 2029. The GBD is also set to receive significant injections, particularly in 2028–2031 when more than 436,000 pyeong is forecast, reinforcing its role as a core office hub. The YBD pipeline remains limited, though it will see modest additions in 2028 and from 2031 onwards, including a 25,000-pyeong project in 2032.
A37: 2026 | B37: 3Q | C37: U/C | D37: Euljiro Central Office 3ga 12 District | E37: Eastern Development | F37: Jung-gu | G37: CBD | H37: =(41984*0.3025)/1000000 -> 0.01270016
A38: 2026 | B38: 4Q | C38: U/C | D38: Supyo City Environment Renovation Office Development Project | E38: n.a. | F38: Jung-gu | G38: CBD | H38: 0.032035
A39: 2026 | B39: 4Q | C39: U/C | D39: The 3rd Seoul City Hall | E39: Seoul Metropolitan Government | F39: Jung-gu | G39: CBD | H39: 0.009974 | I39: The Seoul City departments are currently residing in 'Seoul City Square Building' and will move into their new building after completion
A40: 2027 | B40: 1Q | C40: B/C | D40: Eulji Finance Center (Euljiro 3ga 1, 2 District) | E40: n.a. | F40: Jung-gu | G40: CBD | H40: 0.019659173
A41: 2027 | B41: 1Q | C41: B/C | D41: Euljiro 3ga 6 District | E41: n.a. | F41: Jung-gu | G41: CBD | H41: 0.015759506
A42: 2027 | B42: 2Q | C42: B/C | D42: Euljiro 3ga 12 District | E42: Euljiro 75 PFV | F42: Jung-gu | G42: CBD | H42: 0.013583
A43: 2027 | B43: 4Q | C43: B/C | D43: Euljiro 3ga 10 District | E43: n.a. | F43: Jung-gu | G43: CBD | H43: =9459.147775/1000000 -> 0.0094591478
A44: 2027 | B44: 4Q | C44: B/C | D44: Mugyo-Dadong District 31 (Burim Building) | E44: n.a. | F44: Jung-gu | G44: CBD | H44: =9098/1000000 -> 0.009098
A45: 2027 | B45: 4Q | C45: B/C | D45: Bongrae-dong 1ga (3 District) & Namdaemunro 5ga Development Project | E45: SK D&D | F45: Jung-gu | G45: CBD | H45: 0.019139
A46: 2028 | B46: 1Q | C46: U/C | D46: KDIC Seocho Development Project | E46: MDM, Shinhan, IGIS | F46: Seocho-gu | G46: GBD | H46: 0.105875
A47: 2028 | B47: 1Q | C47: B/C | D47: Kiwoom Finance Square Redevelopment | E47: Kiwoom | F47: Yeongdeungpo-gu | G47: YBD | H47: 0.014796648
A48: 2028 | B48: 2Q | C48: B/C | D48: Sewoon 3-8, 9, 10 Development | E48: n.a. | F48: Jung-gu | G48: CBD | H48: 0.065456934
A49: 2028 | B49: 4Q | C49: B/C | D49: Myeongdong Area District 1 (Yuanta Securities Building) | E49: n.a. | F49: Jung-gu | G49: CBD | H49: =13770.456425/1000000 -> 0.013770456
A50: 2028 | B50: 4Q | C50: B/C | D50: Seosomun 10 District | E50: JB Group | F50: Jung-gu | G50: CBD | H50: 0.010168235
A51: 2028 | B51: 4Q | C51: B/C | D51: Seosomun 11, 12 District | E51: Civic Center PFV | F51: Jung-gu | G51: CBD | H51: 0.030822935
A52: 2028 | B52: 4Q | C52: B/C | D52: Euljiro 3-ga District 9 | E52: n.a. | F52: Jung-gu | G52: CBD | H52: 0.008372
A53: 2028 | B53: 4Q | C53: B/C | D53: Yeoksam-dong Aster Site | E53: KT Estate, Lasalle | F53: Gangnam-gu | G53: GBD | H53: 0.009373265
A54: 2028 | B54: 4Q | C54: B/C | D54: Meritz Fire & Marine Insurance Yeouido Headquarters | E54: Shinyoung | F54: Yeongdeungpo-gu | G54: YBD | H54: 0.01057903
A55: 2028 | B55: 4Q | C55: B/C | D55: Seoul Station Seodaemun 1 District | E55: Samsung | F55: Jung-gu | G55: CBD | H55: 0.049095992
A56: 2029 | B56: 1Q | C56: B/C | D56: Millenium Hilton Hotel Development Project | E56: IGIS (YD427) | F56: Jung-gu | G56: CBD | H56: 0.08
A57: 2029 | B57: 1Q | C57: B/C | D57: North Seoul Station Bongraedong 2ga Development Project | E57: Hanhwa | F57: Jung-gu | G57: CBD | H57: 0.055417093
A58: 2029 | B58: 2Q | C58: B/C | D58: Metro Tower + Seoulro Tower Development Project | E58: IGIS (YD816) | F58: Jung-gu | G58: CBD | H58: 0.03900121 | Q58: 2030 YTD | R58: 2024 4Q | S58: 2024 4Q
A59: 2029 | B59: 4Q | C59: U/C | D59: Sewoon District 4 | E59: Seoul Housing (SH) | F59: Jongro-gu | G59: CBD | H59: =94531.25/1000000 -> 0.09453125 | I59: Postponed from Q4 2026; Office, Officetel, Hotel complex | P59: Office Supply | Q59: =I70 -> 1.2911024 | R59: 2.7683436 | S59: =Q59/R59 -> 0.46638085
A60: 2029 | B60: 4Q | C60: B/C | D60: Sewoon 6-3-3 Development | E60: Hanho Construction (Dblock Group) | F60: Jung-gu | G60: CBD | H60: =26189/1000000 -> 0.026189
A61: 2029 | B61: 4Q | C61: B/C | D61: Sewoon 6-4-22, 23 Development | E61: n.a. | F61: Jung-gu | G61: CBD | H61: =22959.75/1000000 -> 0.02295975
A62: 2030 | B62: 1Q | C62: B/C | D62: Sewoon District 5-1·3 (Daeshin) | E62: IGIS ( Sewoon 5 PFV) | F62: Jung-gu | G62: CBD | H62: 0.040528345 | I62: Office building (Forward purchased by Daeshin Securities)
A63: 2030 | B63: 4Q | C63: B/C | D63: Gangnam Le Méridien Site Mixed-Use | E63: Mastern No.116 Gangnam Premier Project Finance Investment | F63: Gangnam-gu | G63: GBD | H63: 0.040282412
A64: 2031 | B64: 3Q | C64: B/C | D64: Shinhan Financial Tower Headquarters | F64: Jongno-gu | G64: CBD | H64: 0.05219214
A65: 2031 | B65: 3Q | C65: B/C | D65: Gongpyeong District 3 (Former Hana Tour Headquarters) | F65: Jongno-gu | G65: CBD | H65: 0
A66: 2031 | B66: 4Q | C66: B/C | D66: Myeong-dong District 2 | F66: Jung-gu | G66: CBD | H66: 0.014301807
A67: 2031 | B67: 4Q | C67: B/C | D67: HMG Global Business Center | E67: Hyundai Motors Group | F67: Gangnam-gu | G67: GBD | H67: 0.28098832 | I67: Postponed from Q4 2029 to Q4 2031
A68: 2031 | B68: 4Q | C68: B/C | D68: Mirae Asset Securities Building (Woori Financial Group) | E68: DDIVC (NPS: 98%) | F68: Yeongdeungpo-gu | G68: YBD | H68: 0.024897565
A69: 2032 | B69: 4Q | C69: B/C | D69: Korea Fire Insurance Association Redevelopment | F69: Yeongdeungpo-gu | G69: YBD | H69: 0.025
G70: TOTAL | H70: =SUM(H36:H39) -> 0.08980521 | I70: =SUM(H36:H69) -> 1.2911024
A71: Source: Colliers International

Sheet Net Absorption
A1: Seoul Net Absorption
A3: Table: Overall Net Absorption | G3: [Overall summary]
A4: Year | B4: Yearly Net Absorption (pyeong) | C4: Quarter | D4: Quarterly Net Absorption (pyeong) | E4: Quarterly Net Absorption (sq. m.) | G4: In Q4 2025, Seoul’s office market recorded negative net absorption of 24,992 pyeong, partially offsetting the strong positive absorption achieved in Q2 and Q3. While 2025 year-to-date absorption remained marginally positive at 11,528 pyeong, the Q4 reversal reflects year-end lease rationalisation and selective tenant consolidation, rather than a broad-based weakening in demand. The quarterly volatility highlights an increasingly uneven absorption pattern, with occupier expansion remaining concentrated in specific sectors and locations, while some tenants deferred or adjusted space commitments toward year-end.
A5: 2019 | B5: =SUM(D5:D8) -> 91600.025 | C5: 1Q | D5: =SUM(C61,G61,K61) -> 24553.925 | E5: =Table41214[[#This Row],[Quarterly Net Absorption (pyeong)]]/0.3025 -> 81170
C6: 2Q | D6: =SUM(C62,G62,K62) -> 9204.47 | E6: =Table41214[[#This Row],[Quarterly Net Absorption (pyeong)]]/0.3025 -> 30428
C7: 3Q | D7: =SUM(C63,G63,K63) -> 50278.525 | E7: =Table41214[[#This Row],[Quarterly Net Absorption (pyeong)]]/0.3025 -> 166210
C8: 4Q | D8: =SUM(C64,G64,K64) -> 7563.105 | E8: =Table41214[[#This Row],[Quarterly Net Absorption (pyeong)]]/0.3025 -> 25002
A9: 2020 | B9: =SUM(D9:D12) -> 46861.485 | C9: 1Q | D9: =SUM(C65,G65,K65) -> 1201.53 | E9: =Table41214[[#This Row],[Quarterly Net Absorption (pyeong)]]/0.3025 -> 3972
C10: 2Q | D10: =SUM(C66,G66,K66) -> 12314.472 | E10: =Table41214[[#This Row],[Quarterly Net Absorption (pyeong)]]/0.3025 -> 40709
C11: 3Q | D11: =SUM(C67,G67,K67) -> 15210.305 | E11: =Table41214[[#This Row],[Quarterly Net Absorption (pyeong)]]/0.3025 -> 50282
C12: 4Q | D12: =SUM(C68,G68,K68) -> 18135.178 | E12: =Table41214[[#This Row],[Quarterly Net Absorption (pyeong)]]/0.3025 -> 59951
A13: 2021 | B13: =SUM(D13:D16) -> 150786.27 | C13: 1Q | D13: =SUM(C69,G69,K69) -> 38056.618 | E13: =Table41214[[#This Row],[Quarterly Net Absorption (pyeong)]]/0.3025 -> 125807
C14: 2Q | D14: =SUM(C70,G70,K70) -> 17006.247 | E14: =Table41214[[#This Row],[Quarterly Net Absorption (pyeong)]]/0.3025 -> 56219
C15: 3Q | D15: =SUM(C71,G71,K71) -> 43207.588 | E15: =Table41214[[#This Row],[Quarterly Net Absorption (pyeong)]]/0.3025 -> 142835
C16: 4Q | D16: =SUM(C72,G72,K72) -> 52515.815 | E16: =Table41214[[#This Row],[Quarterly Net Absorption (pyeong)]]/0.3025 -> 173606 | G16: [GBD - Projection]
A17: 2022 | B17: =SUM(D17:D20) -> 126882.72 | C17: 1Q | D17: =SUM(C73,G73,K73) -> 63809.652 | E17: =Table41214[[#This Row],[Quarterly Net Absorption (pyeong)]]/0.3025 -> 210941 | G17: Despite the negative citywide absorption in Q4, the GBD continued to demonstrate relative resilience, supported by strong tenant retention and structurally limited Grade A supply. Demand in the district remains underpinned by technology-, AI-, and data-driven occupiers, suggesting that the Q4 decline is largely attributable to CBD-led move-outs and timing effects, rather than a deterioration in GBD fundamentals. As such, the GBD is expected to maintain tight vacancy conditions relative to other submarkets heading into 2026.
C18: 2Q | D18: =SUM(C74,G74,K74) -> 21129.322 | E18: =Table41214[[#This Row],[Quarterly Net Absorption (pyeong)]]/0.3025 -> 69849
C19: 3Q | D19: =SUM(C75,G75,K75) -> 25859.515 | E19: =Table41214[[#This Row],[Quarterly Net Absorption (pyeong)]]/0.3025 -> 85486
C20: 4Q | D20: =SUM(C76,G76,K76) -> 16084.227 | E20: =Table41214[[#This Row],[Quarterly Net Absorption (pyeong)]]/0.3025 -> 53171
A21: 2023 | B21: =SUM(D21:D24) -> 39036 | C21: 1Q | D21: =SUM(C77,G77,K77) -> -14436 | E21: =D21/0.3025 -> -47722.314
C22: 2Q | D22: =SUM(C78,G78,K78) -> 21070 | E22: =D22/0.3025 -> 69652.893
C23: 3Q | D23: =SUM(C79,G79,K79) -> 45692 | E23: =D23/0.3025 -> 151047.93
C24: 4Q | D24: =SUM(C80,G80,K80) -> -13290 | E24: =D24/0.3025 -> -43933.884
A25: 2024 | B25: =SUM(D25:D28) -> -59209 | C25: 1Q | D25: =SUM(C81,G81,K81) -> -12407 | E25: =D25/0.3025 -> -41014.876
C26: 2Q | D26: =SUM(C82,G82,K82) -> -32126 | E26: =D26/0.3025 -> -106201.65
C27: 3Q | D27: =SUM(C83,G83,K83) -> -36156 | E27: =D27/0.3025 -> -119523.97
C28: 4Q | D28: =SUM(C84,G84,K84) -> 21480 | E28: =D28/0.3025 -> 71008.264
A29: 2025 YTD | B29: =SUM(D29:D32) -> 11528 | C29: 1Q | D29: =SUM(C85,G85,K85) -> -79876 | E29: =D29/0.3025 -> -264052.89
C30: 2Q | D30: =SUM(C86,G86,K86) -> 74554 | E30: =D30/0.3025 -> 246459.5
C31: 3Q | D31: =SUM(C87,G87,K87) -> 41842 | E31: =D31/0.3025 -> 138320.66
C32: 4Q | D32: =SUM(C88,G88,K88) -> -24992 | E32: =D32/0.3025 -> -82618.182
A33: Source: Colliers Database
B59: Table: Net Absorption by Submarkets_Unit: pyeong
B60: CBD | C60: Net Absorption | F60: GBD | G60: Net Absorption | J60: YBD | K60: Net Absorption | O60: =(-59209-39036)/39036 -> -2.5167794
B61: 1Q 2019 | C61: 6009.465 | F61: 1Q 2019 | G61: 15470.153 | J61: 1Q 2019 | K61: 3074.3075
B62: 2Q 2019 | C62: -2695.88 | F62: 2Q 2019 | G62: 10922.065 | J62: 2Q 2019 | K62: 978.285
B63: 3Q 2019 | C63: 34631.107 | D63: FY 2019 | F63: 3Q 2019 | G63: 6069.0575 | H63: FY 2019 | J63: 3Q 2019 | K63: 9578.36 | L63: FY 2019
B64: 4Q 2019 | C64: 28560.84 | D64: =SUM(C61:C64) -> 66505.533 | F64: 4Q 2019 | G64: -14949.247 | H64: =SUM(G61:G64) -> 17512.027 | J64: 4Q 2019 | K64: -6048.4875 | L64: =SUM(K61:K64) -> 7582.465
B65: 1Q 2020 | C65: 9336.965 | F65: 1Q 2020 | G65: -2520.43 | J65: 1Q 2020 | K65: -5615.005
B66: 2Q 2020 | C66: -2073.6375 | F66: 2Q 2020 | G66: -391.1325 | J66: 2Q 2020 | K66: 14779.243
B67: 3Q 2020 | C67: 13196.865 | D67: FY 2020 | F67: 3Q 2020 | G67: 2953.3075 | H67: FY 2020 | J67: 3Q 2020 | K67: -939.8675 | L67: FY 2020
B68: 4Q 2020 | C68: -12157.172 | D68: =SUM(C65:C68) -> 8303.02 | F68: 4Q 2020 | G68: 7393.705 | H68: =SUM(G65:G68) -> 7435.45 | J68: 4Q 2020 | K68: 22898.645 | L68: =SUM(K65:K68) -> 31123.015
B69: 1Q 2021 | C69: 14941.08 | F69: 1Q 2021 | G69: 8688.7075 | J69: 1Q 2021 | K69: 14426.83
B70: 2Q 2021 | C70: -2948.77 | F70: 2Q 2021 | G70: 10456.82 | J70: 2Q 2021 | K70: 9498.1975
B71: 3Q 2021 | C71: 17849.618 | D71: FY 2021 | F71: 3Q 2021 | G71: 17204.688 | H71: FY 2021 | J71: 3Q 2021 | K71: 8153.2825 | L71: FY 2021
B72: 4Q 2021 | C72: 12120.57 | D72: =SUM(C69:C72) -> 41962.497 | F72: 4Q 2021 | G72: 19696.38 | H72: 56046.595 | J72: 4Q 2021 | K72: 20698.865 | L72: 52777.175
B73: 1Q 2022 | C73: 29342.5 | F73: 1Q 2022 | G73: 5099.2425 | J73: 1Q 2022 | K73: 29367.91
B74: 2Q 2022 | C74: 18692.987 | F74: 2Q 2022 | G74: -4809.4475 | J74: 2Q 2022 | K74: 7245.7825
B75: 3Q 2022 | C75: 21272.103 | D75: FY 2022 | F75: 3Q 2022 | G75: 2113.265 | H75: FY 2022 | J75: 3Q 2022 | K75: 2474.1475 | L75: FY 2022
B76: 4Q 2022 | C76: 12731.317 | D76: =SUM(C73:C76) -> 82038.908 | F76: 4Q 2022 | G76: 548.13 | H76: 2951.19 | J76: 4Q 2022 | K76: 2804.78 | L76: 41892.62
B77: 1Q 2023 | C77: -6491 | F77: 1Q 2023 | G77: 8605 | J77: 1Q 2023 | K77: -16550
B78: 2Q 2023 | C78: -19078 | F78: 2Q 2023 | G78: 37929 | J78: 2Q 2023 | K78: 2219
B79: 3Q 2023 | C79: 36783 | D79: FY 2023 | F79: 3Q 2023 | G79: 1385 | H79: FY 2023 | J79: 3Q 2023 | K79: 7524 | L79: FY 2023
B80: 4Q 2023 | C80: -4427 | D80: =SUM(C77:C80) -> 6787 | F80: 4Q 2023 | G80: -8530 | H80: =SUM(G77:G80) -> 39389 | J80: 4Q 2023 | K80: -333 | L80: =SUM(K77:K80) -> -7140
B81: 1Q 2024 | C81: -7720 | F81: 1Q 2024 | G81: -10361 | J81: 1Q 2024 | K81: 5674
B82: 2Q 2024 | C82: -12628 | F82: 2Q 2024 | G82: -9839 | J82: 2Q 2024 | K82: -9659
B83: 3Q 2024 | C83: -11421 | D83: FY 2024 | F83: 3Q 2024 | G83: -17066 | H83: FY 2024 | J83: 3Q 2024 | K83: -7669 | L83: FY 2024
B84: 4Q 2024 | C84: 3740 | D84: =SUM(C81:C84) -> -28029 | F84: 4Q 2024 | G84: 9169 | H84: =SUM(G81:G84) -> -28097 | J84: 4Q 2024 | K84: 8571 | L84: =SUM(K81:K84) -> -3083
B85: 1Q 2025 | C85: -31426 | F85: 1Q 2025 | G85: -9990 | J85: 1Q 2025 | K85: -38460
B86: 2Q 2025 | C86: 26929 | F86: 2Q 2025 | G86: 27261 | J86: 2Q 2025 | K86: 20364
B87: 3Q 2025 | C87: -9037 | D87: FY 2025 | F87: 3Q 2025 | G87: 20859 | H87: FY 2025 | J87: 3Q 2025 | K87: 30020 | L87: FY 2025
B88: 4Q 2025 | C88: -3216 | D88: =SUM(C85:C88) -> -16750 | F88: 4Q 2025 | G88: -10474 | H88: =SUM(G85:G88) -> 27656 | J88: 4Q 2025 | K88: -11302 | L88: =SUM(K85:K88) -> 622
B89: Source: Colliers Database
A91: Table: Net Absorption by Submarkets_Unit: pyeong
A92: CBD | B92: 1Q 2019 | C92: 2Q 2019 | D92: 3Q 2019 | E92: 4Q 2019 | F92: 1Q 2020 | G92: 2Q 2020 | H92: 3Q 2020 | I92: 4Q 2020 | J92: 1Q 2021 | K92: 2Q 2021 | L92: 3Q 2021 | M92: 4Q 2021 | N92: 1Q 2022 | O92: 2Q 2022 | P92: 3Q 2022 | Q92: 4Q 2022
A93: Net Absorption | B93: 6009.465 | C93: -2695.88 | D93: 34631.107 | E93: 28560.84 | F93: 9336.965 | G93: -2073.6375 | H93: 13196.865 | I93: -12157.172 | J93: 14941.08 | K93: -2948.77 | L93: 17849.618 | M93: 12120.57 | N93: 29342.5 | O93: 18692.987 | P93: 21272.103 | Q93: 12731.317
E94: =SUM(B93:E93) -> 66505.533 | I94: =SUM(F93:I93) -> 8303.02 | M94: 41962.497 | Q94: 82038.908
A96: CBD | B96: 1Q 2023 | C96: 2Q 2023 | D96: 3Q 2023 | E96: 4Q 2023 | F96: 1Q 2024 | G96: 2Q 2024 | H96: 3Q 2024 | I96: 4Q 2024 | J96: 1Q 2025 | K96: 2Q 2025 | L96: 3Q 2025 | M96: 4Q 2025 | N96: 1Q 2026 | O96: 2Q 2026 | P96: 3Q 2026 | Q96: 4Q 2026
A97: Net Absorption | B97: -6491 | C97: -19078 | D97: 36783 | E97: -4427 | F97: -7720 | G97: -12628 | H97: -11421 | I97: =C84 -> 3740 | J97: =C85 -> -31426 | K97: =C86 -> 26929 | L97: =C87 -> -9037 | M97: =C88 -> -3216
E98: 6787 | I98: =SUM(F97:I97) -> -28029 | M98: =SUM(J97:M97) -> -16750 | Q98: =SUM(N97:Q97) -> 0
A100: CBD | B100: 1Q 2027 | C100: 2Q 2027 | D100: 3Q 2027 | E100: 4Q 2027 | F100: 1Q 2028 | G100: 2Q 2028 | H100: 3Q 2028 | I100: 4Q 2028 | J100: 1Q 2029 | K100: 2Q 2029 | L100: 3Q 2029 | M100: 4Q 2029 | N100: 1Q 2030 | O100: 2Q 2030 | P100: 3Q 2030 | Q100: 4Q 2030
A101: Net Absorption
E102: =SUM(B101:E101) -> 0 | I102: =SUM(F101:I101) -> 0 | K102: =SUM(H101:K101) -> 0 | M102: =SUM(J101:M101) -> 0 | O102: =SUM(L101:O101) -> 0 | Q102: =SUM(N101:Q101) -> 0
A104: GBD | B104: 1Q 2019 | C104: 2Q 2019 | D104: 3Q 2019 | E104: 4Q 2019 | F104: 1Q 2020 | G104: 2Q 2020 | H104: 3Q 2020 | I104: 4Q 2020 | J104: 1Q 2021 | K104: 2Q 2021 | L104: 3Q 2021 | M104: 4Q 2021 | N104: 1Q 2022 | O104: 2Q 2022 | P104: 3Q 2022 | Q104: 4Q 2022
A105: Net Absorption | B105: 15470.153 | C105: 10922.065 | D105: 6069.0575 | E105: -14949.247 | F105: -2520.43 | G105: -391.1325 | H105: 2953.3075 | I105: 7393.705 | J105: 8688.7075 | K105: 10456.82 | L105: 17204.688 | M105: 19696.38 | N105: 5099.2425 | O105: -4809.4475 | P105: 2113.265 | Q105: 548.13
E106: 17512.027 | I106: 7435.45 | M106: 56046.595 | Q106: 2951.19
A108: GBD | B108: 1Q 2023 | C108: 2Q 2023 | D108: 3Q 2023 | E108: 4Q 2023 | F108: 1Q 2024 | G108: 2Q 2024 | H108: 3Q 2024 | I108: 4Q 2024 | J108: 1Q 2025 | K108: 2Q 2025 | L108: 3Q 2025 | M108: 4Q 2025 | N108: 1Q 2026 | O108: 2Q 2026 | P108: 3Q 2026 | Q108: 4Q 2026
A109: Net Absorption | B109: 8605 | C109: 37929 | D109: 1385 | E109: -8530 | F109: -10361 | G109: -9839 | H109: -17066 | I109: =G84 -> 9169 | J109: =G85 -> -9990 | K109: =G86 -> 27261 | L109: =G87 -> 20859 | M109: =G88 -> -10474
E110: 39389 | I110: =SUM(F109:I109) -> -28097 | M110: =SUM(J109:M109) -> 27656 | Q110: =SUM(N109:Q109) -> 0
A112: GBD | B112: 1Q 2027 | C112: 2Q 2027 | D112: 3Q 2027 | E112: 4Q 2027 | F112: 1Q 2028 | G112: 2Q 2028 | H112: 3Q 2028 | I112: 4Q 2028 | J112: 1Q 2029 | K112: 2Q 2029 | L112: 3Q 2029 | M112: 4Q 2029 | N112: 1Q 2030 | O112: 2Q 2030 | P112: 3Q 2030 | Q112: 4Q 2030
A113: Net Absorption
E114: =SUM(B113:E113) -> 0 | I114: =SUM(F113:I113) -> 0 | K114: =SUM(H113:K113) -> 0 | M114: =SUM(J113:M113) -> 0 | O114: =SUM(L113:O113) -> 0 | Q114: =SUM(N113:Q113) -> 0
A116: YBD | B116: 1Q 2019 | C116: 2Q 2019 | D116: 3Q 2019 | E116: 4Q 2019 | F116: 1Q 2020 | G116: 2Q 2020 | H116: 3Q 2020 | I116: 4Q 2020 | J116: 1Q 2021 | K116: 2Q 2021 | L116: 3Q 2021 | M116: 4Q 2021 | N116: 1Q 2022 | O116: 2Q 2022 | P116: 3Q 2022 | Q116: 4Q 2022
A117: Net Absorption | B117: 3074.3075 | C117: 978.285 | D117: 9578.36 | E117: -6048.4875 | F117: -5615.005 | G117: 14779.243 | H117: -939.8675 | I117: 22898.645 | J117: 14426.83 | K117: 9498.1975 | L117: 8153.2825 | M117: 20698.865 | N117: 29367.91 | O117: 7245.7825 | P117: 2474.1475 | Q117: 0
E118: 7582.465 | I118: 31123.015 | M118: 52777.175 | Q118: 39087.84
A120: YBD | B120: 1Q 2023 | C120: 2Q 2023 | D120: 3Q 2023 | E120: 4Q 2023 | F120: 1Q 2024 | G120: 2Q 2024 | H120: 3Q 2024 | I120: 4Q 2024 | J120: 1Q 2025 | K120: 2Q 2025 | L120: 3Q 2025 | M120: 4Q 2025 | N120: 1Q 2026 | O120: 2Q 2026 | P120: 3Q 2026 | Q120: 4Q 2026
A121: Net Absorption | B121: -16550 | C121: 2219 | D121: 7524 | E121: -333 | F121: 5674 | G121: -9659 | H121: -7669 | I121: =K84 -> 8571 | J121: =K85 -> -38460 | K121: =K86 -> 20364 | L121: =K87 -> 30020 | M121: =K88 -> -11302
E122: -7140 | I122: =SUM(F121:I121) -> -3083 | M122: =SUM(J121:M121) -> 622 | Q122: =SUM(N121:Q121) -> 0
A124: YBD | B124: 1Q 2027 | C124: 2Q 2027 | D124: 3Q 2027 | E124: 4Q 2027 | F124: 1Q 2028 | G124: 2Q 2028 | H124: 3Q 2028 | I124: 4Q 2028 | J124: 1Q 2029 | K124: 2Q 2029 | L124: 3Q 2029 | M124: 4Q 2029 | N124: 1Q 2030 | O124: 2Q 2030 | P124: 3Q 2030 | Q124: 4Q 2030
A125: Net Absorption
E126: =SUM(B125:E125) -> 0 | I126: =SUM(F125:I125) -> 0 | K126: =SUM(H125:K125) -> 0 | M126: =SUM(J125:M125) -> 0 | O126: =SUM(L125:O125) -> 0 | Q126: =SUM(N125:Q125) -> 0

Sheet Rent
A1: Seoul Grade A Office Building Rents
A3: Table: Major Submarket Rents
A5: Unit: KRW/pyeong/month | B5: Q1 2019 | C5: Q2 2019 | D5: Q3 2019 | E5: Q4 2019 | F5: Q1 2020 | G5: Q2 2020 | H5: Q3 2020 | I5: Q4 2020 | J5: Q1 2021 | K5: Q2 2021 | L5: Q3 2021 | M5: Q4 2021 | N5: Q1 2022 | O5: Q2 2022 | P5: Q3 2022 | Q5: Q4 2022 | R5: Q1 2023 | S5: Q2 2023 | T5: Q3 2023
A6: CBD | B6: 106690.91 | C6: 106611.57 | D6: 106700.83 | E6: 107150.41 | F6: 107965.48 | G6: 108483.68 | H6: 108532.23 | I6: 109347.13 | J6: 110087.23 | K6: 110500.32 | L6: 110655.31 | M6: 110819.77 | N6: 111240.75 | O6: 111819.62 | P6: =34147/0.3025 -> 112882.64 | Q6: 115064.46 | R6: 117533.88 | S6: =35638/0.3025 -> 117811.57 | T6: =35946/0.3025 -> 118829.75
A7: GBD | B7: 91834.711 | C7: 92148.76 | D7: 92195.041 | E7: 92039.669 | F7: 93927.964 | G7: 94540.006 | H7: 95338.843 | I7: 96061.323 | J7: 98407.796 | K7: 98709.599 | L7: 98818.294 | M7: 98883.512 | N7: 99122.641 | O7: 100450.68 | P7: =30866/0.3025 -> 102036.36 | Q7: 104340.5 | R7: 108419.83 | S7: =33795/0.3025 -> 111719.01 | T7: =34656/0.3025 -> 114565.29
A8: YBD | B8: 77887.603 | C8: 77976.86 | D8: 78204.959 | E8: 78704.132 | F8: 79204.189 | G8: 79556.46 | H8: 82717.355 | I8: 82221.638 | J8: 82521.629 | K8: 83220.459 | L8: 84603.811 | M8: 85699.223 | N8: 86362.528 | O8: 87526.273 | P8: =26741/0.3025 -> 88400 | Q8: 89854.545 | R8: =28293/0.3025 -> 93530.579 | S8: =28497/0.3025 -> 94204.959 | T8: =29301/0.3025 -> 96862.81
A9: Seoul Overall Rent | B9: 95550.413 | C9: 96000 | D9: 96102.479 | E9: 96317.355 | F9: 97438.564 | G9: 98233.846 | H9: 98449.587 | I9: 98789.349 | J9: 99896.336 | K9: 100425.42 | L9: 100885.09 | M9: 101222.85 | N9: 101636.41 | O9: 102597.4 | P9: =O9*1.012 -> 103828.57 | Q9: 105857.85 | R9: 109130.58 | S9: =33434/0.3025 -> 110525.62 | T9: =34009/0.3025 -> 112426.45
A10: Source: Colliers Database
A11: CBD (QoQ) | B11: 0.0070204999 | C11: -0.00074363265 | D11: 0.0008372093 | E11: 0.0042135267 | F11: 0.0076067133 | G11: 0.0047997084 | H11: 0.00044755963 | I11: =I6/H6-1 -> 0.0075083199 | J11: =J6/I6-1 -> 0.0067684061 | K11: =K6/J6-1 -> 0.0037523793 | L11: =L6/K6-1 -> 0.0014025723 | M11: =M6/L6-1 -> 0.001486269 | N11: =N6/M6-1 -> 0.0037987829 | O11: =O6/N6-1 -> 0.0052037801 | P11: =P6/O6-1 -> 0.0095065857 | ... T11: =T6/S6-1 -> 0.0086424603
A12: GBD (QoQ) | B12: 0.0065217391 | C12: 0.0034197264 | D12: 0.00050224215 | E12: -0.0016852522 | F12: 0.020516091 | G12: 0.0065160861 | H12: 0.00844972 | I12: =I7/H7-1 -> 0.0075780268 | J12: =J7/I7-1 -> 0.024426824 | K12: =K7/J7-1 -> 0.0030668606 | L12: =L7/K7-1 -> 0.001101161 | M12: =M7/L7-1 -> 0.00065996988 | N12: =N7/M7-1 -> 0.0024182936 | O12: =O7/N7-1 -> 0.013397923 | P12: =P7/O7-1 -> 0.01578571 | ... T12: =T7/S7-1 -> 0.025477142
A13: YBD (QoQ) | B13: 0.0032361082 | C13: 0.0011459615 | D13: 0.0029252162 | E13: 0.0063828888 | F13: 0.0063536283 | G13: 0.0044476327 | H13: 0.039731471 | I13: =I8/H8-1 -> -0.0059929064 | J13: =J8/I8-1 -> 0.0036485609 | K13: =K8/J8-1 -> 0.0084684488 | L13: =L8/K8-1 -> 0.016622741 | M13: =M8/L8-1 -> 0.012947546 | N13: =N8/M8-1 -> 0.0077399226 | O13: =O8/N8-1 -> 0.013475112 | P13: =P8/O8-1 -> 0.0099824564 | ... T13: =T8/S8-1 -> 0.028213496
A14: Seoul Overall (QoQ) | B14: 0.0062315057 | C14: 0.0047052311 | D14: 0.0010674931 | E14: 0.0022359052 | F14: 0.011640771 | G14: 0.0081618826 | H14: 0.0021961984 | I14: =I9/H9-1 -> 0.0034511332 | J14: =J9/I9-1 -> 0.011205525 | K14: =K9/J9-1 -> 0.0052963218 | L14: =L9/K9-1 -> 0.0045772633 | M14: =M9/L9-1 -> 0.0033479432 | N14: =N9/M9-1 -> 0.0040855995 | O14: =O9/N9-1 -> 0.0094551852 | P14: =P9/O9-1 -> 0.012 | ... T14: =T9/S9-1 -> 0.017198062
A15: Source: Colliers Database
A16: CBD (YoY) | B16: 0.030186219 | C16: 0.025209015 | D16: 0.011469399 | E16: 0.011357609 | F16: 0.011946347 | G16: 0.017560085 | H16: 0.017163925 | I16: =I6/E6-1 -> 0.020501208 | J16: =J6/F6-1 -> 0.019652173 | K16: =K6/G6-1 -> 0.018589363 | L16: =L6/H6-1 -> 0.019561693 | M16: =M6/I6-1 -> 0.013467597 | N16: =N6/J6-1 -> 0.010478214 | O16: =O6/K6-1 -> 0.01193934 | P16: =P6/L6-1 -> 0.020128624 | ... T16: =T6/P6-1 -> 0.052683984
A17: GBD (YoY) | B17: 0.0365533 | C17: 0.036014272 | D17: 0.012819582 | E17: 0.0087681159 | F17: 0.022793701 | G17: 0.025949845 | H17: 0.034099466 | I17: =I7/E7-1 -> 0.043694788 | J17: =J7/F7-1 -> 0.047694344 | K17: =K7/G7-1 -> 0.044104005 | L17: =L7/H7-1 -> 0.036495634 | M17: =M7/I7-1 -> 0.029379028 | N17: =N7/J7-1 -> 0.0072641054 | O17: =O7/K7-1 -> 0.017638397 | P17: =P7/L7-1 -> 0.03256552 | ... T17: =T7/P7-1 -> 0.12278883
A18: YBD (YoY) | B18: 0.0061861325 | C18: 0.0073454049 | D18: 0.0090854803 | E18: 0.01375346 | F18: 0.016903662 | G18: 0.0202573 | H18: 0.057699624 | I18: =I8/E8-1 -> 0.044692771 | J18: =J8/F8-1 -> 0.041884648 | K18: =K8/G8-1 -> 0.046055325 | L18: =L8/H8-1 -> 0.022806043 | M18: =M8/I8-1 -> 0.042295249 | N18: =N8/J8-1 -> 0.046544154 | O18: =O8/K8-1 -> 0.051739849 | P18: =P8/L8-1 -> 0.04487019 | ... T18: =T8/P8-1 -> 0.095733144
A19: Seoul Overall (YoY) | B19: 0.063366138 | C19: 0.065297139 | D19: 0.052140763 | E19: 0.014308094 | F19: 0.019760777 | G19: 0.023269227 | H19: 0.024422964 | I19: =I9/E9-1 -> 0.025665095 | J19: =J9/F9-1 -> 0.025223815 | K19: =K9/G9-1 -> 0.022309758 | L19: =L9/H9-1 -> 0.02473861 | M19: =M9/I9-1 -> 0.024633231 | N19: =N9/J9-1 -> 0.01741876 | O19: =O9/K9-1 -> 0.021627774 | P19: =P9/L9-1 -> 0.029176495 | ... T19: =T9/P9-1 -> 0.082808427
A20: Source: Colliers Database
A22: Unit: KRW/pyeong/month | B22: Q4 2023 | C22: Q1 2024 | D22: Q2 2024 | E22: Q3 2024 | F22: Q4 2024 | G22: Q1 2025 | H22: Q2 2025 | I22: Q3 2025 | J22: Q4 2025
A23: CBD | B23: =36615/0.3025 -> 121041.32 | C23: =36948/0.3025 -> 122142.15 | D23: 123203.31 | E23: =37465/0.3025 -> 123851.24 | F23: =38088/0.3025 -> 125910.74 | G23: =38796/0.3025 -> 128251.24 | H23: =39507/0.3025 -> 130601.65 | I23: =39921/0.3025 -> 131970.25 | J23: =40367/0.3025 -> 133444.63
A24: GBD | B24: =36411/0.3025 -> 120366.94 | C24: =36477/0.3025 -> 120585.12 | D24: 122330.58 | E24: =38448/0.3025 -> 127100.83 | F24: =38989/0.3025 -> 128889.26 | G24: =39113/0.3025 -> 129299.17 | H24: =40469/0.3025 -> 133781.82 | I24: =40854/0.3025 -> 135054.55 | J24: =41436/0.3025 -> 136978.51
A25: YBD | B25: =29841/0.3025 -> 98647.934 | C25: =30692/0.3025 -> 101461.16 | D25: 102294.21 | E25: =31599/0.3025 -> 104459.5 | F25: =31925/0.3025 -> 105537.19 | G25: =32832/0.3025 -> 108535.54 | H25: =32923/0.3025 -> 108836.36 | I25: =33051/0.3025 -> 109259.5 | J25: =33441/0.3025 -> 110548.76 | V25: [Overall Summary]
A26: Seoul Overall Rent | B26: =35016/0.3025 -> 115755.37 | C26: =35303/0.3025 -> 116704.13 | D26: 117960.33 | E26: =36401/0.3025 -> 120333.88 | F26: =36933/0.3025 -> 122092.56 | G26: =37499/0.3025 -> 123963.64 | H26: =38290/0.3025 -> 126578.51 | I26: =38627/0.3025 -> 127692.56 | J26: =39105/0.3025 -> 129272.73 | V26: In Q4 2025, Seoul’s overall Grade A office rent rose to KRW 129,273 per pyeong per month, marking a 1.2% quarter-on-quarter increase and a 5.9% year-on-year growth. Compared to the steady momentum observed in Q3, rental growth in Q4 reflected a year-end consolidation of leasing demand, with limited new Grade A supply entering the market and occupier decisions increasingly focused on securing long-term space ahead of anticipated cost pressures. Landlords of prime assets were therefore able to translate tight availability into incremental rental uplifts, particularly in well-located, institutionally managed buildings. While macroeconomic uncertainty continued to temper broader office demand, the imbalance between constrained supply and sustained demand for core Grade A space supported rental stability and reinforced the market’s defensive characteristics entering 2026.
A27: Source: Colliers Database
A28: CBD (QoQ) | B28: =B23/T6-1 -> 0.01861125 | C28: =C23/B23-1 -> 0.0090946333 | D28: =D23/C23-1 -> 0.0086878857 | E28: =E23/D23-1 -> 0.0052590625 | F28: =F23/E23-1 -> 0.016628854 | G28: =G23/F23-1 -> 0.018588532 | H28: =H23/G23-1 -> 0.018326632 | I28: =I23/H23-1 -> 0.010479156 | J28: =J23/I23-1 -> 0.011172065
A29: GBD (QoQ) | B29: =B24/T7-1 -> 0.050640582 | C29: =C24/B24-1 -> 0.001812639 | D29: =D24/C24-1 -> 0.014474875 | E29: =E24/D24-1 -> 0.03899473 | F29: =F24/E24-1 -> 0.014070953 | G29: =G24/F24-1 -> 0.0031803842 | H29: =H24/G24-1 -> 0.03466878 | I29: =I24/H24-1 -> 0.0095134547 | J29: =J24/I24-1 -> 0.014245851
A30: YBD (QoQ) | B30: =B25/T8-1 -> 0.018429405 | C30: =C25/B25-1 -> 0.028517811 | D30: =D25/C25-1 -> 0.0082106086 | E30: =E25/D25-1 -> 0.02116727 | F30: =F25/E25-1 -> 0.010316782 | G30: =G25/F25-1 -> 0.028410337 | H30: =H25/G25-1 -> 0.0027716862 | I30: =I25/H25-1 -> 0.0038878596 | J30: =J25/I25-1 -> 0.011799946
A31: Seoul Overall (QoQ) | B31: =B26/T9-1 -> 0.029609809 | C31: =C26/B26-1 -> 0.0081962531 | D31: =D26/C26-1 -> 0.010763958 | E31: =E26/D26-1 -> 0.020121627 | F31: =F26/E26-1 -> 0.014614983 | G31: =G26/F26-1 -> 0.015325048 | H31: =H26/G26-1 -> 0.021093896 | I31: =I26/H26-1 -> 0.0088012536 | J31: =J26/I26-1 -> 0.012374764
A32: Source: Colliers Database
A33: CBD (YoY) | B33: =B23/Q6-1 -> 0.051943575 | C33: =C23/R6-1 -> 0.039207965 | D33: =D23/S6-1 -> 0.045765756 | E33: =E23/T6-1 -> 0.042257831 | F33: =F23/B23-1 -> 0.040229414 | G33: =G23/C23-1 -> 0.050016239 | H33: =H23/D23-1 -> 0.060049907 | I33: =I23/E23-1 -> 0.065554518 | J33: =J23/F23-1 -> 0.059835119
A34: GBD (YoY) | B34: =B24/Q7-1 -> 0.15359757 | C34: =C24/R7-1 -> 0.11220538 | D34: =D24/S7-1 -> 0.094984465 | E34: =E24/T7-1 -> 0.10941828 | F34: =F24/B24-1 -> 0.070802779 | G34: =G24/C24-1 -> 0.072264715 | H34: =H24/D24-1 -> 0.093608972 | I34: =I24/E24-1 -> 0.062578027 | J34: =J24/F24-1 -> 0.062761292
A35: YBD (YoY) | B35: =B25/Q8-1 -> 0.097862477 | C35: =C25/R8-1 -> 0.084791291 | D35: =D25/S8-1 -> 0.085868688 | E35: =E25/T8-1 -> 0.078427357 | F35: =F25/B25-1 -> 0.069836802 | G35: =G25/C25-1 -> 0.06972501 | H35: =H25/D25-1 -> 0.06395424 | I35: =I25/E25-1 -> 0.045950821 | J35: =J25/F25-1 -> 0.047486296
A36: Seoul Overall (YoY) | B36: =B26/Q9-1 -> 0.09349822 | C36: =C26/R9-1 -> 0.069399006 | D36: =D26/S9-1 -> 0.067266854 | E36: =E26/T9-1 -> 0.070334323 | F36: =F26/B26-1 -> 0.054746402 | G36: =G26/C26-1 -> 0.062204345 | H36: =H26/D26-1 -> 0.073060001 | I36: =I26/E26-1 -> 0.061152166 | J36: =J26/F26-1 -> 0.058809195
A37: Source: Colliers Database
V38: [GBD]
V39: In Q4 2025, GBD headline office rents increased to KRW 136,979 per pyeong per month, maintaining the highest rental level among Seoul’s major business districts. Rents rose by 1.4% quarter-on-quarter, while year-on-year growth moderated to 6.3%, reflecting a normalization of leasing activity toward year-end. Despite this moderation, GBD continued to outperform the broader Seoul market, supported by limited Grade A supply, high tenant retention, and sustained demand from technology and multinational occupiers, reinforcing its position as Seoul’s leading office submarket heading into 2026.
A52: Unit: KRW/pyeong/month | B52: Q1 2019 | C52: Q2 2019 | D52: Q3 2019 | E52: Q4 2019 | F52: Q1 2020 | G52: Q2 2020 | H52: Q3 2020 | I52: Q4 2020 | J52: Q1 2021 | K52: Q2 2021 | L52: Q3 2021 | M52: Q4 2021 | N52: Q1 2022 | O52: Q2 2022 | P52: Q3 2022 | Q52: Q4 2022 | R52: Q1 2023 | S52: Q2 2023 | T52: Q3 2023 | U52: Q4 2023 | V52: Q1 2024 | W52: Q2 2024 | X52: Q3 2024 | Y52: Q4 2024 | Z52: Q1 2025 | AA52: Q2 2025 | AB52: Q3 2025 | AC52: Q4 2025 | AD52: Q1 2026 | AE52: Q2 2026 | AF52: Q3 2026 | AG52: Q4 2026
A53: CBD | B53: 106690.91 | C53: 106611.57 | D53: 106700.83 | E53: 107150.41 | F53: 107965.48 | G53: 108483.68 | H53: 108532.23 | I53: 109347.13 | J53: 110087.23 | K53: 110500.32 | L53: 110655.31 | M53: 110819.77 | N53: 111240.75 | O53: 111819.62 | P53: =34147/0.3025 -> 112882.64 | Q53: 115064.46 | R53: 117533.88 | S53: =35638/0.3025 -> 117811.57 | T53: =35946/0.3025 -> 118829.75 | U53: =36615/0.3025 -> 121041.32 | V53: =36948/0.3025 -> 122142.15 | W53: =D23 -> 123203.31 | X53: =E23 -> 123851.24 | Y53: =F23 -> 125910.74 | Z53: =G23 -> 128251.24 | AA53: =H23 -> 130601.65 | AB53: =I23 -> 131970.25 | AC53: =J23 -> 133444.63 | AD53: =K23 -> 0 | ... AG53: =N23 -> 0
A54: GBD | B54: 91834.711 | C54: 92148.76 | D54: 92195.041 | E54: 92039.669 | F54: 93927.964 | G54: 94540.006 | H54: 95338.843 | I54: 96061.323 | J54: 98407.796 | K54: 98709.599 | L54: 98818.294 | M54: 98883.512 | N54: 99122.641 | O54: 100450.68 | P54: =30866/0.3025 -> 102036.36 | Q54: 104340.5 | R54: 108419.83 | S54: =33795/0.3025 -> 111719.01 | T54: =34656/0.3025 -> 114565.29 | U54: =36411/0.3025 -> 120366.94 | V54: =36477/0.3025 -> 120585.12 | W54: =D24 -> 122330.58 | X54: =E24 -> 127100.83 | Y54: =F24 -> 128889.26 | Z54: =G24 -> 129299.17 | AA54: =H24 -> 133781.82 | AB54: =I24 -> 135054.55 | AC54: =J24 -> 136978.51 | AD54: =K24 -> 0 | ... AG54: =N24 -> 0
A55: YBD | B55: 77887.603 | C55: 77976.86 | D55: 78204.959 | E55: 78704.132 | F55: 79204.189 | G55: 79556.46 | H55: 82717.355 | I55: 82221.638 | J55: 82521.629 | K55: 83220.459 | L55: 84603.811 | M55: 85699.223 | N55: 86362.528 | O55: 87526.273 | P55: =26741/0.3025 -> 88400 | Q55: 89854.545 | R55: =28293/0.3025 -> 93530.579 | S55: =28497/0.3025 -> 94204.959 | T55: =29301/0.3025 -> 96862.81 | U55: =29841/0.3025 -> 98647.934 | V55: =30692/0.3025 -> 101461.16 | W55: =D25 -> 102294.21 | X55: =E25 -> 104459.5 | Y55: =F25 -> 105537.19 | Z55: =G25 -> 108535.54 | AA55: =H25 -> 108836.36 | AB55: =I25 -> 109259.5 | AC55: =J25 -> 110548.76 | AD55: =K25 -> 0 | ... AG55: =N25 -> 0
A56: Seoul Overall Rent | B56: 95550.413 | C56: 96000 | D56: 96102.479 | E56: 96317.355 | F56: 97438.564 | G56: 98233.846 | H56: 98449.587 | I56: 98789.349 | J56: 99896.336 | K56: 100425.42 | L56: 100885.09 | M56: 101222.85 | N56: 101636.41 | O56: 102597.4 | P56: =O56*1.012 -> 103828.57 | Q56: 105857.85 | R56: 109130.58 | S56: =33434/0.3025 -> 110525.62 | T56: =34009/0.3025 -> 112426.45 | U56: =35016/0.3025 -> 115755.37 | V56: =35303/0.3025 -> 116704.13 | W56: =D26 -> 117960.33 | X56: =E26 -> 120333.88 | Y56: =F26 -> 122092.56 | Z56: =G26 -> 123963.64 | AA56: =H26 -> 126578.51 | AB56: =I26 -> 127692.56 | AC56: =J26 -> 129272.73 | AD56: =K26 -> 0 | ... AG56: =N26 -> 0
A57: Source: Colliers Database
A58: CBD (QoQ) | B58: 0.0070204999 | C58: -0.00074363265 | D58: 0.0008372093 | E58: 0.0042135267 | F58: 0.0076067133 | G58: =G53/F53-1 -> 0.0047997084 | H58: =H53/G53-1 -> 0.00044755963 | I58: =I53/H53-1 -> 0.0075083199 | J58: =J53/I53-1 -> 0.0067684061 | K58: =K53/J53-1 -> 0.0037523793 | L58: =L53/K53-1 -> 0.0014025723 | M58: =M53/L53-1 -> 0.001486269 | N58: =N53/M53-1 -> 0.0037987829 | ... AG58: =AG53/AF53-1 -> #DIV/0!
A59: GBD (QoQ) | B59: 0.0065217391 | C59: 0.0034197264 | D59: 0.00050224215 | E59: -0.0016852522 | F59: 0.020516091 | G59: =G54/F54-1 -> 0.0065160861 | H59: =H54/G54-1 -> 0.00844972 | I59: =I54/H54-1 -> 0.0075780268 | J59: =J54/I54-1 -> 0.024426824 | K59: =K54/J54-1 -> 0.0030668606 | L59: =L54/K54-1 -> 0.001101161 | M59: =M54/L54-1 -> 0.00065996988 | N59: =N54/M54-1 -> 0.0024182936 | ... AG59: =AG54/AF54-1 -> #DIV/0!
A60: YBD (QoQ) | B60: 0.0032361082 | C60: 0.0011459615 | D60: 0.0029252162 | E60: 0.0063828888 | F60: 0.0063536283 | G60: =G55/F55-1 -> 0.0044476327 | H60: =H55/G55-1 -> 0.039731471 | I60: =I55/H55-1 -> -0.0059929064 | J60: =J55/I55-1 -> 0.0036485609 | K60: =K55/J55-1 -> 0.0084684488 | L60: =L55/K55-1 -> 0.016622741 | M60: =M55/L55-1 -> 0.012947546 | N60: =N55/M55-1 -> 0.0077399226 | ... AG60: =AG55/AF55-1 -> #DIV/0!
A61: Seoul Overall (QoQ) | B61: 0.0062315057 | C61: 0.0047052311 | D61: 0.0010674931 | E61: 0.0022359052 | F61: 0.011640771 | G61: =G56/F56-1 -> 0.0081618826 | H61: =H56/G56-1 -> 0.0021961984 | I61: =I56/H56-1 -> 0.0034511332 | J61: =J56/I56-1 -> 0.011205525 | K61: =K56/J56-1 -> 0.0052963218 | L61: =L56/K56-1 -> 0.0045772633 | M61: =M56/L56-1 -> 0.0033479432 | N61: =N56/M56-1 -> 0.0040855995 | ... AG61: =AG56/AF56-1 -> #DIV/0!
A62: Source: Colliers Database
A63: CBD (YoY) | B63: 0.030186219 | C63: 0.025209015 | D63: 0.011469399 | E63: 0.011357609 | F63: 0.011946347 | G63: =G53/C53-1 -> 0.017560085 | H63: =H53/D53-1 -> 0.017163925 | I63: =I53/E53-1 -> 0.020501208 | J63: =J53/F53-1 -> 0.019652173 | K63: =K53/G53-1 -> 0.018589363 | L63: =L53/H53-1 -> 0.019561693 | M63: =M53/I53-1 -> 0.013467597 | N63: =N53/J53-1 -> 0.010478214 | ... AG63: =AG53/AC53-1 -> -1
A64: GBD (YoY) | B64: 0.0365533 | C64: 0.036014272 | D64: 0.012819582 | E64: 0.0087681159 | F64: 0.022793701 | G64: =G54/C54-1 -> 0.025949845 | H64: =H54/D54-1 -> 0.034099466 | I64: =I54/E54-1 -> 0.043694788 | J64: =J54/F54-1 -> 0.047694344 | K64: =K54/G54-1 -> 0.044104005 | L64: =L54/H54-1 -> 0.036495634 | M64: =M54/I54-1 -> 0.029379028 | N64: =N54/J54-1 -> 0.0072641054 | ... AG64: =AG54/AC54-1 -> -1
A65: YBD (YoY) | B65: 0.0061861325 | C65: 0.0073454049 | D65: 0.0090854803 | E65: 0.01375346 | F65: 0.016903662 | G65: =G55/C55-1 -> 0.0202573 | H65: =H55/D55-1 -> 0.057699624 | I65: =I55/E55-1 -> 0.044692771 | J65: =J55/F55-1 -> 0.041884648 | K65: =K55/G55-1 -> 0.046055325 | L65: =L55/H55-1 -> 0.022806043 | M65: =M55/I55-1 -> 0.042295249 | N65: =N55/J55-1 -> 0.046544154 | ... AG65: =AG55/AC55-1 -> -1
A66: Seoul Overall (YoY) | B66: 0.063366138 | C66: 0.065297139 | D66: 0.052140763 | E66: 0.014308094 | F66: 0.019760777 | G66: =G56/C56-1 -> 0.023269227 | H66: =H56/D56-1 -> 0.024422964 | I66: =I56/E56-1 -> 0.025665095 | J66: =J56/F56-1 -> 0.025223815 | K66: =K56/G56-1 -> 0.022309758 | L66: =L56/H56-1 -> 0.02473861 | M66: =M56/I56-1 -> 0.024633231 | N66: =N56/J56-1 -> 0.01741876 | ... AG66: =AG56/AC56-1 -> -1
A67: Source: Colliers Database
M69: =E23/D6-1 -> 0.16073365
M70: =_xlfn.RRI(2024-2019,D6,E23) -> 0.030259232

Sheet Vacancy Rate
A1: Seoul Vacancy Rate
R2: ▼
A3: Table: Major Submarket Vacancy Rates
A4: [Vacancy Rate] | B4: Q1 2011 | C4: Q2 2011 | D4: Q3 2011 | E4: Q4 2011 | F4: Q1 2012 | G4: In Q2 2025, the office absorption rate turned positive, indicating a recovery in demand compared to the negative absorption recorded in the previous quarter. Leasing demand increased primarily in newly completed buildings, with several relocations and expansions by firms in finance, law, and tax services across major business districts. In the CBD, the newly completed '107 Building' saw SK Telecom’s task force lease three floors and Samsung Fire & Marine Insurance lease 2.5 floors, contributing to the uptick. In YBD, Fubon Bank opened its first branch in IFC 2, and Kakao Pay Securities relocated its office from Pangyo to Yeouido Finance Center. | H4: Q3 2012 | I4: Q4 2012 | J4: Q1 2013 | K4: Q2 2013 | L4: Q3 2013 | M4: Q4 2013 | N4: Q1 2014 | O4: Q2 2014 | P4: Q3 2014 | Q4: Q4 2014 | R4: Q1 2015 | S4: Q2 2015 | T4: Q3 2015 | U4: Q4 2015
A5: CBD | B5: 0.148 | C5: 0.184 | D5: 0.266 | E5: 0.19 | F5: 0.181 | G5: 0.15 | H5: 0.127 | I5: 0.127 | J5: 0.135 | K5: 0.163 | L5: 0.14 | M5: 0.093 | N5: 0.097 | O5: 0.088 | P5: 0.091 | Q5: 0.107 | R5: 0.137 | S5: 0.147 | T5: 0.15 | U5: 0.149
A6: GBD | B6: 0.022 | C6: 0.023 | D6: 0.023 | E6: 0.026 | F6: 0.011 | G6: 0.044 | H6: 0.043 | I6: 0.04 | J6: 0.076 | K6: 0.075 | L6: 0.063 | M6: 0.071 | N6: 0.08 | O6: 0.089 | P6: 0.091 | Q6: 0.083 | R6: 0.086 | S6: 0.09 | T6: 0.086 | U6: 0.082
A7: YBD | B7: 0.039 | C7: 0.02 | D7: 0.05 | E7: 0.08 | F7: 0.051 | G7: 0.048 | H7: 0.043 | I7: 0.226 | J7: 0.214 | K7: 0.219 | L7: 0.236 | M7: 0.222 | N7: 0.229 | O7: 0.209 | P7: 0.21 | Q7: 0.167 | R7: 0.165 | S7: 0.178 | T7: 0.155 | U7: 0.142
A8: Seoul Overall Vacancy | B8: 0.076 | C8: 0.088 | D8: 0.136 | E8: 0.104 | F8: 0.092 | G8: 0.091 | H8: 0.079 | I8: 0.122 | J8: 0.132 | K8: 0.145 | L8: 0.138 | M8: 0.118 | N8: 0.124 | O8: 0.118 | P8: 0.12 | Q8: 0.114 | R8: 0.126 | S8: 0.134 | T8: 0.129 | U8: 0.125
A9: Source: Colliers Database
A10: QoQ Change | B10: Q1 2011 | C10: Q2 2011 | D10: Q3 2011 | E10: Q4 2011 | F10: Q1 2012 | G10: Q2 2012 | H10: Q3 2012 | I10: Q4 2012 | J10: Q1 2013 | K10: Q2 2013 | L10: Q3 2013 | M10: Q4 2013 | N10: Q1 2014 | O10: Q2 2014 | P10: Q3 2014 | Q10: Q4 2014 | R10: Q1 2015 | S10: Q2 2015 | T10: Q3 2015 | U10: Q4 2015
A11: CBD | C11: =C5-B5 -> 0.036 | D11: =D5-C5 -> 0.082 | E11: =E5-D5 -> -0.076 | F11: =F5-E5 -> -0.009 | G11: =G5-F5 -> -0.031 | H11: =H5-G5 -> -0.023 | I11: =I5-H5 -> 0 | J11: =J5-I5 -> 0.008 | ... U11: =U5-T5 -> -0.001
A12: GBD | C12: =C6-B6 -> 0.001 | D12: =D6-C6 -> 0 | E12: =E6-D6 -> 0.003 | F12: =F6-E6 -> -0.015 | G12: =G6-F6 -> 0.033 | H12: =H6-G6 -> -0.001 | I12: =I6-H6 -> -0.003 | J12: =J6-I6 -> 0.036 | ... U12: =U6-T6 -> -0.004
A13: YBD | C13: =C7-B7 -> -0.019 | D13: =D7-C7 -> 0.03 | E13: =E7-D7 -> 0.03 | F13: =F7-E7 -> -0.029 | G13: =G7-F7 -> -0.003 | H13: =H7-G7 -> -0.005 | I13: =I7-H7 -> 0.183 | J13: =J7-I7 -> -0.012 | ... U13: =U7-T7 -> -0.013
A14: Seoul Overall Vacancy | C14: =C8-B8 -> 0.012 | D14: =D8-C8 -> 0.048 | E14: =E8-D8 -> -0.032 | F14: =F8-E8 -> -0.012 | G14: =G8-F8 -> -0.001 | H14: =H8-G8 -> -0.012 | I14: =I8-H8 -> 0.043 | J14: =J8-I8 -> 0.01 | ... U14: =U8-T8 -> -0.004
A15: Source: Colliers Database
A16: YoY Change | B16: Q1 2011 | C16: Q2 2011 | D16: Q3 2011 | E16: Q4 2011 | F16: Q1 2012 | G16: Q2 2012 | H16: Q3 2012 | I16: Q4 2012 | J16: Q1 2013 | K16: Q2 2013 | L16: Q3 2013 | M16: Q4 2013 | N16: Q1 2014 | O16: Q2 2014 | P16: Q3 2014 | Q16: Q4 2014 | R16: Q1 2015 | S16: Q2 2015 | T16: Q3 2015 | U16: Q4 2015
A17: CBD | F17: =F5/B5-1 -> 0.22297297 | G17: In the GBD, the newly completed OPUS 459 (Baekam Building) secured leases from multiple companies, including tech firms. Additionally, Viva Republica and its affiliate Toss Income signed leases in Gangnam Finance Center and POSCO Tower Yeoksam, demonstrating stable demand for Grade A office space in the GBD. | H17: =H5/D5-1 -> -0.52255639 | I17: =I5/E5-1 -> -0.33157895 | J17: =J5/F5-1 -> -0.25414365 | K17: =K5/G5-1 -> 0.086666667 | L17: =L5/H5-1 -> 0.1023622 | M17: =M5/I5-1 -> -0.26771654 | N17: =N5/J5-1 -> -0.28148148 | O17: =O5/K5-1 -> -0.4601227 | ... U17: =U5/Q5-1 -> 0.39252336
A18: GBD | F18: =F6/B6-1 -> -0.5 | G18: =G6/C6-1 -> 0.91304348 | H18: =H6/D6-1 -> 0.86956522 | I18: =I6/E6-1 -> 0.53846154 | J18: =J6/F6-1 -> 5.9090909 | K18: =K6/G6-1 -> 0.70454545 | L18: =L6/H6-1 -> 0.46511628 | M18: =M6/I6-1 -> 0.775 | ... U18: =U6/Q6-1 -> -0.012048193
A19: YBD | F19: =F7/B7-1 -> 0.30769231 | G19: =G7/C7-1 -> 1.4 | H19: =H7/D7-1 -> -0.14 | I19: =I7/E7-1 -> 1.825 | J19: =J7/F7-1 -> 3.1960784 | K19: =K7/G7-1 -> 3.5625 | L19: =L7/H7-1 -> 4.4883721 | M19: =M7/I7-1 -> -0.017699115 | ... U19: =U7/Q7-1 -> -0.1497006
A20: Seoul Overall Vacancy | F20: =F8/B8-1 -> 0.21052632 | G20: =G8/C8-1 -> 0.034090909 | H20: =H8/D8-1 -> -0.41911765 | I20: =I8/E8-1 -> 0.17307692 | J20: =J8/F8-1 -> 0.43478261 | K20: =K8/G8-1 -> 0.59340659 | L20: =L8/H8-1 -> 0.74683544 | M20: =M8/I8-1 -> -0.032786885 | ... U20: =U8/Q8-1 -> 0.096491228
A22: [Vacancy Rate] | B22: Q1 2019 | C22: Q2 2019 | D22: Q3 2019 | E22: Q4 2019 | F22: Q1 2020 | G22: Q2 2020 | H22: Q3 2020 | I22: Q4 2020 | J22: Q1 2021 | K22: Q2 2021 | L22: Q3 2021 | M22: Q4 2021 | N22: Q1 2022 | O22: Q2 2022 | P22: Q3 2022 | Q22: Q4 2022 | R22: Q1 2023 | S22: Q2 2023 | T22: Q3 2023 | U22: Q4 2023 | V22: Q1 2024 | W22: Q2 2024 | X22: Q3 2024 | Y22: Q4 2024 | Z22: Q1 2025 | AA22: Q2 2025 | AB22: Q3 2025 | AC22: Q4 2025
A23: CBD | B23: 0.13000898 | C23: 0.13333139 | D23: 0.10099496 | E23: 0.078650457 | F23: 0.070088158 | G23: 0.11380211 | H23: 0.101 | I23: 0.11250484 | J23: 0.099699515 | K23: 0.10222697 | L23: 0.089969874 | M23: 0.0948279 | N23: 0.07 | O23: 0.053175238 | P23: 0.035 | Q23: 0.024 | R23: 0.026 | S23: 0.031 | T23: 0.02 | U23: 0.021 | V23: 0.022 | W23: 0.026 | X23: 0.029 | Y23: =Y42 -> 0.028 | Z23: =Z42 -> 0.045 | AA23: =AA42 -> 0.044 | AB23: =AB42 -> 0.046 | AC23: 0.048
A24: GBD | B24: 0.039566451 | C24: 0.028736048 | D24: 0.021080038 | E24: 0.038848163 | F24: 0.041940748 | G24: 0.04242061 | H24: 0.039 | I24: 0.040274985 | J24: 0.084243728 | K24: 0.033085517 | L24: 0.013967714 | M24: 0.01119892 | N24: 0.006 | O24: 0.010876782 | P24: 0.009 | Q24: 0.008 | R24: 0.021 | S24: 0.009 | T24: 0.008 | U24: 0.011 | V24: 0.015 | W24: 0.018 | X24: 0.023 | Y24: =Y43 -> 0.02 | Z24: =Z43 -> 0.023 | AA24: =AA43 -> 0.021 | AB24: =AB43 -> 0.014 | AC24: 0.018
A25: YBD | B25: 0.088249457 | C25: 0.086179825 | D25: 0.065911672 | E25: 0.078710712 | F25: 0.090592398 | G25: 0.059318733 | H25: 0.208 | I25: 0.15309332 | J25: 0.12933477 | K25: 0.11632951 | L25: 0.10259084 | M25: 0.081451222 | N25: 0.032 | O25: 0.019756245 | P25: 0.016 | Q25: 0.011 | R25: 0.019 | S25: 0.018 | T25: 0.024 | U25: 0.024 | V25: 0.023 | W25: 0.028 | X25: 0.031 | Y25: =Y44 -> 0.027 | Z25: =Z44 -> 0.045 | AA25: =AA44 -> 0.036 | AB25: =AB44 -> 0.022 | AC25: 0.027
A26: Seoul Overall Vacancy | B26: 0.089881494 | C26: 0.088 | D26: 0.067064117 | E26: 0.065021288 | F26: 0.064516363 | G26: 0.079441766 | H26: 0.106 | I26: 0.099001354 | J26: 0.10122767 | K26: 0.081982242 | L26: 0.067181595 | M26: 0.06369898 | N26: 0.04 | O26: 0.031512445 | P26: 0.022 | Q26: 0.016 | R26: 0.023 | S26: 0.021 | T26: 0.017 | U26: 0.018 | V26: 0.02 | W26: 0.024 | X26: 0.028 | Y26: =Y45 -> 0.025 | Z26: =Z45 -> 0.038 | AA26: =AA45 -> 0.034 | AB26: =AB45 -> 0.03 | AC26: 0.033
A27: Source: Colliers Database
A28: QoQ Change | B28: Q1 2019 | C28: Q2 2019 | D28: Q3 2019 | E28: Q4 2019 | F28: Q1 2020 | G28: Q2 2020 | H28: Q3 2020 | I28: Q4 2020 | J28: Q1 2021 | K28: Q2 2021 | L28: Q3 2021 | M28: Q4 2021 | N28: Q1 2022 | O28: Q2 2022 | P28: Q3 2022 | Q28: Q4 2022 | R28: Q1 2023 | S28: Q2 2023 | T28: Q3 2023 | U28: Q4 2023 | V28: Q1 2024 | W28: Q2 2024 | X28: Q3 2024 | Y28: Q4 2024 | Z28: Q1 2025 | AA28: Q2 2025 | AB28: Q3 2025 | AC28: Q4 2025
A29: CBD | B29: 0.01203742 | C29: 0.0033224091 | D29: -0.03233643 | E29: -0.0223445 | F29: -0.0085622989 | G29: 0.043713954 | H29: -0.012802111 | I29: 0.011504837 | J29: =J23-I29 -> 0.088194678 | K29: =K23-J23 -> 0.002527459 | L29: =L23-K23 -> -0.0122571 | M29: =M23-L23 -> 0.0048580262 | N29: =N23-M23 -> -0.0248279 | O29: =O23-N23 -> -0.016824762 | P29: =P23-O23 -> -0.018175238 | Q29: =Q23-P23 -> -0.011 | R29: =R23-Q23 -> 0.002 | ... AC29: =AC23-AB23 -> 0.002
A30: GBD | B30: -0.020063774 | C30: https://www.segye.com/newsView/20250929511083?OutUrl=naver | D30: -0.0076560097 | E30: 0.017768125 | F30: 0.003092585 | G30: 0.0004798622 | H30: -0.0034206103 | I30: 0.0012749854 | J30: =J24-I30 -> 0.082968743 | K30: =K24-J24 -> -0.051158212 | L30: =L24-K24 -> -0.019117803 | M30: =M24-L24 -> -0.002768794 | N30: =N24-M24 -> -0.0051989195 | O30: =O24-N24 -> 0.004876782 | P30: =P24-O24 -> -0.001876782 | Q30: =Q24-P24 -> -0.001 | R30: =R24-Q24 -> 0.013 | ... AC30: =AC24-AB24 -> 0.004
A31: YBD | B31: -0.00650527 | C31: -0.0020696316 | D31: -0.020268153 | E31: 0.01279904 | F31: 0.011881687 | G31: -0.031273665 | H31: 0.14868127 | I31: -0.054906679 | J31: =J25-I31 -> 0.18424145 | K31: =K25-J25 -> -0.013005255 | L31: =L25-K25 -> -0.013738678 | M31: =M25-L25 -> -0.021139613 | N31: =N25-M25 -> -0.049451222 | O31: =O25-N25 -> -0.012243755 | P31: =P25-O25 -> -0.0037562454 | Q31: =Q25-P25 -> -0.005 | R31: =R25-Q25 -> 0.008 | ... AC31: =AC25-AB25 -> 0.005
A32: Seoul Overall Vacancy | B32: -0.0051185059 | C32: -0.0018814941 | D32: -0.020935883 | E32: -0.0020428288 | F32: -0.0005049251 | G32: 0.014925403 | H32: 0.026558234 | I32: -0.0069986459 | J32: =J26-I32 -> 0.10822631 | K32: =K26-J26 -> -0.019245426 | L32: =L26-K26 -> -0.014800647 | M32: =M26-L26 -> -0.0034826153 | N32: =N26-M26 -> -0.02369898 | O32: =O26-N26 -> -0.0084875546 | P32: =P26-O26 -> -0.0095124454 | Q32: =Q26-P26 -> -0.006 | R32: =R26-Q26 -> 0.007 | ... AC32: =AC26-AB26 -> 0.003
A33: Source: Colliers Database
A34: YoY Change | B34: Q1 2019 | C34: Q2 2019 | D34: Q3 2019 | E34: Q4 2019 | F34: Q1 2020 | G34: Q2 2020 | H34: Q3 2020 | I34: Q4 2020 | J34: Q1 2021 | K34: Q2 2021 | L34: Q3 2021 | M34: Q4 2021 | N34: Q1 2022 | O34: Q2 2022 | P34: Q3 2022 | Q34: Q4 2022 | R34: Q1 2023 | S34: Q2 2023 | T34: Q3 2023 | U34: Q4 2023 | V34: Q1 2024 | W34: Q2 2024 | X34: Q3 2024 | Y34: Q4 2024 | Z34: Q1 2025 | AA34: Q2 2025 | AB34: Q3 2025 | AC34: Q4 2025
A35: CBD | B35: 0.017008978 | C35: 0.018331387 | D35: -0.031005043 | E35: -0.039321102 | F35: -0.05992082 | G35: -0.019529276 | H35: 5.0430636e-06 | I35: 0.033854381 | J35: =J23-F23 -> 0.029611357 | K35: =K23-G23 -> -0.011575137 | L35: =L23-H23 -> -0.011030126 | M35: =M23-I23 -> -0.017676937 | N35: =N23-J23 -> -0.029699515 | O35: =O23-K23 -> -0.049051736 | P35: =P23-L23 -> -0.054969874 | Q35: =Q23-M23 -> -0.0708279 | ... AC35: =AC23-Y23 -> 0.02
A36: GBD | B36: -0.019933549 | C36: -0.023263952 | D36: -0.048919962 | E36: -0.020782061 | F36: 0.0023742976 | G36: 0.013684562 | H36: 0.017919962 | I36: 0.0014268224 | J36: =J24-F24 -> 0.04230298 | K36: =K24-G24 -> -0.0093350937 | L36: =L24-H24 -> -0.025032286 | M36: =M24-I24 -> -0.029076066 | N36: =N24-J24 -> -0.078243728 | O36: =O24-K24 -> -0.022208735 | P36: =P24-L24 -> -0.0049677136 | Q36: =Q24-M24 -> -0.0031989195 | ... AC36: =AC24-Y24 -> -0.002 | AE36: [Overall Summary]
A37: YBD | B37: -0.13475054 | C37: -0.073820175 | D37: -0.061088328 | E37: -0.016044015 | F37: 0.0023429417 | G37: -0.026861092 | H37: 0.14208833 | I37: 0.074382609 | J37: =J25-F25 -> 0.03874237 | K37: =K25-G25 -> 0.05701078 | L37: =L25-H25 -> -0.10540916 | M37: =M25-I25 -> -0.071642099 | N37: =N25-J25 -> -0.097334768 | O37: =O25-K25 -> -0.096573267 | P37: =P25-L25 -> -0.086590835 | Q37: =Q25-M25 -> -0.070451222 | ... AC37: =AC25-Y25 -> 0 | AE37: In Q4 2025, Seoul’s overall Grade A office vacancy rate edged up to 3.3% (+0.3pp QoQ), reflecting mild normalization after Q3’s tightening. The CBD vacancy increased to 4.8%, while the GBD and YBD remained tight at 1.8% and 2.7%, respectively, supported by limited near-term supply. Looking ahead, vacancy pressure is expected to rise from 2026, with concentrated supply in the CBD and other submarkets potentially pushing vacancy rates above 10% by 2029, subject to absorption and project delivery timing.
A38: Seoul Overall Vacancy | B38: -0.027901924 | C38: -0.014 | D38: -0.041851994 | E38: -0.029978712 | F38: -0.025365131 | G38: -0.0085582344 | H38: 0.038935883 | I38: 0.033980066 | J38: =J26-F26 -> 0.036711305 | K38: =K26-G26 -> 0.0025404767 | L38: =L26-H26 -> -0.038818405 | M38: =M26-I26 -> -0.035302374 | N38: =N26-J26 -> -0.061227668 | O38: =O26-K26 -> -0.050469797 | P38: =P26-L26 -> -0.045181595 | Q38: =Q26-M26 -> -0.04769898 | ... AC38: =AC26-Y26 -> 0.008
A41: [Vacancy Rate] | B41: Q1 2019 | C41: Q2 2019 | D41: Q3 2019 | E41: Q4 2019 | F41: Q1 2020 | G41: Q2 2020 | H41: Q3 2020 | I41: Q4 2020 | J41: Q1 2021 | K41: Q2 2021 | L41: Q3 2021 | M41: Q4 2021 | N41: Q1 2022 | O41: Q2 2022 | P41: Q3 2022 | Q41: Q4 2022 | R41: Q1 2023 | S41: Q2 2023 | T41: Q3 2023 | U41: Q4 2023 | V41: Q1 2024 | W41: Q2 2024 | X41: Q3 2024 | Y41: Q4 2024 | Z41: Q1 2025 | AA41: Q2 2025 | AB41: Q3 2025 | AC41: Q4 2025
A42: CBD | B42: 0.13000898 | C42: 0.13333139 | D42: 0.10099496 | E42: 0.078650457 | F42: 0.070088158 | G42: =G23 -> 0.11380211 | H42: 0.101 | I42: 0.11250484 | J42: 0.099699515 | K42: 0.10222697 | L42: 0.089969874 | M42: 0.0948279 | N42: 0.07 | O42: 0.053175238 | P42: 0.035 | Q42: 0.024 | R42: 0.026 | S42: 0.031 | T42: 0.02 | U42: 0.021 | V42: 0.022 | W42: 0.026 | X42: =X23 -> 0.029 | Y42: 0.028 | Z42: 0.045 | AA42: 0.044 | AB42: 0.046 | AC42: 0.048
A43: GBD | B43: 0.039566451 | C43: 0.028736048 | D43: 0.021080038 | E43: 0.038848163 | F43: 0.041940748 | G43: 0.04242061 | H43: 0.039 | I43: 0.040274985 | J43: 0.084243728 | K43: 0.033085517 | L43: 0.013967714 | M43: 0.01119892 | N43: 0.006 | O43: 0.010876782 | P43: 0.009 | Q43: 0.008 | R43: 0.021 | S43: 0.009 | T43: 0.008 | U43: 0.011 | V43: 0.015 | W43: 0.018 | X43: =X24 -> 0.023 | Y43: 0.02 | Z43: 0.023 | AA43: 0.021 | AB43: 0.014 | AC43: 0.018
A44: YBD | B44: 0.088249457 | C44: 0.086179825 | D44: 0.065911672 | E44: 0.078710712 | F44: 0.090592398 | G44: 0.059318733 | H44: 0.208 | I44: 0.15309332 | J44: 0.12933477 | K44: 0.11632951 | L44: 0.10259084 | M44: 0.081451222 | N44: 0.032 | O44: 0.019756245 | P44: 0.016 | Q44: 0.011 | R44: 0.019 | S44: 0.018 | T44: 0.024 | U44: 0.024 | V44: 0.023 | W44: 0.028 | X44: =X25 -> 0.031 | Y44: 0.027 | Z44: 0.045 | AA44: 0.036 | AB44: 0.022 | AC44: 0.027
A45: Seoul Overall Vacancy | B45: 0.089881494 | C45: 0.088 | D45: 0.067064117 | E45: 0.065021288 | F45: 0.064516363 | G45: 0.079441766 | H45: 0.106 | I45: 0.099001354 | J45: 0.10122767 | K45: 0.081982242 | L45: 0.067181595 | M45: 0.06369898 | N45: 0.04 | O45: 0.031512445 | P45: 0.022 | Q45: 0.016 | R45: 0.023 | S45: 0.021 | T45: 0.017 | U45: 0.018 | V45: 0.02 | W45: 0.024 | X45: =X26 -> 0.028 | Y45: 0.025 | Z45: 0.038 | AA45: 0.034 | AB45: 0.03 | AC45: 0.033
A46: Source: Colliers Database
A47: QoQ Change | B47: Q1 2019 | C47: Q2 2019 | D47: Q3 2019 | E47: Q4 2019 | F47: Q1 2020 | G47: Q2 2020 | H47: Q3 2020 | I47: Q4 2020 | J47: Q1 2021 | K47: Q2 2021 | L47: Q3 2021 | M47: Q4 2021 | N47: Q1 2022 | O47: Q2 2022 | P47: Q3 2022 | Q47: Q4 2022 | R47: Q1 2023 | S47: Q2 2023 | T47: Q3 2023 | U47: Q4 2023 | V47: Q1 2024 | W47: Q2 2024 | X47: Q3 2024 | Y47: Q4 2024 | Z47: =Z41 -> Q1 2025 | AA47: =AA41 -> Q2 2025 | AB47: =AB41 -> Q3 2025 | AC47: =AC41 -> Q4 2025
A48: CBD | B48: 0.01203742 | C48: 0.0033224091 | D48: -0.03233643 | E48: -0.0223445 | F48: -0.0085622989 | G48: 0.043713954 | H48: -0.012802111 | I48: 0.011504837 | J48: -0.012805322 | K48: 0.002527459 | L48: -0.0122571 | M48: 0.0048580262 | N48: -0.0248279 | O48: -0.016824762 | P48: -0.018175238 | Q48: -0.011 | R48: 0.002 | S48: 0.005 | T48: -0.011 | U48: 0.001 | V48: 0.001 | W48: 0.004 | X48: 0.003 | Y48: -0.001 | Z48: 0.017 | AA48: =AA42-Z42 -> -0.001 | AB48: =AB42-AA42 -> 0.002 | AC48: =AC42-AB42 -> 0.002
A49: GBD | B49: -0.020063774 | C49: -0.010830402 | D49: -0.0076560097 | E49: 0.017768125 | F49: 0.003092585 | G49: 0.0004798622 | H49: -0.0034206103 | I49: 0.0012749854 | J49: 0.043968743 | K49: -0.051158212 | L49: -0.019117803 | M49: -0.002768794 | N49: -0.0051989195 | O49: 0.004876782 | P49: -0.001876782 | Q49: -0.001 | R49: 0.013 | S49: -0.012 | T49: -0.001 | U49: 0.003 | V49: 0.004 | W49: 0.003 | X49: 0.005 | Y49: -0.003 | Z49: 0.003 | AA49: =AA43-Z43 -> -0.002 | AB49: =AB43-AA43 -> -0.007 | AC49: =AC43-AB43 -> 0.004
A50: YBD | B50: -0.00650527 | C50: -0.0020696316 | D50: -0.020268153 | E50: 0.01279904 | F50: 0.011881687 | G50: -0.031273665 | H50: 0.14868127 | I50: -0.054906679 | J50: -0.023758553 | K50: -0.013005255 | L50: -0.013738678 | M50: -0.021139613 | N50: -0.049451222 | O50: -0.012243755 | P50: -0.0037562454 | Q50: -0.005 | R50: 0.008 | S50: -0.001 | T50: 0.006 | U50: 0 | V50: -0.001 | W50: 0.005 | X50: 0.003 | Y50: -0.004 | Z50: 0.018 | AA50: =AA44-Z44 -> -0.009 | AB50: =AB44-AA44 -> -0.014 | AC50: =AC44-AB44 -> 0.005
A51: Seoul Overall Vacancy | B51: -0.0051185059 | C51: -0.0018814941 | D51: -0.020935883 | E51: -0.0020428288 | F51: -0.0005049251 | G51: 0.014925403 | H51: 0.026558234 | I51: -0.0069986459 | J51: 0.0022263138 | K51: -0.019245426 | L51: -0.014800647 | M51: -0.0034826153 | N51: -0.02369898 | O51: -0.0084875546 | P51: -0.0095124454 | Q51: -0.006 | R51: 0.007 | S51: -0.002 | T51: -0.004 | U51: 0.001 | V51: 0.002 | W51: 0.004 | X51: 0.004 | Y51: -0.003 | Z51: 0.013 | AA51: =AA45-Z45 -> -0.004 | AB51: =AB45-AA45 -> -0.004 | AC51: =AC45-AB45 -> 0.003 | AE51: [GBD]
A52: Source: Colliers Database | AE52: In Q4 2025, GBD vacancy remained tight at 1.8%, reflecting strong tenant retention and sustained demand for prime Grade A offices. With limited near-term supply, vacancy is expected to remain structurally low in the short term, reinforcing GBD’s resilience despite rising citywide vacancy pressures expected from 2026 onward.
A53: YoY Change | B53: Q1 2019 | C53: Q2 2019 | D53: Q3 2019 | E53: Q4 2019 | F53: Q1 2020 | G53: Q2 2020 | H53: Q3 2020 | I53: Q4 2020 | J53: Q1 2021 | K53: Q2 2021 | L53: Q3 2021 | M53: Q4 2021 | N53: Q1 2022 | O53: Q2 2022 | P53: Q3 2022 | Q53: Q4 2022 | R53: Q1 2023 | S53: Q2 2023 | T53: Q3 2023 | U53: Q4 2023 | V53: Q1 2024 | W53: Q2 2024 | X53: Q3 2024 | Y53: Q4 2024 | Z53: =Z41 -> Q1 2025 | AA53: =AA41 -> Q2 2025 | AB53: =AB41 -> Q3 2025 | AC53: =AC41 -> Q4 2025
A54: CBD | B54: 0.017008978 | C54: 0.018331387 | D54: -0.031005043 | E54: -0.039321102 | F54: -0.05992082 | G54: -0.019529276 | H54: 5.0430636e-06 | I54: 0.033854381 | J54: 0.029611357 | K54: -0.011575137 | L54: -0.011030126 | M54: -0.017676937 | N54: -0.029699515 | O54: -0.049051736 | P54: -0.054969874 | Q54: -0.0708279 | R54: -0.044 | S54: -0.022175238 | T54: -0.015 | U54: -0.003 | V54: -0.004 | W54: -0.005 | X54: 0.009 | Y54: 0.007 | Z54: 0.023 | AA54: =AA42-W42 -> 0.018 | AB54: =AB42-X42 -> 0.017 | AC54: =AC42-Y42 -> 0.02
A55: GBD | B55: -0.019933549 | C55: -0.023263952 | D55: -0.048919962 | E55: -0.020782061 | F55: 0.0023742976 | G55: 0.013684562 | H55: 0.017919962 | I55: 0.0014268224 | J55: 0.04230298 | K55: -0.0093350937 | L55: -0.025032286 | M55: -0.029076066 | N55: -0.078243728 | O55: -0.022208735 | P55: -0.0049677136 | Q55: -0.0031989195 | R55: 0.015 | S55: -0.001876782 | T55: -0.001 | U55: 0.003 | V55: -0.006 | W55: 0.009 | X55: 0.015 | Y55: 0.009 | Z55: 0.008 | AA55: =AA43-W43 -> 0.003 | AB55: =AB43-X43 -> -0.009 | AC55: =AC43-Y43 -> -0.002
A56: YBD | B56: -0.13475054 | C56: -0.073820175 | D56: -0.061088328 | E56: -0.016044015 | F56: 0.0023429417 | G56: -0.026861092 | H56: 0.14208833 | I56: 0.074382609 | J56: 0.03874237 | K56: 0.05701078 | L56: -0.10540916 | M56: -0.071642099 | N56: -0.097334768 | O56: -0.096573267 | P56: -0.086590835 | Q56: -0.070451222 | R56: -0.013 | S56: -0.0017562454 | T56: 0.008 | U56: 0.013 | V56: 0.004 | W56: 0.01 | X56: 0.007 | Y56: 0.003 | Z56: 0.022 | AA56: =AA44-W44 -> 0.008 | AB56: =AB44-X44 -> -0.009 | AC56: =AC44-Y44 -> 0
A57: Seoul Overall Vacancy | B57: -0.027901924 | C57: -0.014 | D57: -0.041851994 | E57: -0.029978712 | F57: -0.025365131 | G57: -0.0085582344 | H57: 0.038935883 | I57: 0.033980066 | J57: 0.036711305 | K57: 0.0025404767 | L57: -0.038818405 | M57: -0.035302374 | N57: -0.061227668 | O57: -0.050469797 | P57: -0.045181595 | Q57: -0.04769898 | R57: -0.017 | S57: -0.010512445 | T57: -0.005 | U57: 0.002 | V57: -0.003 | W57: 0.003 | X57: 0.011 | Y57: 0.007 | Z57: 0.018 | AA57: =AA45-W45 -> 0.01 | AB57: =AB45-X45 -> 0.002 | AC57: =AC45-Y45 -> 0.008

Sheet CV & Yields
A1: Seoul Grade A Office Building Capital Values & Yields
C2: 0.3025
A3: Table: Overall Capital Values and Yields | C3: 10.7639
A6: Overall | C6: 2019 | G6: 2020 | K6: 2021 | O6: 2022 | T6: [Overall Summary]
C7: Q1 | D7: Q2 | E7: Q3 | F7: Q4 | G7: Q1 | H7: Q2 | I7: Q3 | J7: Q4 | K7: Q1 | L7: Q2 | M7: Q3 | N7: Q4 | O7: Q1 | P7: Q2 | Q7: Q3 | R7: Q4 | T7: In Q4 2025, Seoul’s Grade A office investment market recorded a quarter-on-quarter increase in transaction value, led by the CBD and GBD as investor confidence improved. Share deals accounted for 4 of 9 transactions, reflecting continued preference for equity-based structures. However, the higher share of share deals—around 50% of activity—placed downward pressure on capital values, as these transactions are typically priced below asset deals due to their exemption from the 4.6% acquisition tax. Despite this, cap rates remained broadly stable, indicating sustained demand for prime, income-secure assets.
A8: Capital Value (KRW/pyeong (GFA)) | B8: Quarterly | C8: 18882714 | D8: 18764157 | E8: 19602885 | F8: 19804626 | G8: 21500772 | H8: 21678067 | I8: 21958242 | J8: 21931407 | K8: 23260223 | L8: 23273725 | M8: 23286133 | N8: 23277282 | O8: 23842852 | P8: 20514502 | Q8: =7376807/0.3025 -> 24386139 | R8: 26783054
B9: Yearly | C9: =((AVERAGE(C8:F8))) -> 19263596 | D9: 0 | E9: 0 | F9: 0 | G9: =((AVERAGE(G8:J8))) -> 21767122 | H9: 0 | I9: 0 | J9: 0 | K9: =((AVERAGE(K8:N8))) -> 23274341 | L9: 0 | M9: 0 | N9: 0 | O9: In the GBD, the newly completed OPUS 459 (Baekam Building) secured leases from multiple companies, including tech firms. Additionally, Viva Republica and its affiliate Toss Income signed leases in Gangnam Finance Center and POSCO Tower Yeoksam, demonstrating stable demand for Grade A office space in the GBD. | P9: 0 | Q9: 0 | R9: 0
A10: Net Yield (%) | B10: Quarterly | C10: 0.04 | D10: 0.043 | E10: 0.04 | F10: 0.042 | G10: 0.042 | H10: 0.039 | I10: 0.039 | J10: 0.038 | K10: 0.037 | L10: 0.035 | M10: 0.033 | N10: 0.033 | O10: 0.032 | P10: 0.033 | Q10: 0.035 | R10: 0.04
B11: Yearly | C11: 0.04125 | G11: 0.0395 | K11: =AVERAGE(K10:N10) -> 0.0345 | O11: =AVERAGE(O10:R10) -> 0.035
A12: Source: Colliers Database
A14: Overall | C14: 2023 | G14: 2024 | K14: 2025 | O14: 2026
C15: Q1 | D15: Q2 | E15: Q3 | F15: Q4 | G15: Q1 | H15: Q2 | I15: Q3 | J15: Q4 | K15: Q1 | L15: Q2 | M15: Q3 | N15: Q4 | O15: Q1 | P15: Q2 | Q15: Q3 | R15: Q4 | AG15: =_xlfn.RRI(2024-2018,G9,P16) -> -1
A16: Capital Value (KRW/pyeong (GFA)) | B16: Quarterly | C16: 29417256 | D16: 27132560 | E16: 27338125 | F16: 28349369 | G16: 33546273 | H16: =X98 -> 20514502 | I16: 35179120 | J16: 31003046 | K16: 32679428 | L16: 33496414 | M16: 33831378 | N16: 32398890
B17: Yearly | C17: =AVERAGE(C16:F16) -> 28059328 | D17: 0 | E17: 0 | F17: 0 | G17: =AVERAGE(G16:J16) -> 30060735 | H17: 0 | I17: 0 | J17: 0 | K17: =((AVERAGE(K16:N16))) -> 33101527 | L17: 0 | M17: 0 | N17: 0 | O17: =AVERAGE(O16:R16) -> #DIV/0! | P17: 0 | Q17: 0 | R17: 0
A18: Net Yield (%) | B18: Quarterly | C18: 0.04 | D18: 0.043 | E18: 0.042 | F18: 0.043 | G18: 0.044 | H18: 0.044 | I18: 0.043 | J18: 0.046 | K18: 0.042 | L18: 0.04 | M18: 0.04 | N18: 0.043
B19: Yearly | C19: =AVERAGE(C18:F18) -> 0.042 | G19: =AVERAGE(G18:J18) -> 0.04425 | K19: =AVERAGE(K18:N18) -> 0.04125 | O19: =AVERAGE(O18:R18) -> #DIV/0!
A20: Source: Colliers Database | T20: [GBD]
T21: In Q4 2025, GBD recorded a quarter-on-quarter increase in Grade A office transaction value, driven by renewed investor activity in prime, stabilized assets. Share deals formed a notable portion of transactions, reflecting continued use of flexible acquisition structures. Despite higher activity, cap rates remained broadly stable, reinforcing GBD’s position as a defensive and liquid office investment market heading into 2026.
A22: Overall | C22: 2027 | G22: 2028 | K22: 2029 | O22: 2030
C23: Q1 | D23: Q2 | E23: Q3 | F23: Q4 | G23: Q1 | H23: Q2 | I23: Q3 | J23: Q4 | K23: Q1 | L23: Q2 | M23: Q3 | N23: Q4 | O23: Q1 | P23: Q2 | Q23: Q3 | R23: Q4
A24: Capital Value (KRW/pyeong (GFA)) | B24: Quarterly
B25: Yearly | C25: =AVERAGE(C24:F24) -> #DIV/0! | D25: 0 | E25: 0 | F25: 0 | G25: =AVERAGE(G24:J24) -> #DIV/0! | H25: 0 | I25: 0 | J25: 0 | K25: =AVERAGE(K24:N24) -> #DIV/0! | L25: 0 | M25: 0 | N25: 0 | O25: =AVERAGE(O24:R24) -> #DIV/0! | P25: 0 | Q25: 0 | R25: 0
A26: Net Yield (%) | B26: Quarterly
B27: Yearly | C27: =AVERAGE(C26:F26) -> #DIV/0! | G27: =AVERAGE(G26:J26) -> #DIV/0! | K27: =AVERAGE(K26:N26) -> #DIV/0! | O27: =AVERAGE(O26:R26) -> #DIV/0!
A28: Source: Colliers Database
A30: Table: Capital Values KRW/pyeong (GFA) by Submarkets | C30: https://www.segye.com/newsView/20250929511083?OutUrl=naver
A31: Capital Value KRW/pyeong (GFA) | C31: 2019 | G31: 2020 | K31: 2021 | O31: 2022
C32: Q1 | D32: Q2 | E32: Q3 | F32: Q4 | G32: Q1 | H32: Q2 | I32: Q3 | J32: Q4 | K32: Q1 | L32: Q2 | M32: Q3 | N32: Q4 | O32: Q1 | P32: Q2 | Q32: Q3 | R32: Q4
A33: CBD | B33: Quarterly | C33: 24614657 | D33: 22813804 | E33: 24976829 | F33: 21289082 | G33: 23584169 | H33: 23869304 | I33: 24176450 | J33: 23343055 | K33: 25033856 | L33: 25550100 | M33: 12996155 | N33: 20889893 | O33: 25422039 | P33: 32185242 | Q33: 33794504 | R33: 35484230
B34: Yearly | C34: 23423593 | G34: 23743244 | K34: 21117501 | O34: =AVERAGE(O33:R33) -> 31721504 | P34: 0 | Q34: 0 | R34: 0
A35: GBD | B35: Quarterly | C35: 23245008 | D35: 24498602 | E35: 24059394 | F35: 22816806 | G35: 24007369 | H35: 23804273 | I35: 27693115 | J35: 27867197 | K35: 27905215 | L35: 34799480 | M35: 22250537 | N35: 24581641 | O35: 34566370 | P35: 38038014 | Q35: 39939915 | R35: 41936911
B36: Yearly | C36: 23654953 | G36: 25842989 | K36: 27384219 | O36: =AVERAGE(O35:R35) -> 38620302 | P36: 0 | Q36: 0 | R36: 0
A37: YBD | B37: Quarterly | C37: 16549838 | D37: 17092095 | E37: 17092095 | F37: 20263596 | G37: 22247536 | H37: 22247536 | I37: 17968510 | J37: 21496000 | K37: 21506185 | L37: 21780315 | M37: 18838922 | N37: 19819386 | O37: 21180030 | P37: 19819386 | Q37: 20810355 | R37: 20810355
B38: Yearly | C38: 17749406 | G38: 20989895 | K38: 20486202 | O38: =AVERAGE(O37:R37) -> 20655032 | P38: 0 | Q38: 0 | R38: 0
A39: Source: Colliers Database
A41: Table: Capital Values KRW/pyeong (GFA) by Submarkets
A42: Capital Value KRW/pyeong (GFA) | C42: 2023 | K42: 2025 | O42: 2026
C43: Q1 | D43: Q2 | E43: Q3 | F43: Q4 | G43: Q1 | H43: Q2 | I43: Q3 | J43: Q4 | K43: Q1 | L43: Q2 | M43: Q3 | N43: Q4 | O43: Q1 | P43: Q2 | Q43: Q3 | R43: Q4
A44: CBD | B44: Quarterly | C44: 35484230 | D44: 33008586 | E44: 33258669 | F44: =E44 -> 33258669 | G44: 32195240 | H44: 27494932 | I44: 37139433 | J44: 32136795 | K44: 35029107 | L44: 35729689 | M44: 36086986 | N44: 35437420
B45: Yearly | C45: =AVERAGE(C44:F44) -> 33752539 | D45: 0 | E45: 0 | F45: 0 | G45: =AVERAGE(G44:J44) -> 32241600 | H45: 0 | I45: 0 | J45: 0 | K45: =AVERAGE(K44:N44) -> 35570800 | L45: 0 | M45: 0 | N45: 0 | O45: =AVERAGE(O44:R44) -> #DIV/0! | P45: 0 | Q45: 0 | R45: 0
A46: GBD | B46: Quarterly | C46: 41936911 | D46: 39011080 | E46: 39306640 | F46: 40372307 | G46: 34221790 | H46: =X98 -> 20514502 | I46: 40498680 | J46: 35043556 | K46: 37847040 | L46: 38603981 | M46: 38990021 | N46: 39496891
B47: Yearly | C47: =AVERAGE(C46:F46) -> 40156734 | D47: 0 | E47: 0 | F47: 0 | G47: =AVERAGE(G46:J46) -> 32569632 | H47: 0 | I47: 0 | J47: 0 | K47: =AVERAGE(K46:N46) -> 38734483 | L47: 0 | M47: 0 | N47: 0 | O47: =AVERAGE(O46:R46) -> #DIV/0! | P47: 0 | Q47: 0 | R47: 0
A48: YBD | B48: Quarterly | C48: 20810355 | D48: 19358470 | E48: 19505136 | F48: 19505136 | G48: 19505136 | H48: 19505136 | I48: 18659060 | J48: 16145707 | K48: 16145707 | L48: =K48 -> 16145707 | M48: 16145707 | N48: =M48 -> 16145707
B49: Yearly | C49: =AVERAGE(C48:F48) -> 19794774 | D49: 0 | E49: 0 | F49: 0 | G49: =AVERAGE(G48:J48) -> 18453760 | H49: 0 | I49: 0 | J49: 0 | K49: =AVERAGE(K48:N48) -> 16145707 | L49: 0 | M49: 0 | N49: 0 | O49: =AVERAGE(O48:R48) -> #DIV/0! | P49: 0 | Q49: 0 | R49: 0
A50: Source: Colliers Database
A52: Table: Capital Values KRW/pyeong (GFA) by Submarkets
A53: Capital Value KRW/pyeong (GFA) | C53: 2027 | G53: 2028 | K53: 2029 | O53: 2030
C54: Q1 | D54: Q2 | E54: Q3 | F54: Q4 | G54: Q1 | H54: Q2 | I54: Q3 | J54: Q4 | K54: Q1 | L54: Q2 | M54: Q3 | N54: Q4 | O54: Q1 | P54: Q2 | Q54: Q3 | R54: Q4
A55: CBD | B55: Quarterly
B56: Yearly | C56: =AVERAGE(C55:F55) -> #DIV/0! | D56: 0 | E56: 0 | F56: 0 | G56: =AVERAGE(G55:J55) -> #DIV/0! | H56: 0 | I56: 0 | J56: 0 | K56: =AVERAGE(K55:N55) -> #DIV/0! | L56: 0 | M56: 0 | N56: 0 | O56: =AVERAGE(O55:R55) -> #DIV/0! | P56: 0 | Q56: 0 | R56: 0
A57: GBD | B57: Quarterly
B58: Yearly | C58: =AVERAGE(C57:F57) -> #DIV/0! | D58: 0 | E58: 0 | F58: 0 | G58: =AVERAGE(G57:J57) -> #DIV/0! | H58: 0 | I58: 0 | J58: 0 | K58: =AVERAGE(K57:N57) -> #DIV/0! | L58: 0 | M58: 0 | N58: 0 | O58: =AVERAGE(O57:R57) -> #DIV/0! | P58: 0 | Q58: 0 | R58: 0
A59: YBD | B59: Quarterly
B60: Yearly | C60: =AVERAGE(C59:F59) -> #DIV/0! | D60: 0 | E60: 0 | F60: 0 | G60: =AVERAGE(G59:J59) -> #DIV/0! | H60: 0 | I60: 0 | J60: 0 | K60: =AVERAGE(K59:N59) -> #DIV/0! | L60: 0 | M60: 0 | N60: 0 | O60: =AVERAGE(O59:R59) -> #DIV/0! | P60: 0 | Q60: 0 | R60: 0
A61: Source: Colliers Database
A63: Table: Net Yields (%) by Submarkets
A64: Net Yield (%) | C64: 2019 | G64: 2020 | K64: 2021 | O64: 2022
C65: Q1 | D65: Q2 | E65: Q3 | F65: Q4 | G65: Q1 | H65: Q2 | I65: Q3 | J65: Q4 | K65: Q1 | L65: Q2 | M65: Q3 | N65: Q4 | O65: Q1 | P65: Q2 | Q65: Q3 | R65: Q4
A66: CBD | B66: Quarterly | C66: 0.047 | D66: 0.052 | E66: 0.047 | F66: 0.046 | G66: 0.046 | H66: 0.046 | I66: 0.045 | J66: 0.04 | K66: 0.04 | L66: 0.043 | M66: 0.039 | N66: 0.036 | O66: 0.036 | P66: 0.035 | Q66: 0.034 | R66: 0.039
B67: Yearly | C67: =AVERAGE(C66:F66) -> 0.048 | G67: =AVERAGE(G66:J66) -> 0.04425 | K67: =AVERAGE(K66:N66) -> 0.0395 | O67: =AVERAGE(O66:R66) -> 0.036
A68: GBD | B68: Quarterly | C68: 0.048 | D68: 0.046 | E68: 0.045 | F68: 0.044 | G68: 0.046 | H68: 0.039 | I68: 0.037 | J68: 0.035 | K68: 0.038 | L68: 0.037 | M68: 0.036 | N68: 0.037 | O68: 0.035 | P68: 0.033 | Q68: 0.033 | R68: 0.038
B69: Yearly | C69: =AVERAGE(C68:F68) -> 0.04575 | G69: =AVERAGE(G68:J68) -> 0.03925 | K69: =AVERAGE(K68:N68) -> 0.037 | O69: =AVERAGE(O68:R68) -> 0.03475
A70: YBD | B70: Quarterly | C70: 0.049 | D70: 0.05 | E70: 0.05 | F70: 0.044 | G70: 0.042 | H70: 0.041 | I70: 0.041 | J70: 0.036 | K70: 0.035 | L70: 0.037 | M70: 0.037 | N70: 0.037 | O70: 0.037 | P70: 0.037 | Q70: 0.036 | R70: 0.041
B71: Yearly | C71: =AVERAGE(C70:F70) -> 0.04825 | G71: =AVERAGE(G70:J70) -> 0.04 | K71: =AVERAGE(K70:N70) -> 0.0365 | O71: =AVERAGE(O70:R70) -> 0.03775
A72: Source: Colliers Database
A74: Table: Net Yields (%) by Submarkets
A75: Net Yield (%) | C75: 2023 | G75: 2024 | K75: 2025 | O75: 2026
C76: Q1 | D76: Q2 | E76: Q3 | F76: Q4 | G76: Q1 | H76: Q2 | I76: Q3 | J76: Q4 | K76: Q1 | L76: Q2 | M76: Q3 | N76: Q4 | O76: Q1 | P76: Q2 | Q76: Q3 | R76: Q4
A77: CBD | B77: Quarterly | C77: =B77 -> Quarterly | D77: 0.041925 | E77: 0.041925 | F77: 0.041925 | G77: 0.044 | H77: 0.044 | I77: 0.042 | J77: 0.045 | K77: 0.042 | L77: 0.04 | M77: 0.04 | N77: 0.042
B78: Yearly | C78: =AVERAGE(C77:F77) -> 0.041925 | G78: =AVERAGE(G77:J77) -> 0.04375 | K78: =AVERAGE(K77:N77) -> 0.041 | O78: =AVERAGE(O77:R77) -> #DIV/0!
A79: GBD | B79: Quarterly | C79: =B79 -> Quarterly | D79: 0.04085 | E79: 0.04085 | F79: 0.04085 | G79: 0.044 | H79: 0.044 | I79: 0.042 | J79: 0.045 | K79: 0.041 | L79: 0.039 | M79: 0.039 | N79: =M79 -> 0.039
B80: Yearly | C80: =AVERAGE(C79:F79) -> 0.04085 | G80: =AVERAGE(G79:J79) -> 0.04375 | K80: =AVERAGE(K79:N79) -> 0.0395 | O80: =AVERAGE(O79:R79) -> #DIV/0!
A81: YBD | B81: Quarterly | C81: =B81 -> Quarterly | D81: 0.044075 | E81: 0.044075 | F81: 0.044075 | G81: 0.044075 | H81: 0.044075 | I81: 0.045 | J81: 0.047 | K81: 0.047 | L81: 0.047 | M81: 0.047 | N81: =M81 -> 0.047
B82: Yearly | C82: =AVERAGE(C81:F81) -> 0.044075 | G82: =AVERAGE(G81:J81) -> 0.0450375 | K82: =AVERAGE(K81:N81) -> 0.047 | O82: =AVERAGE(O81:R81) -> #DIV/0!
A83: Source: Colliers Database
A85: Table: Net Yields (%) by Submarkets
A86: Net Yield (%) | C86: 2027 | G86: 2028 | K86: 2029 | O86: 2030
C87: Q1 | D87: Q2 | E87: Q3 | F87: Q4 | G87: Q1 | H87: Q2 | I87: Q3 | J87: Q4 | K87: Q1 | L87: Q2 | M87: Q3 | N87: Q4 | O87: Q1 | P87: Q2 | Q87: Q3 | R87: Q4
A88: CBD | B88: Quarterly
B89: Yearly | C89: =AVERAGE(C88:F88) -> #DIV/0! | G89: =AVERAGE(G88:J88) -> #DIV/0! | K89: =AVERAGE(K88:N88) -> #DIV/0! | O89: =AVERAGE(O88:R88) -> #DIV/0!
A90: GBD | B90: Quarterly
B91: Yearly | C91: =AVERAGE(C90:F90) -> #DIV/0! | G91: =AVERAGE(G90:J90) -> #DIV/0! | K91: =AVERAGE(K90:N90) -> #DIV/0! | O91: =AVERAGE(O90:R90) -> #DIV/0!
A92: YBD | B92: Quarterly
B93: Yearly | C93: =AVERAGE(C92:F92) -> #DIV/0! | G93: =AVERAGE(G92:J92) -> #DIV/0! | K93: =AVERAGE(K92:N92) -> #DIV/0! | O93: =AVERAGE(O92:R92) -> #DIV/0!
A94: Source: Colliers Database
A96: Overall | C96: 2017 | G96: 2018 | K96: 2019 | O96: 2020 | S96: 2021 | W96: 2022 | AA96: 2023 | AE96: 2024 | AI96: 2025
C97: Q1 | D97: Q2 | E97: Q3 | F97: Q4 | G97: Q1 | H97: Q2 | I97: Q3 | J97: Q4 | K97: Q1 | L97: Q2 | M97: Q3 | N97: Q4 | O97: Q1 | P97: Q2 | Q97: Q3 | R97: Q4 | S97: Q1 | T97: Q2 | U97: Q3 | V97: Q4 | W97: Q1 | X97: Q2 | Y97: Q3 | Z97: Q4 | AA97: Q1 | AB97: Q2 | AC97: Q3 | AD97: Q4 | AE97: Q1 | AF97: Q2 | AG97: Q3 | AH97: Q4 | AI97: Q1 | AJ97: Q2 | AK97: Q3 | AL97: Q4
A98: Capital Value (KRW/pyeong (GFA)) | B98: Quarterly | C98: 15311831 | D98: 16762286 | E98: 17045130 | F98: 16077029 | G98: 19681071 | H98: 19667339 | I98: 19612144 | J98: 19886143 | K98: 18882714 | L98: 18764157 | M98: 19602885 | N98: 19804626 | O98: 21500772 | P98: 21678067 | Q98: 21958242 | R98: 21931407 | S98: 23260223 | T98: 23273725 | U98: 23286133 | V98: 23277282 | W98: 23842852 | X98: 20514502 | Y98: 24386139 | Z98: 26783054 | AA98: 29417256 | AB98: 27132560 | AC98: 27338125 | AD98: 28349369 | AE98: 33546273 | AF98: 32237955 | AG98: 35179120 | AH98: 31003046 | AI98: =K16 -> 32679428 | AJ98: =L16 -> 33496414 | AK98: =M16 -> 33831378 | AL98: =N16 -> 32398890
B99: Yearly | C99: =((AVERAGE(C98:F98))) -> 16299069 | G99: =((AVERAGE(G98:J98))) -> 19711674 | K99: =((AVERAGE(K98:N98))) -> 19263596 | L99: 0 | M99: 0 | N99: 0 | O99: =((AVERAGE(O98:R98))) -> 21767122 | P99: 0 | Q99: 0 | R99: 0 | S99: =((AVERAGE(S98:V98))) -> 23274341 | T99: 0 | U99: 0 | V99: 0 | W99: =AVERAGE(W98:Z98) -> 23881637 | X99: 0 | Y99: 0 | Z99: 0 | AA99: =AVERAGE(AA98:AD98) -> 28059328 | AB99: 0 | AC99: 0 | AD99: 0 | AE99: =AVERAGE(AE98:AH98) -> 32991598 | AF99: 0 | AG99: 0 | AH99: 0 | AI99: =AVERAGE(AI98:AL98) -> 33101527 | AJ99: 0 | AK99: 0 | AL99: 0
A100: Net Yield (%) | B100: Quarterly | C100: 0.047 | D100: 0.047 | E100: 0.0475 | F100: 0.047 | G100: 0.044 | H100: 0.04 | I100: 0.042 | J100: 0.039 | K100: 0.04 | L100: 0.043 | M100: 0.04 | N100: 0.042 | O100: 0.042 | P100: 0.039 | Q100: 0.039 | R100: 0.038 | S100: 0.037 | T100: 0.035 | U100: 0.033 | V100: 0.033 | W100: 0.032 | X100: 0.033 | Y100: 0.035 | Z100: 0.04 | AA100: 0.04 | AB100: 0.043 | AC100: 0.042 | AD100: 0.043 | AE100: 0.044 | AF100: =H18 -> 0.044 | AG100: =I18 -> 0.043 | AH100: =J18 -> 0.046 | AI100: =K18 -> 0.042 | AJ100: =L18 -> 0.04 | AK100: =M18 -> 0.04 | AL100: =N18 -> 0.043
B101: Yearly | C101: 0.047125 | G101: 0.04125 | K101: 0.04125 | O101: 0.0395 | S101: =AVERAGE(S100:V100) -> 0.0345 | W101: =AVERAGE(W100:Z100) -> 0.035 | AA101: =AVERAGE(AA100:AD100) -> 0.042 | AE101: =AVERAGE(AE100:AH100) -> 0.04425 | AI101: =AVERAGE(AI100:AL100) -> 0.04125
A102: Source: Colliers Database

Sheet Major Deals
A1: Seoul Selected Transactions
A5: Table: Major Grade A Office Building Rents | E5: =TODAY() -> 46111
A6: Details
A7: Property | B7: Location | C7: Submarket | D7: Location & Submarket | E7: Completion Date | F7: Age | G7: Year | H7: ='[23]Major Deals Work Sheet (PPT)'!B12 -> Building Age/Completion | I7: NLA (pyeong) | J7: NLA (sqm) | K7: sq. m. / py | L7: NLA (sf) | M7: Transaction Price (USD) | N7: Transaction Price (Billion KRW) | O7: Transaction Price (Million SGD) | P7: Unit Rate (USD/pyeong) | Q7: Unit Rate (KRW/pyeong) | R7: Unit Rate (KRW/sqm) | S7: Unit Rate (KRW Million/pyeong) | T7: Unit Rate (USD/sqm) | U7: Unit Rate (USD/sf) | V7: Net Yield | W7: Date | X7: Type | Y7: Tenure | Z7: ='[23]Major Deals Work Sheet (PPT)'!B21 -> Transaction Type | AA7: Occupancy | AB7: ='[23]Major Deals Work Sheet (PPT)'!B20 -> Entry NPI Yield | AC7: Buyer | AD7: Seller | AE7: Remarks | AF7: Source
A8: SK Seorin Building | B8: Jongro | C8: CBD | D8: =CONCATENATE(B8&" - "&C8) -> Jongro - CBD | I8: 25349.999 | J8: =I8/0.3025 -> 83801.65 | L8: =J8*10.7639 -> 902032.58 | M8: 8.86e+08 | N8: 1151.0026 | O8: =N8*0.001015*1000 -> 1168.2676 | P8: 45404443 | Q8: 45404443 | R8: =(N8*1000000000)/J8 -> 13734844 | S8: =Q8/1000000 -> 45.404443 | T8: =M8/J8 -> 10572.584 | U8: =M8/L8 -> 982.22616 | V8: na | W8: 07 2022 | X8: Office | Y8: Freehold | AC8: SK REITs | AD8: Hana AIM | AE8: SK REITs acquired the Seorin Building in a similar fashion it acquired Jongro Tower in CBD. SK REITs will become one the largest domestic public REITs with acquiring the building.
A9: Alpharium Tower 1, 2 | B9: Pangyo | C9: Others (BBD) | D9: =CONCATENATE(B9&" - "&C9) -> Pangyo - Others (BBD) | I9: 33957.137 | J9: =I9/0.3025 -> 112255 | L9: =J9*10.7639 -> 1208301.6 | M9: 1.0182898e+09 | N9: 1227.5483 | O9: =N9*0.001015*1000 -> 1245.9615 | P9: 36149935 | Q9: 36149935 | R9: =(N9*1000000000)/J9 -> 10935355 | S9: =Q9/1000000 -> 36.149935 | T9: =M9/J9 -> 9071.2196 | U9: =M9/L9 -> 842.74469 | V9: na | W9: 02 2022 | X9: Office | Y9: Freehold | AC9: Mastern | AD9: ARA Korea, KB Securities & Esk Veritas AM | AE9: Alpharium Tower was sold at the highest value per area in the Bundang area. Alpharium Tower earned KRW 500 Billion in 5 years by selling the Alpharium Tower. It was sold at KRW 1,068 / Mn sqf.
A10: Emart Seongsu-dong HQ | B10: Seongsu | C10: Others | D10: =CONCATENATE(B10&" - "&C10) -> Seongsu - Others | I10: 30192.107 | J10: =I10/0.3025 -> 99808.62 | L10: =J10*10.7639 -> 1074330 | M10: 1.017e+09 | N10: 1232.7057 | O10: =N10*0.001015*1000 -> 1251.1963 | P10: 40828740 | Q10: 40828740 | R10: =(N10*1000000000)/J10 -> 12350694 | S10: =Q10/1000000 -> 40.82874 | T10: =M10/J10 -> 10189.501 | U10: =M10/L10 -> 946.63651 | V10: na | W10: 03 2022 | X10: Office | Y10: Freehold | AC10: Mirae Asset & Krafton | AD10: E-mart (Shinsege) | AE10: E-mart (Shinsege) sold its E-mart Seoungdu-dong HQ building and acquired more than KRW 1Trillion. E-mart (Shinsege) is currently liquidating its assets to increase its investments in e-commerce.
A11: SK U Tower (SK Hynix HQ) | B11: Bundang | C11: Others (BBD) | D11: =CONCATENATE(B11&" - "&C11) -> Bundang - Others (BBD) | I11: 26995.492 | J11: =I11/0.3025 -> 89241.297 | L11: =J11*10.7639 -> 960584.4 | M11: 591000000 | N11: 767.3544 | O11: =N11*0.001015*1000 -> 778.86472 | P11: 28425279 | Q11: 28425279 | R11: =(N11*1000000000)/J11 -> 8598646.9 | S11: =Q11/1000000 -> 28.425279 | T11: =M11/J11 -> 6622.4945 | U11: =M11/L11 -> 615.25047 | V11: na | W11: 06 2022 | X11: Office | Y11: Freehold | AC11: SK REITs | AD11: SK Hynix | AE11: SK REITs is a sponsor REITs of SK Group which liquidates real estates owned by SK Group. SK REITs acquired the SK U Tower, landmark of Bundang, to expand its REITs portfolio.
A12: Shinhan Investment Building | B12: Yeoido | C12: YBD | D12: =CONCATENATE(B12&" - "&C12) -> Yeoido - YBD | I12: 21237.822 | J12: =I12/0.3025 -> 70207.676 | L12: =J12*10.7639 -> 755708.4 | M12: 533000000 | N12: 762.2966 | O12: =N12*0.001015*1000 -> 773.73105 | P12: 35893351 | Q12: 35893351 | R12: =(N12*1000000000)/J12 -> 10857739 | S12: =Q12/1000000 -> 35.893351 | T12: =M12/J12 -> 7591.7625 | U12: =M12/L12 -> 705.2985 | V12: 0.033 | W12: 09 2022 | X12: Office | Y12: Freehold | AC12: IGIS & KKR | AD12: Shinhan Asset Management | AE12: Shinhan Asset Management decided to sell its building at the peak of the real estate market. Shinhan Asset Management earned more than KRW 400 Billion with this deal, and the capital gain will be booked in Q3's earnings. Shinhan Investment, the existing tenant for the building, will stay for the next two years and move to TP Tower (YBD).
A13: Jongro Tower | B13: Jongro | C13: CBD | D13: =CONCATENATE(B13&" - "&C13) -> Jongro - CBD | I13: 18408.763 | J13: =I13/0.3025 -> 60855.415 | L13: =J13*10.7639 -> 655041.6 | M13: 4.8934363e+08 | N13: 624.45141 | O13: =N13*0.001015*1000 -> 633.81818 | P13: 26582.103 | Q13: 33921422 | R13: =(N13*1000000000)/J13 -> 10261230 | S13: =Q13/1000000 -> 33.921422 | T13: =M13/J13 -> 8041.0861 | U13: =M13/L13 -> 747.04207 | V13: na | W13: 10 2022 | X13: Office | Y13: Freehold | AC13: SK REITs | AD13: KB Asset Management | AE13: SK REITs acquired the Jongro Tower to build its 'Green Campus' in CBD. The acquired value was KRW 100 Billion higher than the market projection. Jongro Tower will be filled out with SK subsidiaries such as SK E&S, SK Energy, SK On, SK Geocentric, SK Forestry, and SK Ecoplant.
A14: Samhwan Building | B14: Jongro | C14: CBD | D14: =CONCATENATE(B14&" - "&C14) -> Jongro - CBD | I14: 9499.2623 | J14: =I14/0.3025 -> 31402.52 | L14: =J14*10.7639 -> 338013.59 | M14: 1.7490792e+08 | N14: 223.2 | O14: =N14*0.001015*1000 -> 226.548 | P14: 18412.79 | Q14: 23496561 | R14: =(N14*1000000000)/J14 -> 7107709.8 | S14: =Q14/1000000 -> 23.496561 | T14: =M14/J14 -> 5569.869 | U14: =M14/L14 -> 517.45826 | V14: na | W14: 12 2022 | X14: Office | Y14: Freehold | AC14: Keppel Asset Management | AD14: Hana AIM
A15: Samsung Life Insurance Daechi Tower | B15: Daechi | C15: GBD | D15: =CONCATENATE(B15&" - "&C15) -> Daechi - GBD | I15: 13671 | J15: =I15/0.3025 -> 45193.388 | L15: =J15*10.7639 -> 486457.11 | M15: 3.6480133e+08 | N15: 481.1 | O15: =N15*0.001015*1000 -> 488.3165 | P15: 26684.32 | Q15: 35191281 | R15: =(N15*1000000000)/J15 -> 10645362 | S15: =Q15/1000000 -> 35.191281 | T15: =M15/J15 -> 8072.0067 | U15: =M15/L15 -> 749.91469 | V15: na | W15: 11 2022 | X15: Office | Y15: Freehold | AC15: Samsung SRA | AD15: Samsung Life Insurance | AE15: Samsung FN REITs (Samsung Life Insurance & Samsung General Insurance) acquired 'Samsung Life Insurance Daechi Tower', and is looking forward to launch its first dividend product. The 'Samsung Life Insurance Daechi Tower' was sold at a 'Sales and Lease Back' method. Samsung Life Insurance has signed a contract for 5 years with a yearly rent of KRW 12.6 billion. Samsung FN REITs is expected to go public in 1H 2023.
A16: Hanhwa General Insurance Building | B16: Yeoido | C16: YBD | D16: =CONCATENATE(B16&" - "&C16) -> Yeoido - YBD | I16: 18041 | J16: =I16/0.3025 -> 59639.669 | L16: =J16*10.7639 -> 641955.44 | M16: 3.4576888e+08 | N16: 456 | O16: =N16*0.001015*1000 -> 462.84 | P16: 19165.727 | Q16: 25275761 | R16: =(N16*1000000000)/J16 -> 7645917.6 | S16: =Q16/1000000 -> 25.275761 | T16: =M16/J16 -> 5797.6324 | U16: =M16/L16 -> 538.6182 | V16: na | W16: 11 2022 | X16: Office | Y16: Freehold | AC16: Hanhwa Asset Management | AD16: Hanhwa General Insurance | AE16: Hanhwa General Insurance Building was sold and acquired by Hanhwa REITs. Hanhwa REITs is founded upon real estate assets owned by Hanhwa group and is the sponsor REITs of the group. Institutions showed much interest in Hanhwa REITs as it appointed neutral and capable board members. Hanhwa REITs is expected to go public in February 2023.
A17: Samsung Life Insurance S1 Building | B17: Sunhwa | C17: CBD | D17: =CONCATENATE(B17&" - "&C17) -> Sunhwa - CBD | I17: 8352 | J17: =I17/0.3025 -> 27609.917 | L17: =J17*10.7639 -> 297190.39 | M17: 1.4899909e+08 | N17: 196.5 | O17: =N17*0.001015*1000 -> 199.4475 | P17: 17839.929 | Q17: 23527299 | R17: =(N17*1000000000)/J17 -> 7117007.9 | S17: =Q17/1000000 -> 23.527299 | T17: =M17/J17 -> 5396.5786 | U17: =M17/L17 -> 501.35905 | V17: 0.0485 | W17: 11 2022 | X17: Office | Y17: Freehold | AC17: Samsung SRA | AD17: Samsung Life Insurance | AE17: Samsung FN REITs (Samsung Life Insurance & Samsung General Insurance) acquired 'Samsung Life Insurance S1 Building', and is looking forward to launch its first dividend product. Unlike 'Samsung Life Insurance Daechi Building' the existing tenant Samsung S1 terminated its leasing contract. Samsung Life Insurance has lent KRW 150 billion to Samsung FN REITs at 5.09% (Senior Loan). Samsung FN REITs is expected to go public in 1H 2023.
A18: Samsung Daese Building | B18: Daechi | C18: GBD | D18: =CONCATENATE(B18&" - "&C18) -> Daechi - GBD | E18: 34901 | F18: =($E$5-E18)/365 -> 30.712329 | G18: =YEAR(E18) -> 1995 | I18: 1404.1112 | J18: =I18/0.3025 -> 4641.69 | L18: =J18*10.7639 -> 49962.687 | M18: 1.3068751e+08 | N18: 163 | O18: =N18*0.001015*1000 -> 165.445 | P18: =M18/I18 -> 93074.9 | Q18: =(N18*1000000000)/I18 -> 1.1608767e+08 | R18: =(N18*1000000000)/J18 -> 35116520 | S18: =Q18/1000000 -> 116.08767 | T18: =M18/J18 -> 28155.157 | U18: =M18/L18 -> 2615.7022 | V18: na | W18: 01 2023 | X18: Office | Y18: Freehold | AC18: Bithumb Korea | AD18: Individual | AE18: The building is located in the center of GBD. Across the building is Hyundai department store and COEX. Morover, the building is right next to the 'Glass Tower' which is located in the Samsung subway station crossroad. The building was completed in year 1995 and total of 42 parking spaces are available.
A19: Seosomun J&M Building | B19: Junggu | C19: CBD | D19: =CONCATENATE(B19&" - "&C19) -> Junggu - CBD | E19: 24082 | F19: =($E$5-E19)/365 -> 60.353425 | G19: =YEAR(E19) -> 1965 | I19: 6090 | J19: =I19/0.3025 -> 20132.231 | L19: =J19*10.7639 -> 216701.33 | M19: 2.3251153e+08 | N19: 290 | O19: =N19*0.001015*1000 -> 294.35 | P19: =M19/I19 -> 38179.232 | Q19: =(N19*1000000000)/I19 -> 47619048 | R19: =(N19*1000000000)/J19 -> 14404762 | S19: =Q19/1000000 -> 47.619048 | T19: =M19/J19 -> 11549.218 | U19: =M19/L19 -> 1072.9585 | V19: na | W19: 01 2023 | X19: Office | Y19: Freehold | AC19: Civic Center PFV | AD19: Joongang Holdings | AE19: The property was sold in year 2020 but due to license issues, land purpose conversion issues, and financing issues the title transfer was occurred in January 2nd 2023.The all-in financing cost for the property was near 10% and the building will be redeveloped. The property is one of many redevelopment project near the Seoul station area.
A20: Gangnam Building | B20: Junggu | C20: CBD | D20: =CONCATENATE(B20&" - "&C20) -> Junggu - CBD | G20: =YEAR(E20) -> 1900 | I20: 1948.1393 | J20: =I20/0.3025 -> 6440.13 | L20: =J20*10.7639 -> 69320.915 | M20: Pending | N20: Pending | O20: =N20*0.001015*1000 -> #VALUE! | P20: Pending | Q20: Pending | U20: =M20/L20 -> #VALUE! | V20: Pending | W20: Pending | X20: Office | Y20: Freehold | AC20: Samsung SRA | AD20: IB Networks Co Ltd | AE20: The building is currently on sale (Starting from 2023-02-27). The building will be redeveloped under the project called 'Project EFC Office Development'. The expected completion date of the proejct is 1Q 2027. The magnitude of the development is estimated at 24-Storey (GFA: 65,719.31 sqm) office building. Bidding has begun on 7th of March 2023. Mirae Asset Capital is the preferred negotiator.
A21: Autoway Tower | B21: Daechi | C21: GBD | D21: =CONCATENATE(B21&" - "&C21) -> Daechi - GBD | E21: 41677 | F21: =($E$5-E21)/365 -> 12.147945 | G21: =YEAR(E21) -> 2014 | I21: =J21*0.3025 -> 14435.66 | J21: 47721.19 | L21: =J21*10.7639 -> 513666.12 | M21: =595000000000/1247.25 -> 4.7704951e+08 | N21: 595 | O21: =N21*0.001015*1000 -> 603.925 | P21: =M21/I21 -> 33046.602 | Q21: =(N21*1000000000)/I21 -> 41217374 | R21: =(N21*1000000000)/J21 -> 12468256 | S21: =Q21/1000000 -> 41.217374 | T21: =M21/J21 -> 9996.5971 | U21: =M21/L21 -> 928.71516 | V21: na | W21: 01 2023 | X21: Office | Y21: Freehold | AC21: Nexon | AD21: KTCU's 50% share | AE21: The buiilding is located in the prime area of the GBD close to Samsung station and Taehaeran-ro. It has achieved LEED 'Platinum' grade and GRESB '5-Star'. KCTU decided to sell the property due to lack of liquidity by KCTU members.
A22: Concordian Building | B22: Jongro | C22: CBD | D22: =CONCATENATE(B22&" - "&C22) -> Jongro - CBD | E22: 39731 | F22: =($E$5-E22)/365 -> 17.479452 | G22: =YEAR(E22) -> 2008 | I22: =J22*0.3025 -> 18360.389 | J22: 60695.5 | L22: =J22*10.7639 -> 653320.29 | M22: =629176000000/1320.01 -> 4.7664487e+08 | N22: =(M22*1320.01)/1000000000 -> 629.176 | O22: =N22*0.001015*1000 -> 638.61364 | P22: =M22/I22 -> 25960.5 | Q22: =(N22*1000000000)/I22 -> 34268120 | R22: =(N22*1000000000)/J22 -> 10366106 | S22: =Q22/1000000 -> 34.26812 | T22: =M22/J22 -> 7853.0513 | U22: =M22/L22 -> 729.57304 | V22: 0.035 | W22: 04 2023 | X22: Office | Y22: Freehold | AC22: Mastern | AD22: DWS | AE22: The building is located in the center of the CBD, and major tenants including Lotte card, Serveone (LG), and Binggrae are residing in the building. The building was initially offered at KRW 37 million per pyeong but lowered to KRW 34 million per pyeong due to increasing financing cost.
A23: Hyundai Card Building 1BL | B23: Yeongdeungpo | C23: YBD | D23: =CONCATENATE(B23&" - "&C23) -> Yeongdeungpo - YBD | E23: 33824 | F23: =($E$5-E23)/365 -> 33.663014 | G23: =YEAR(E23) -> 1992 | I23: =J23*0.3025 -> 11255 | J23: 37206.61 | L23: =J23*10.7639 -> 400488.23 | M23: =245000000000/1320.01 -> 1.8560465e+08 | N23: =(M23*1320.01)/1000000000 -> 245 | O23: =N23*0.001015*1000 -> 248.675 | P23: =M23/I23 -> 16490.863 | Q23: =(N23*1000000000)/I23 -> 21768104 | R23: =(N23*1000000000)/J23 -> 6584851.5 | S23: =Q23/1000000 -> 21.768104 | T23: =M23/J23 -> 4988.486 | U23: =M23/L23 -> 463.44597 | V23: na | W23: 04 2023 | X23: Office | Y23: Freehold | AC23: Hyundai Card Inc. | AD23: NH Amundi | AE23: The property is a Grade A office building in the YBD. Hyundai card had sold its property to enhance financial soundness according to the new accounting principles. The building offers high accessibility to public transportation and landmarks such as the National Assembly.
A24: Namsan Green Building | B24: Junggu | C24: CBD | D24: =CONCATENATE(B24&" - "&C24) -> Junggu - CBD | E24: 34503 | F24: =($E$5-E24)/365 -> 31.80274 | G24: =YEAR(E24) -> 1994 | I24: =J24*0.3025 -> 17416.298 | J24: 57574.54 | L24: =J24*10.7639 -> 619726.59 | M24: =475950000000/1328.21 -> 3.5833942e+08 | N24: =(M24*1328.21)/1000000000 -> 475.95 | O24: =N24*0.001015*1000 -> 483.08925 | P24: =M24/I24 -> 20574.947 | Q24: =(N24*1000000000)/I24 -> 27327851 | R24: =(N24*1000000000)/J24 -> 8266674.8 | S24: =Q24/1000000 -> 27.327851 | T24: =M24/J24 -> 6223.9215 | U24: =M24/L24 -> 578.22179 | V24: 0.0344 | W24: 05 2023 | X24: Office | Y24: Freehold | AC24: KKR | AD24: IGIS | AE24: The building is located in the CBD, and major tenants including SK Telecom and SK Broadband are residing in the building. The buyer plans to renovate the building and re-lease the property like the case of Samhwan building.
A25: BOK Sogong Ancilliary Building | B25: Junggu | C25: CBD | D25: =CONCATENATE(B25&" - "&C25) -> Junggu - CBD | E25: 24086 | F25: =($E$5-E25)/365 -> 60.342466 | G25: =YEAR(E25) -> 1965 | I25: =J25*0.3025 -> 4738.841 | J25: 15665.59 | L25: =J25*10.7639 -> 168622.84 | M25: =140949795115/1328.21 -> 1.0612011e+08 | N25: =(M25*1328.21)/1000000000 -> 140.9498 | O25: =N25*0.001015*1000 -> 143.06404 | P25: =M25/I25 -> 22393.685 | Q25: =(N25*1000000000)/I25 -> 29743517 | R25: =(N25*1000000000)/J25 -> 8997413.8 | S25: =Q25/1000000 -> 29.743517 | T25: =M25/J25 -> 6774.0898 | U25: =M25/L25 -> 629.33414 | V25: na | W25: 06 2023 | X25: Office | Y25: Freehold | AC25: Keppel | AD25: Bank of Korea | AE25: The CBD located building was sold by BOK as it became obsolete after the completion of its new HQ building. The increasing financing cost has decreased the transaction value by KRW 7 billion when compared to the initial offering price. The transaction includes not only the main building but also a nearby 3 storey parking lot building and land.
A26: Scale Tower (Tiger 318) | B26: Gangnam | C26: GBD | D26: =CONCATENATE(B26&" - "&C26) -> Gangnam - GBD | E26: 45016 | F26: =($E$5-E26)/365 -> 3 | G26: =YEAR(E26) -> 2023 | I26: =J26*0.3025 -> 14943.167 | J26: 49398.9 | L26: =J26*10.7639 -> 531724.82 | M26: =506400000000/1328.21 -> 3.8126501e+08 | N26: =(M26*1328.21)/1000000000 -> 506.4 | O26: =N26*0.001015*1000 -> 513.996 | P26: =M26/I26 -> 25514.337 | Q26: =(N26*1000000000)/I26 -> 33888398 | R26: =(N26*1000000000)/J26 -> 10251240 | S26: =Q26/1000000 -> 33.888398 | T26: =M26/J26 -> 7718.0871 | U26: =M26/L26 -> 717.03444 | V26: na | W26: 06 2023 | X26: Office | Y26: Freehold | AC26: Hyundai Motors Group | AD26: SK D&D (Tiger Alternative General Real Estate Trust Fund 318: 50%) | AE26: The building is located in the prime GBD area with a GFA over 15,000 pyeong (Grade A). Hyundai Motors Group was searching for an office building after selling the shares of 'Autoway Tower' to Nexon, and acquired the 'Scale Building' in a share deal for its domestic sales team.
A27: Asterium Yongsan | B27: Yongsan | C27: CBD | D27: =CONCATENATE(B27&" - "&C27) -> Yongsan - CBD | E27: 41257 | F27: =($E$5-E27)/365 -> 13.29863 | G27: =YEAR(E27) -> 2012 | I27: 3064.5 | J27: =I27/0.3025 -> 10130.579 | L27: =J27*10.7639 -> 109044.53 | M27: =(N27*1000000000)/1328.21 -> 47206391 | N27: 62.7 | O27: =N27*0.001015*1000 -> 63.6405 | P27: =M27/I27 -> 15404.272 | Q27: =(N27*1000000000)/I27 -> 20460108 | R27: =(N27*1000000000)/J27 -> 6189182.6 | S27: =Q27/1000000 -> 20.460108 | T27: =M27/J27 -> 4659.7922 | U27: =M27/L27 -> 432.90928 | V27: 0.05 | W27: 45064 | X27: Office | Y27: Freehold | AC27: Shinhan Alpha REITs | AD27: M PLUS AMC | AE27: The building is located in the CBD and is masterleased to 'LS Networks' until July 2025. Shinhan REITs acquired the asset with its blind fund established in 2022. The value of the asset is expected to increase with the construction of the new subway 'GTX-B Shinnbundang line' and the redevelopment of the Yongsan maintenance depot area.
A28: Sambu Building | B28: Junggu | C28: CBD | D28: =CONCATENATE(B28&" - "&C28) -> Junggu - CBD | E28: 30905 | F28: =($E$5-E28)/365 -> 41.660274 | G28: =YEAR(E28) -> 1984 | I28: 4616.2105 | J28: =I28/0.3025 -> 15260.2 | L28: =J28*10.7639 -> 164259.27 | M28: =(N28*1000000000)/1286.3 -> 79492342 | N28: 102.251 | O28: =N28*0.001015*1000 -> 103.78477 | P28: =M28/I28 -> 17220.259 | Q28: =(N28*1000000000)/I28 -> 22150420 | R28: =(N28*1000000000)/J28 -> 6700502 | S28: =Q28/1000000 -> 22.15042 | T28: =M28/J28 -> 5209.1285 | U28: =M28/L28 -> 483.94434 | V28: na | W28: 45110 | X28: Office | Y28: Freehold | AC28: SK D&D | AD28: IGIS | AE28: The building is located in the CBD and was acquired by SK D&D for Co-Living coversion purpose. In 2022, the office building was offered a selling price of KRW 170 billion but unsuccessful closing a deal due to surging construction and financing cost. The building was originally acquired by IGIS AMC in year 2021 from Samik Instruments.
A29: Lotte Homeshoping Yangpyeong-dong HQ | B29: Yeongdeungpogu | C29: YBD | D29: =CONCATENATE(B29&" - "&C29) -> Yeongdeungpogu - YBD | E29: 40199 | F29: =($E$5-E29)/365 -> 16.19726 | G29: =YEAR(E29) -> 2010 | I29: 13739.396 | J29: =I29/0.3025 -> 45419.49 | L29: =J29*10.7639 -> 488890.85 | M29: =(N29*1000000000)/1313.47 -> 1.5519959e+08 | N29: 203.85 | O29: =N29*0.001015*1000 -> 206.90775 | P29: =M29/I29 -> 11295.954 | Q29: =(N29*1000000000)/I29 -> 14836897 | R29: =(N29*1000000000)/J29 -> 4488161.4 | S29: =Q29/1000000 -> 14.836897 | T29: =M29/J29 -> 3417.0262 | U29: =M29/L29 -> 317.45243 | V29: 0.027186657 | W29: 45170 | X29: Office | Y29: Freehold | AC29: Woori Home Shopping (Lotte Home Shopping) | AD29: Lotte Corportation (64.6%), Lotte Well Food (35.4%) | AE29: The building is located in the YBD and 'Woori Home Shopping (Lotte Home Shopping)' made an public announcement that it will acquire the office building at KRW 203.9 billion. 'Woori Home Shopping (Lotte Home Shopping)' decided to acquire the asset in order to save rent and enhance the workplace environment. Lotte Group is exepected to make a capital gain worth KRW 130 billion via this deal.
A30: HJ Heavy Industry Seoul HQ Building | B30: Yongsan | C30: CBD | D30: =CONCATENATE(B30&" - "&C30) -> Yongsan - CBD | E30: 39582 | F30: =($E$5-E30)/365 -> 17.887671 | G30: =YEAR(E30) -> 2008 | I30: 9615.6341 | J30: =I30/0.3025 -> 31787.22 | L30: =J30*10.7639 -> 342154.46 | M30: =(N30*1000000000)/1286.3 -> 1.7569774e+08 | N30: 226 | O30: =N30*0.001015*1000 -> 229.39 | P30: =M30/I30 -> 18272.091 | Q30: =(N30*1000000000)/I30 -> 23503390 | R30: =(N30*1000000000)/J30 -> 7109775.6 | S30: =Q30/1000000 -> 23.50339 | T30: =M30/J30 -> 5527.3074 | U30: =M30/L30 -> 513.50416 | V30: na | W30: 45138 | X30: Office | Y30: Freehold | AC30: KOREIT | AD30: KORAMCO TRUST | AE30: The building is located in the CBD and was a 'Sale and Leaseback' transaction. HJ Heavy Industry, the anchor tenant and the previous owner of the asset, had delegated its 'Buy Back Option' to KOREIT. KOREIT is exepected to add the asset into its REITs.
A31: Yongsan The Prime Tower | B31: Yongsan | C31: CBD | D31: =CONCATENATE(B31&" - "&C31) -> Yongsan - CBD | E31: 41662 | F31: =($E$5-E31)/365 -> 12.189041 | G31: =YEAR(E31) -> 2014 | I31: 11800.465 | J31: =I31/0.3025 -> 39009.801 | L31: =J31*10.7639 -> 419897.6 | M31: =(N31*1000000000)/1318.47 -> 1.8079289e+08 | N31: 238.37 | O31: =N31*0.001015*1000 -> 241.94555 | P31: =M31/I31 -> 15320.828 | Q31: =(N31*1000000000)/I31 -> 20200052 | R31: =(N31*1000000000)/J31 -> 6110515.7 | S31: =Q31/1000000 -> 20.200052 | T31: =M31/J31 -> 4634.5504 | U31: =M31/L31 -> 430.56424 | V31: 0.037 | W31: 45149 | X31: Office | Y31: Freehold | AC31: IGIS AMC | AD31: Shinhan Alpha REITs | AE31: The building is located in the CBD and Shinhan Alpha REITs made an capital gain of KRW 73 billion through this deal. The asset was acquired at KRW 14 million/pyeong five years ago and was sold at KRW 20 million/ peyong. For the past five years the asset maintained an average occupancy rate of 99%.
A32: Posco Tower Yeoksam | B32: Gangnam | C32: GBD | D32: =CONCATENATE(B32&" - "&C32) -> Gangnam - GBD | E32: 37806 | F32: =($E$5-E32)/365 -> 22.753425 | G32: =YEAR(E32) -> 2003 | I32: 13068.838 | J32: =I32/0.3025 -> 43202.77 | L32: =J32*10.7639 -> 465030.3 | M32: =(N32*1000000000)/1318.47 -> 1.1585322e+08 | N32: 152.749 | O32: =N32*0.001015*1000 -> 155.04023 | P32: =M32/I32 -> 8864.8451 | Q32: =(N32*1000000000)/I32 -> 11688032 | R32: =(N32*1000000000)/J32 -> 3535629.8 | S32: =Q32/1000000 -> 11.688032 | T32: =M32/J32 -> 2681.6156 | U32: =M32/L32 -> 249.13049 | V32: *4.9% (estimated) | W32: 45152 | X32: Office | Y32: Freehold | AC32: Posco Holdings | AD32: Q Sone | AE32: The building is located in the center of the GBD. Posco Holdings acquired the building by buying 'Q Sone' who owned the asset. Major tenants include Tesla Korea and Mugunghwa Trust .
A33: Tower 8 | B33: Jongro | C33: CBD | D33: =CONCATENATE(B33&" - "&C33) -> Jongro - CBD | E33: 42118 | F33: =($E$5-E33)/365 -> 10.939726 | G33: =YEAR(E33) -> 2015 | I33: 15625.48 | J33: =I33/0.3025 -> 51654.48 | L33: =J33*10.7639 -> 556003.66 | M33: =(N33*1000000000)/1318.47 -> 4.1639173e+08 | N33: 549 | O33: =N33*0.001015*1000 -> 557.235 | P33: =M33/I33 -> 26648.252 | Q33: =(N33*1000000000)/I33 -> 35134920 | R33: =(N33*1000000000)/J33 -> 10628313 | S33: =Q33/1000000 -> 35.13492 | T33: =M33/J33 -> 8061.0961 | U33: =M33/L33 -> 748.90106 | V33: 0.038 | W33: 45156 | X33: Office | Y33: Freehold | AC33: Credit Union, Mirae Asset | AD33: DWS | AE33: The building is located in the CBD and recorded an higher value than the 'Concordian Building' deal at KRW 35 million/pyeong. Tenants include Pan Ocean (Halim Group), Expedia Korea, HIS Korea, and CJ Daehantongeun. DWS had acquired the asset at KRW 325 billion in 2015 and expected to make a capital gain over KRW 220 billion.
A34: Citi Bank Center Korea | B34: Jongro-gu | C34: CBD | D34: =CONCATENATE(B34&" - "&C34) -> Jongro-gu - CBD | E34: 32105 | F34: =($E$5-E34)/365 -> 38.372603 | G34: =YEAR(E34) -> 1987 | I34: 5974.5565 | J34: =I34/0.3025 -> 19750.6 | L34: =J34*10.7639 -> 212593.48 | M34: =(N34*1000000000)/1329.47 -> 1.2582984e+08 | N34: 167.287 | O34: =N34*0.001015*1000 -> 169.79631 | P34: =M34/I34 -> 21060.951 | Q34: =(N34*1000000000)/I34 -> 27999903 | R34: =(N34*1000000000)/J34 -> 8469970.5 | S34: =Q34/1000000 -> 27.999903 | T34: =M34/J34 -> 6370.9377 | U34: =M34/L34 -> 591.88005 | V34: 0.04 | W34: 45181 | X34: Office | Y34: Freehold | AC34: Keppel | AD34: Capitaland | AE34: The building is located in the CBD and is 100% occupied by Citi Bank until Feb 17th 2029. There is a value-up opportunity regarding FAR as it has additional room of 246% FAR.
A35: Majestar Tower 1 | B35: Seocho-gu | C35: GBD | D35: =CONCATENATE(B35&" - "&C35) -> Seocho-gu - GBD | E35: 42915 | F35: =($E$5-E35)/365 -> 8.7561644 | G35: =YEAR(E35) -> 2017 | I35: 14090.704 | J35: =I35/0.3025 -> 46580.84 | L35: =J35*10.7639 -> 501391.5 | M35: =(N35*1000000000)/1350.69 -> 3.8498841e+08 | N35: 520 | O35: =N35*0.001015*1000 -> 527.8 | P35: =M35/I35 -> 27322.156 | Q35: =(N35*1000000000)/I35 -> 36903763 | R35: =(N35*1000000000)/J35 -> 11163388 | S35: =Q35/1000000 -> 36.903763 | T35: =M35/J35 -> 8264.9521 | U35: =M35/L35 -> 767.83992 | V35: 0.041778579 | W35: 45217 | X35: Office | Y35: Freehold | AC35: KORAMCO Asset Trust & NH Investment Securities | AD35: IGIS (Invesco) | AE35: The building is located in the GBD and acquired the highest LEED Grade by the USGBC: Platinum. The buyer KORAMCO Asset Trust is now the owner of both 'Majestar Tower 1' and 'Majestar Tower 2' which they have acquired in 2017 and managed since.
A36: Musinsa Campus E1 | B36: Seongdong-gu | C36: Others | D36: =CONCATENATE(B36&" - "&C36) -> Seongdong-gu - Others | E36: 25628 | F36: =($E$5-E36)/365 -> 56.117808 | G36: =YEAR(E36) -> 1970 | I36: 5599.753 | J36: =I36/0.3025 -> 18511.58 | L36: =J36*10.7639 -> 199256.8 | M36: =(N36*1000000000)/1350.69 -> 82562246 | N36: 111.516 | O36: =N36*0.001015*1000 -> 113.18874 | P36: =M36/I36 -> 14743.909 | Q36: =(N36*1000000000)/I36 -> 19914450 | R36: =(N36*1000000000)/J36 -> 6024121.1 | S36: =Q36/1000000 -> 19.91445 | T36: =M36/J36 -> 4460.0324 | U36: =M36/L36 -> 414.35097 | V36: na | W36: 45204 | X36: Office | Y36: Freehold | AC36: Mastern | AD36: Musinsa | AE36: The building is located in Seongdong-gu which is the uprising business disctricts for tech and startups. The property in particular is situated in the 'Seongsu IT district unit planning zone' which will be the center of the newly constructed office building zone. This was a 'Sale and Leaseback' deal where 'Musinsa' will lease the area for 15 years.
A37: Samsung SDS Tower | B37: Songpa-gu | C37: GBD | D37: =CONCATENATE(B37&" - "&C37) -> Songpa-gu - GBD | E37: 41761 | F37: =($E$5-E37)/365 -> 11.917808 | G37: =YEAR(E37) -> 2014 | I37: =J37*0.3025 -> 30109.924 | J37: 99536.94 | L37: =J37*10.7639 -> 1071405.7 | M37: =(N37*1000000000)/1350.69 -> 6.2930798e+08 | N37: 850 | O37: =N37*0.001015*1000 -> 862.75 | P37: =M37/I37 -> 20900.351 | Q37: =(N37*1000000000)/I37 -> 28229895 | R37: =(N37*1000000000)/J37 -> 8539543.2 | S37: =Q37/1000000 -> 28.229895 | T37: =M37/J37 -> 6322.3561 | U37: =M37/L37 -> 587.36667 | V37: 0.0412 | W37: 45226 | X37: Office | Y37: Freehold | AC37: KB AMC | AD37: Ryukyung PSG | AE37: The building is located in the GBD and is occupied by 'Samsung SDS' (Headquarters) until the end of June 2034. The transaction recorded the highest value in 2023 surpassing the previous record holder 'Pangyo Alphadom' by KRW122 billion.
A38: HSBC Building | B38: Jung-gu | C38: CBD | D38: =CONCATENATE(B38&" - "&C38) -> Jung-gu - CBD | E38: 33728 | F38: =($E$5-E38)/365 -> 33.926027 | G38: =YEAR(E38) -> 1992 | I38: 7505.6512 | J38: =I38/0.3025 -> 24812.07 | L38: =J38*10.7639 -> 267074.64 | M38: =(N38*1000000000)/1310.39 -> 1.3812682e+08 | N38: 181 | O38: =N38*0.001015*1000 -> 183.715 | P38: =M38/I38 -> 18403.042 | Q38: =(N38*1000000000)/I38 -> 24115163 | R38: =(N38*1000000000)/J38 -> 7294836.7 | S38: =Q38/1000000 -> 24.115163 | T38: =M38/J38 -> 5566.9203 | U38: =M38/L38 -> 517.18432 | V38: 0.044 | W38: 45260 | X38: Office | Y38: Freehold | AC38: Shinhan Alpha REITs | AD38: KCLAVIS AMC (Prain Global) | AE38: The building is located in the CBD and was a strata deal: B1F, 8F-18F, GFA 24,812.07sq. m. (66%). The property had a 100% occupancy rate with anchor tenants including IBK, Prain Global, and S-Oil. The HSBC buiilding transaction was the benificiary of the nearby development cases around the Seoul Station and was sold at a higher value than the seller's expectation.
A39: Bundang Seohyun Building | B39: Bundang-gu | C39: BBD | D39: =CONCATENATE(B39&" - "&C39) -> Bundang-gu - BBD | E39: 35814 | F39: =($E$5-E39)/365 -> 28.210959 | G39: =YEAR(E39) -> 1998 | I39: =J39*0.3025 -> 5275.3731 | J39: 17439.25 | L39: =J39*10.7639 -> 187714.34 | M39: =(N39*1000000000)/1310.39 -> 72192248 | N39: 94.6 | O39: =N39*0.001015*1000 -> 96.019 | P39: =M39/I39 -> 13684.766 | Q39: =(N39*1000000000)/I39 -> 17932381 | R39: =(N39*1000000000)/J39 -> 5424545.2 | S39: =Q39/1000000 -> 17.932381 | T39: =M39/J39 -> 4139.6418 | U39: =M39/L39 -> 384.58568 | V39: 0.049 | W39: 45265 | X39: Office | Y39: Freehold | AC39: Vestas AMC | AD39: Kyobo Asset Trust | AE39: The building is located in the prime business and retail are of the BBD. The property had a 100% occupancy rate with anchor tenants including Keyence, AK S&D, and Danal. The property inherits a value-add opportunity of an additional GFA of 4,347 sq. m. when newly constructed.
A40: Centerpoint Gangnam | B40: Gangnam-gu | C40: GBD | D40: =CONCATENATE(B40&" - "&C40) -> Gangnam-gu - GBD | E40: 45505 | F40: =($E$5-E40)/365 -> 1.660274 | G40: =YEAR(E40) -> 2024 | I40: =J40*0.3025 -> 7837.9444 | J40: 25910.56 | L40: =J40*10.7639 -> 278898.68 | M40: =(N40*1000000000)/1310.39 -> 2.6222892e+08 | N40: 343.62216 | O40: =N40*0.001015*1000 -> 348.77649 | P40: =M40/I40 -> 33456.339 | Q40: =(N40*1000000000)/I40 -> 43840852 | R40: =(N40*1000000000)/J40 -> 13261858 | S40: =Q40/1000000 -> 43.840852 | T40: =M40/J40 -> 10120.543 | U40: =M40/L40 -> 940.23008 | V40: 0.039 | W40: 45288 | X40: Office | Y40: Freehold | AC40: Mastern | AD40: F&F | AE40: The building is located in GBD and is a forward purchase deal acquired by the strategic investor (SI) 'F&F'. 'F&F' was the preferred bidder for 'Majestar 1' in 2023. The building will be used as the new headquarters for 'F&F'.
A41: Gwanghwamun G Tower | B41: Jongro-gu | C41: CBD | D41: =CONCATENATE(B41&" - "&C41) -> Jongro-gu - CBD | E41: 42328 | F41: =($E$5-E41)/365 -> 10.364384 | G41: =YEAR(E41) -> 2015 | I41: 10511.028 | J41: =I41/0.3025 -> 34747.2 | L41: =J41*10.7639 -> 374015.39 | M41: =(N41*1000000000)/1331.74 -> 2.1700933e+08 | N41: 289 | O41: =N41*0.001015*1000 -> 293.335 | P41: =M41/I41 -> 20645.871 | Q41: =(N41*1000000000)/I41 -> 27494932 | R41: =(N41*1000000000)/J41 -> 8317216.9 | S41: =Q41/1000000 -> 27.494932 | T41: =M41/J41 -> 6245.3759 | U41: =M41/L41 -> 580.21497 | V41: 0.044 | W41: 45379 | X41: Office | Y41: Freehold | AC41: Shinhan REITs | AD41: IGIS (KB Bank) | AE41: The building is located in the CBD and is comprised of accomodation (hotel), office, and retail. Major tenants include Shilla Stay, BRK, Starbucks, etc. The occupancy rate at the acquisition period was recorded at 97.1%.
A42: Jamsil Sigma Tower | B42: Songpa-gu | C42: GBD | D42: =CONCATENATE(B42&" - "&C42) -> Songpa-gu - GBD | E42: 35426 | F42: =($E$5-E42)/365 -> 29.273973 | G42: =YEAR(E42) -> 1996 | I42: 8413.735 | J42: =I42/0.3025 -> 27814 | L42: =J42*10.7639 -> 299387.11 | M42: =(N42*1000000000)/1331.74 -> 1.2389806e+08 | N42: 165 | O42: =N42*0.001015*1000 -> 167.475 | P42: =M42/I42 -> 14725.691 | Q42: =(N42*1000000000)/I42 -> 19610791 | R42: =(N42*1000000000)/J42 -> 5932264.3 | S42: =Q42/1000000 -> 19.610791 | T42: =M42/J42 -> 4454.5214 | U42: =M42/L42 -> 413.83898 | V42: 0.048 | W42: 45355 | X42: Office | Y42: Freehold | AC42: RIFA AMC (Aberdeen) | AD42: Together AMC | AE42: The building is located in the GBD and is a residential and office mixed property. The deal was a strata deal and was limited to the entire office proportion of the building (1F-2F, 4F-11F) and excluding the apartment area.
A43: T412 | B43: Gangnam-gu | C43: GBD | D43: =CONCATENATE(B43&" - "&C43) -> Gangnam-gu - GBD | E43: 36768 | F43: =($E$5-E43)/365 -> 25.59726 | G43: =YEAR(E43) -> 2000 | I43: 7982.609 | J43: =I43/0.3025 -> 26388.79 | L43: =J43*10.7639 -> 284046.3 | M43: =(N43*1000000000)/1331.74 -> 2.4606905e+08 | N43: 327.7 | O43: =N43*0.001015*1000 -> 332.6155 | P43: =M43/I43 -> 30825.643 | Q43: =(N43*1000000000)/I43 -> 41051741 | R43: =(N43*1000000000)/J43 -> 12418152 | S43: =Q43/1000000 -> 41.051741 | T43: =M43/J43 -> 9324.7569 | U43: =M43/L43 -> 866.2991 | V43: 0.04 | W43: 45380 | X43: Office | Y43: Freehold | AC43: Allerman | AD43: Hanhwa AMC | AE43: The building is located in the prime loaction in the GBD near to the Hyundai Motors Group HQ project GBC. The property was acquired by Allerman, bedding product manufacturing company, and will be used as its headquarter. The building has an high accessibility to public transportation and the nearest subway is 2 minutes by walk: Seolleung Station (Line 2).
A44: Arc Place | B44: Gangnam-gu | C44: GBD | D44: =CONCATENATE(B44&" - "&C44) -> Gangnam-gu - GBD | E44: 35853 | F44: =($E$5-E44)/365 -> 28.10411 | G44: =YEAR(E44) -> 1998 | I44: 18974.406 | J44: =I44/0.3025 -> 62725.31 | L44: =J44*10.7639 -> 675168.96 | M44: =(N44*1000000000)/1331.74 -> 5.944852e+08 | N44: 791.69972 | O44: =N44*0.001015*1000 -> 803.57522 | P44: =M44/I44 -> 31330.899 | Q44: =(N44*1000000000)/I44 -> 41724611 | R44: =(N44*1000000000)/J44 -> 12621695 | S44: =Q44/1000000 -> 41.724611 | T44: =M44/J44 -> 9477.5969 | U44: =M44/L44 -> 880.49842 | V44: 0.043 | W44: 45371 | X44: Office | Y44: Freehold | AC44: KORAMCO (KTCU) | AD44: Blackstone | AE44: The building is located in the prime location in the GBD and was acquired by KORAMCO Asset Trust. The communal areas including the lobby were renovated in year 2018 and the occupancy rate at the point of acquisition was recorded at 100%. Notable tenants include Warner Bros Korea, Dyson, Ebay, and Lotte Capital.
A45: *K Square City | B45: Jung-gu | C45: CBD | D45: =CONCATENATE(B45&" - "&C45) -> Jung-gu - CBD | E45: 35642 | F45: =($E$5-E45)/365 -> 28.682192 | G45: =YEAR(E45) -> 1997 | I45: 8320.7871 | J45: =I45/0.3025 -> 27506.734 | L45: =J45*10.7639 -> 296079.74 | M45: =(N45*1000000000)/1331.74 -> 2.3052548e+08 | N45: 307 | O45: =N45*0.001015*1000 -> 311.605 | P45: =M45/I45 -> 27704.768 | Q45: =(N45*1000000000)/I45 -> 36895548 | R45: =(N45*1000000000)/J45 -> 11160903 | S45: =Q45/1000000 -> 36.895548 | T45: =M45/J45 -> 8380.6924 | U45: =M45/L45 -> 778.59255 | V45: 0.039 | W45: 45372 | X45: Office | Y45: Freehold | AC45: Pacific AMC (Dongyang Iife Insurance) | AD45: KORAMCO Asset Trust REITs (KTCU, POBA, NH) | AE45: The building is located in the CBD near to the Cheonggyecheon. This was a strata deal involving 66% of the total GFA: B2-13F, 19F-20F. This was one of the value-add projects of the KORAMCO Asset Trust where building was fully renovated in July 2021 with floor extensions and machinery/electricity equipment changes. The seller was able to save value from the strata deal by adding the management right of the entire building in the deal.
A46: Icon Yeoksam | B46: Gangnam-gu | C46: GBD | D46: =CONCATENATE(B46&" - "&C46) -> Gangnam-gu - GBD | E46: 43028 | F46: =($E$5-E46)/365 -> 8.4465753 | G46: =YEAR(E46) -> 2017 | I46: 5922.8381 | J46: =I46/0.3025 -> 19579.63 | L46: =J46*10.7639 -> 210753.18 | M46: =(N46*1000000000)/1331.74 -> 1.5343686e+08 | N46: 204.338 | O46: =N46*0.001015*1000 -> 207.40307 | P46: =M46/I46 -> 25905.969 | Q46: =(N46*1000000000)/I46 -> 34500015 | R46: =(N46*1000000000)/J46 -> 10436254 | S46: =Q46/1000000 -> 34.500015 | T46: =M46/J46 -> 7836.5555 | U46: =M46/L46 -> 728.04053 | V46: 0.04 | W46: 45380 | X46: Office | Y46: Freehold | AC46: Capstone AMC (Shinsegae Property, Korea Post) | AD46: Capitaland (M&G)
A47: Seoulleung WeWork Tower | B47: Gangnam-gu | C47: GBD | D47: =CONCATENATE(B47&" - "&C47) -> Gangnam-gu - GBD | E47: 34323 | F47: =($E$5-E47)/365 -> 32.29589 | G47: =YEAR(E47) -> 1993 | I47: 4559.8426 | J47: =I47/0.3025 -> 15073.86 | L47: =J47*10.7639 -> 162253.52 | M47: =(N47*1000000000)/1331.74 -> 1.1038191e+08 | N47: 147 | O47: =N47*0.001015*1000 -> 149.205 | P47: =M47/I47 -> 24207.394 | Q47: =(N47*1000000000)/I47 -> 32237955 | R47: =(N47*1000000000)/J47 -> 9751981.2 | S47: =Q47/1000000 -> 32.237955 | T47: =M47/J47 -> 7322.7366 | U47: =M47/L47 -> 680.30515 | V47: 0.038 | W47: 45422 | X47: Office | Y47: Freehold | AC47: Hyunjin Group | AD47: Shinhan REITs AMC | AE47: The building is located in the prime location in the GBD and is within 700m to two subway stations: Seolleung Station Line 2 and Sooinbundang Line. Moreover, it is near to the HMG GBC project and the new GTX which are valuable factors for additional future capital gain. The building is currently 100% master leased to We Work.
A48: Golden Tower | B48: Gangnam-gu | C48: GBD | D48: =CONCATENATE(B48&" - "&C48) -> Gangnam-gu - GBD | E48: 35039 | F48: =($E$5-E48)/365 -> 30.334247 | G48: =YEAR(E48) -> 1995 | I48: 12245.218 | J48: =I48/0.3025 -> 40480.06 | L48: =J48*10.7639 -> 435723.32 | M48: =(N48*1000000000)/1331.74 -> 3.3099554e+08 | N48: 440.8 | O48: =N48*0.001015*1000 -> 447.412 | P48: =M48/I48 -> 27030.596 | Q48: =(N48*1000000000)/I48 -> 35997725 | R48: =(N48*1000000000)/J48 -> 10889312 | S48: =Q48/1000000 -> 35.997725 | T48: =M48/J48 -> 8176.7552 | U48: =M48/L48 -> 759.64615 | V48: 0.033 | W48: 45490 | X48: Office | Y48: Freehold | AC48: Capitaland (50%) + KB Bank (50%) | AD48: KORAMCO REITs (NPS: 100%) | AE48: The building is located in the prime location in the GBD and was acquired by Capitaland. Anchor tenants include, Koramco Trust, Acuon Capital, Ford, and Simmons. Golden Tower was first negotiated around the KRW40 million per pyeong level with the preferred bidder Daeshin Asset Trust but dropped out in the process and was acquired at KRW 36 million per pyeong with the second highest bidder.
A49: City Square Building | B49: Jung-gu | C49: CBD | D49: =CONCATENATE(B49&" - "&C49) -> Jung-gu - CBD | E49: 43656 | F49: =($E$5-E49)/365 -> 6.7260274 | G49: =YEAR(E49) -> 2019 | I49: 11570.9 | J49: =I49/0.3025 -> 38250.91 | L49: =J49*10.7639 -> 411728.97 | M49: =(N49*1000000000)/1331.74 -> 3.2147641e+08 | N49: 428.123 | O49: =N49*0.001015*1000 -> 434.54485 | P49: =M49/I49 -> 27783.181 | Q49: =(N49*1000000000)/I49 -> 36999973 | R49: =(N49*1000000000)/J49 -> 11192492 | S49: =Q49/1000000 -> 36.999973 | T49: =M49/J49 -> 8404.4122 | U49: =M49/L49 -> 780.7962 | V49: 0.035 | W49: 45502 | X49: Office | Y49: Freehold | AC49: Shinhan REITs (Hyundai Corporation) | AD49: Hangang AMC | AE49: The building is located in the CBD and was acquired by Shinhan REITs. The property is a LEED Platinum certiified builing and has a average floor height of 2.8 meters. In terms of tenancy, the Seoul Metropolitan Government is occupying more than 80% of the GLA and will lease the area until December 2029. The occupancy rate was recorded at 100% at the point of acquisition.
A50: **Hanhwa HQ (Block 1: Office) | B50: Jung-gu | C50: CBD | D50: =CONCATENATE(B50&" - "&C50) -> Jung-gu - CBD | E50: 32078 | F50: =($E$5-E50)/365 -> 38.446575 | G50: =YEAR(E50) -> 1987 | I50: 22495.5 | J50: =I50/0.3025 -> 74365.29 | L50: =J50*10.7639 -> 800460.55 | M50: =(N50*1000000000)/1331.74 -> 6.0672504e+08 | N50: 808 | O50: =N50*0.001015*1000 -> 820.12 | P50: =M50/I50 -> 26970.951 | Q50: =(N50*1000000000)/I50 -> 35918294 | R50: =(N50*1000000000)/J50 -> 10865284 | S50: =Q50/1000000 -> 35.918294 | T50: =M50/J50 -> 8158.7127 | U50: =M50/L50 -> 757.96995 | V50: 0.047 | W50: 45532 | X50: Office | Y50: Freehold | AC50: Hanhwa REITs | AD50: Hanhwa Life Insurance | AE50: The building is located in the prime location in the CBD and was acquired by Hanhwa REITS which is the specially related legal entity to the seller: Hanhwa Life Insurance. The building was renovated in November 2019 and tenants include the majority of the Hanhwa Group subsidiaries including Hanhwa Impact, E&C, System, Energy, ICT, Global etc. With a 100% occupancy rate at the point of transaction, the seller sold the building to enhance financial solvency and acquire cash.
A51: Myeongdong N Buidling | B51: Jung-gu | C51: CBD | D51: =CONCATENATE(B51&" - "&C51) -> Jung-gu - CBD | E51: 25986 | F51: =($E$5-E51)/365 -> 55.136986 | G51: =YEAR(E51) -> 1971 | I51: 4159.0876 | J51: =I51/0.3025 -> 13749.05 | L51: =J51*10.7639 -> 147993.4 | M51: =(N51*1000000000)/1331.74 -> 1.2023743e+08 | N51: 160.125 | O51: =N51*0.001015*1000 -> 162.52688 | P51: =M51/I51 -> 28909.57 | Q51: =(N51*1000000000)/I51 -> 38500030 | R51: =(N51*1000000000)/J51 -> 11646259 | S51: =Q51/1000000 -> 38.50003 | T51: =M51/J51 -> 8745.1448 | U51: =M51/L51 -> 812.45133 | V51: 0.043 | W51: 45525 | X51: Office | Y51: Freehold | AC51: D&D Platform REITs | AD51: SK D&D | AE51: The building is located in the prime retail and office location in the CBD, and was acquired by D&D Platform REITs which is the specially related legal entity to the seller: SK D&D. The building was developed by SK D&D and is the mother company of the DDI Platform REITs. The SK Group aimed to bring capital gain to the SK D&D and help boost the stock value of the DDI Platform REITs by acquiring a prime asset in the CBD area. SK D&D has invested in common shares worth KRW13 billion in the transaction due to lack of liquidity in the market.
A52: Fastfive Tower | B52: Jung-gu | C52: CBD | D52: =CONCATENATE(B52&" - "&C52) -> Jung-gu - CBD | E52: 34682 | F52: =($E$5-E52)/365 -> 31.312329 | G52: =YEAR(E52) -> 1994 | I52: 4567.2599 | J52: =I52/0.3025 -> 15098.38 | L52: =J52*10.7639 -> 162517.45 | M52: =(N52*1000000000)/1331.74 -> 89552766 | N52: 119.261 | O52: =N52*0.001015*1000 -> 121.04992 | P52: =M52/I52 -> 19607.547 | Q52: =(N52*1000000000)/I52 -> 26112155 | R52: =(N52*1000000000)/J52 -> 7898926.9 | S52: =Q52/1000000 -> 26.112155 | T52: =M52/J52 -> 5931.2831 | U52: =M52/L52 -> 551.03476 | V52: 0.039 | W52: 45539 | X52: Office | Y52: Freehold | AC52: Shinhan REITs AMC | AD52: KR Dadong | AE52: The building is located in the CBD property and was acquired by Shinhan REITs AMC via auction. The property was in a troubled situation in a debtor-controlled sale. The acquisition price was at the 72.7% level of the appraised value. The buyer is planning a value-add project including redevelopment and adding extra space.
A53: ***Taeyoung HQ | B53: Yeongdeungpo-gu | C53: YBD | D53: =CONCATENATE(B53&" - "&C53) -> Yeongdeungpo-gu - YBD | E53: 39167 | F53: =($E$5-E53)/365 -> 19.024658 | G53: =YEAR(E53) -> 2007 | I53: 12326.451 | J53: =I53/0.3025 -> 40748.6 | L53: =J53*10.7639 -> 438613.86 | M53: =(N53*1000000000)/1331.74 -> 1.7270638e+08 | N53: 230 | O53: =N53*0.001015*1000 -> 233.45 | P53: =M53/I53 -> 14011.038 | Q53: =(N53*1000000000)/I53 -> 18659060 | R53: =(N53*1000000000)/J53 -> 5644365.7 | S53: =Q53/1000000 -> 18.65906 | T53: =M53/J53 -> 4238.3391 | U53: =M53/L53 -> 393.75497 | V53: 0.047 | W53: 45539 | X53: Office | Y53: Freehold | AC53: TY number 1 CR REITs (DDI) | AD53: Taeyoung Construction | AE53: The building is located in the YBD and was acquired by a TY number 1 Corporate Restructuring REITs established by DDI. The property was sold in the workout process of the Taeyoung Group in a sale and lease back acquisition form. Taeyoung group sold the property to enhance financial insolvency issues and acquire cash.
A54: The Asset Gangnam | B54: Seocho-gu | C54: GBD | D54: =CONCATENATE(B54&" - "&C54) -> Seocho-gu - GBD | E54: 39440 | F54: =($E$5-E54)/365 -> 18.276712 | G54: =YEAR(E54) -> 2007 | I54: =J54*0.3025 -> 24537.977 | J54: 81117.28 | L54: =J54*10.7639 -> 873138.29 | M54: =(N54*1000000000)/1331.74 -> 8.2914082e+08 | N54: 1104.2 | O54: =N54*0.001015*1000 -> 1120.763 | P54: =M54/I54 -> 33790.105 | Q54: =(N54*1000000000)/I54 -> 44999634 | R54: =(N54*1000000000)/J54 -> 13612389 | S54: =Q54/1000000 -> 44.999634 | T54: =M54/J54 -> 10221.507 | U54: =M54/L54 -> 949.60997 | V54: 0.0311 | W54: 45560 | X54: Office | Y54: Freehold | AC54: KORAMCO Asset Trust | AD54: Samsung SRA | AE54: The building is located in the GBD and is directly connected to the Gangnam subway station. As of January 2024, there were 13 tenants including Samsung Fire & Insurance and the occupancy rate was recorded at 100% in 1Q 2024.
A55: The Exchange Seoul + The Exchange Seoul Mall | B55: Jung-gu | C55: CBD | D55: =CONCATENATE(B55&" - "&C55) -> Jung-gu - CBD | E55: 29556 | F55: =($E$5-E55)/365 -> 45.356164 | G55: =YEAR(E55) -> 1980 | H55: 44 years (Built in 1980) | I55: =J55*0.3025 -> 9383.9584 | J55: 31021.35 | K55: 31,021 sq. m. (9,384 py) | L55: =J55*10.7639 -> 333910.71 | M55: =(N55*1000000000)/1331.74 -> 1.8601979e+08 | N55: 247.73 | O55: =N55*0.001015*1000 -> 251.44595 | P55: =M55/I55 -> 19823.169 | Q55: =(N55*1000000000)/I55 -> 26399307 | R55: =(N55*1000000000)/J55 -> 7985790.4 | S55: =Q55/1000000 -> 26.399307 | T55: =M55/J55 -> 5996.5087 | U55: =M55/L55 -> 557.09442 | V55: 0.04 | W55: 45576 | X55: Office + Mall | Y55: Freehold | Z55: Asset Deal | AA55: N/A | AB55: =V55 -> 0.04 | AC55: KORAMCO Asset Trust | AD55: GIC | AE55: The building is located in the prime CBD location and was completed in 1980. The property is a subject to a possible redevelopment deal as it is included in the Seoul City renovation and development district number 4. The buyer is planning to redevelop the property.
A56: Mirae Asset Yeouido HQ | B56: Yeongdeungpo-gu | C56: YBD | D56: =CONCATENATE(B56&" - "&C56) -> Yeongdeungpo-gu - YBD | E56: 31045 | F56: =($E$5-E56)/365 -> 41.276712 | G56: =YEAR(E56) -> 1984 | H56: 40 years (Built in 1984) | I56: =J56*0.3025 -> 11823.966 | J56: 39087.49 | K56: 39,087 sq. m. (11,824 py) | L56: =J56*10.7639 -> 420733.83 | M56: =(N56*1000000000)/1331.74 -> 2.7985943e+08 | N56: 372.7 | O56: =N56*0.001015*1000 -> 378.2905 | P56: =M56/I56 -> 23668.83 | Q56: =(N56*1000000000)/I56 -> 31520727 | R56: =(N56*1000000000)/J56 -> 9535020 | S56: =Q56/1000000 -> 31.520727 | T56: =M56/J56 -> 7159.821 | U56: =M56/L56 -> 665.16978 | V56: n.a. | W56: 45565 | X56: Office | Y56: Freehold | Z56: Asset Deal | AA56: N/A | AB56: N/A | AC56: Woori AMC | AD56: Mirae Asset Securities | AE56: The building is located in the YBD and was acquired by the Woori AMC to to demolish the existing building and construct the headquarter building of the Woori Group. Subsidiaries of the Woori Group including Woori Investment Securities, Woori Card, and Woori Bank are expected to move into the new HQ building.
A57: Jeongdong Building | B57: Jung-gu | C57: CBD | D57: =CONCATENATE(B57&" - "&C57) -> Jung-gu - CBD | E57: 28846 | F57: =($E$5-E57)/365 -> 47.30137 | G57: =YEAR(E57) -> 1978 | H57: 46 years (Built in 1978) | I57: =J57*0.3025 -> 11901.303 | J57: 39343.15 | K57: 39,343 sq. m. (11,901 py) | L57: =J57*10.7639 -> 423485.73 | M57: =(N57*1000000000)/1331.74 -> 2.6281406e+08 | N57: 350 | O57: =N57*0.001015*1000 -> 355.25 | P57: =M57/I57 -> 22082.798 | Q57: =(N57*1000000000)/I57 -> 29408545 | R57: =(N57*1000000000)/J57 -> 8896084.8 | S57: =Q57/1000000 -> 29.408545 | T57: =M57/J57 -> 6680.0463 | U57: =M57/L57 -> 620.59721 | V57: 0.045 | W57: 45580 | X57: Office | Y57: Freehold | Z57: Share Deal | AA57: 1 | AB57: 0.045 | AC57: Nuveen Real Estate | AD57: IGIS (Samsung Fire Insurance, NH Insurance, Met Life) | AE57: The building is located in the CBD and is near to the Seoul History Museum. Notable tenants include GGGI, Opus PE, Embassy of New Zealand, and Kim & Chang. The Jeongdong Building is also know for its high efficiency rate at approximately 57%. This transaction was a share deal.
A58: D Tower Donuimun | B58: Jongro-gu | C58: CBD | D58: =CONCATENATE(B58&" - "&C58) -> Jongro-gu - CBD | E58: 43999 | F58: =($E$5-E58)/365 -> 5.7863014 | G58: =YEAR(E58) -> 2020 | H58: 5 years (Built in 2020) | I58: =J58*0.3025 -> 26082.857 | J58: 86224.32 | K58: 86,224 sq. m. (26,083 py) | L58: =J58*10.7639 -> 928109.96 | M58: =(N58*1000000000)/1331.74 -> 6.7227837e+08 | N58: 895.3 | O58: =N58*0.001015*1000 -> 908.7295 | P58: =M58/I58 -> 25774.722 | Q58: =(N58*1000000000)/I58 -> 34325228 | R58: =(N58*1000000000)/J58 -> 10383381 | S58: =Q58/1000000 -> 34.325228 | T58: =M58/J58 -> 7796.8533 | U58: =M58/L58 -> 724.35207 | V58: 0.038 | W58: 45597 | X58: Office | Y58: Freehold | Z58: Asset Deal | AA58: N/A | AB58: 0.038 | AC58: NH Nonghyup REITs | AD58: Mastern AMC | AE58: The building is located in the Seosomun area of the CBD and the owner Mastern is trying to dispose to asset as its fund will expire in January 2025. Tenants include DL, DL E&C, DL Chemical, DL Energy. The asset is LEED (O+M) Platinum certified building,
A59: NH Nonghyup Capital Building | B59: Yeongdeungpo-gu | C59: YBD | D59: =CONCATENATE(B59&" - "&C59) -> Yeongdeungpo-gu - YBD | E59: 34876 | F59: =($E$5-E59)/365 -> 30.780822 | G59: =YEAR(E59) -> 1995 | H59: 30 years (Built in 1995) | I59: =J59*0.3025 -> 6261.9345 | J59: 20700.61 | K59: 20,701 sq. m. (6,262 py) | L59: =J59*10.7639 -> 222819.3 | M59: =(N59*1000000000)/1331.74 -> 1.0550107e+08 | N59: 140.5 | O59: =N59*0.001015*1000 -> 142.6075 | P59: =M59/I59 -> 16848 | Q59: =(N59*1000000000)/I59 -> 22437156 | R59: =(N59*1000000000)/J59 -> 6787239.6 | S59: =Q59/1000000 -> 22.437156 | T59: =M59/J59 -> 5096.52 | U59: =M59/L59 -> 473.48266 | V59: 0.041 | W59: 45611 | X59: Office | Y59: Freehold | Z59: Asset Deal | AA59: 1 | AB59: 0.041 | AC59: KORAMCO Asset Trust | AD59: KREITS | AE59: The building is located in the YBD area and is deemed to have a value up opportunity via rent rent increase with the WALE of 2.1 years. The current BAR is at 566.31% and there is a room for an additional renovation to increase the office area. Orchestro, a cloud computing company invested in fund for acquiring the building and is expected to use the building for its headquarter building.
A60: KOREIT Tower | B60: Gangnam-gu | C60: GBD | D60: =CONCATENATE(B60&" - "&C60) -> Gangnam-gu - GBD | E60: 37134 | F60: =($E$5-E60)/365 -> 24.594521 | G60: =YEAR(E60) -> 2001 | H60: 23 years (Built in 2001) | I60: =J60*0.3025 -> 10582.554 | J60: 34983.65 | K60: 34,984 sq. m. (10,583 py) | L60: =J60*10.7639 -> 376560.51 | M60: =(N60*1000000000)/1331.74 -> 3.3482512e+08 | N60: 445.9 | O60: =N60*0.001015*1000 -> 452.5885 | P60: =M60/I60 -> 31639.348 | Q60: =(N60*1000000000)/I60 -> 42135386 | R60: =(N60*1000000000)/J60 -> 12745954 | S60: =Q60/1000000 -> 42.135386 | T60: =M60/J60 -> 9570.9029 | U60: =M60/L60 -> 889.16683 | V60: 0.02502092 | W60: 45637 | X60: Office + Data Centre | Y60: Freehold | Z60: Share Deal | AA60: 1 | AB60: N/A | AC60: KORAMCO AMC | AD60: KOREIT REITS | AE60: The building is located in the prime GBD area where most of the are is leased to KOREIT and its related company Dongbu Construction. The building comprises of a data center area, 8,145.43㎡ in GFA, which accounts for more than 14% of the overall GFA of the building. This transaction was a share deal.
A61: *K Square City: Strata Deal (GFA: 66%)
A62: **Hanhwa HQ Building: Strata Deal (GFA: 48.6%)
A63: ***Taeyoung HQ Building: Strata Deal (GFA: 97.3%)
A64: Source: Colliers Database, Market News
A65: Crystal Square | B65: Jung-gu | C65: CBD | D65: =CONCATENATE(B65&" - "&C65) -> Jung-gu - CBD | E65: 44281 | F65: =($E$5-E65)/365 -> 5.0136986 | G65: =YEAR(E65) -> 2021 | H65: 4 years (Built in 2021) | I65: =J65*0.3025 -> 5572.9575 | J65: 18423 | K65: 18,423 sq. m. (5,573 py) | L65: =J65*10.7639 -> 198303.33 | M65: =(N65*1000000000)/1331.74 -> 1.5528557e+08 | N65: 206.8 | O65: =N65*0.001015*1000 -> 209.902 | P65: =M65/I65 -> 27864.122 | Q65: =(N65*1000000000)/I65 -> 37107765 | R65: =(N65*1000000000)/J65 -> 11225099 | S65: =Q65/1000000 -> 37.107765 | T65: =M65/J65 -> 8428.8968 | U65: =M65/L65 -> 783.0709 | V65: 0.039 | W65: 45702 | X65: Office | Y65: Freehold | Z65: Asset Deal | AA65: 1 | AB65: N/A | AC65: Capitaland AMC(Aberdeen) | AD65: Sillajen, Leedcorp | AE65: The building is located in the Supyo area in the CBD and the buyer, Leadcorp is a strategic investor. The building recorded a 100% occupancy rate at the point of acquisition and major tenants include KB Card 90% of GLA), Starbucks, 7-Eleven.
A66: Gangnam Finance Plaza | B66: Gangnam-gu | C66: GBD | D66: =CONCATENATE(B66&" - "&C66) -> Gangnam-gu - GBD | E66: 34624 | F66: =($E$5-E66)/365 -> 31.471233 | G66: =YEAR(E66) -> 1994 | H66: 30 years (Built in 1994) | I66: =J66*0.3025 -> 7314.2866 | J66: 24179.46 | K66: 24,179 sq. m. (7,314 py) | L66: =J66*10.7639 -> 260265.29 | M66: =(N66*1000000000)/1331.74 -> 2.0724766e+08 | N66: 276 | O66: =N66*0.001015*1000 -> 280.14 | P66: =M66/I66 -> 28334.638 | Q66: =(N66*1000000000)/I66 -> 37734370 | R66: =(N66*1000000000)/J66 -> 11414647 | S66: =Q66/1000000 -> 37.73437 | T66: =M66/J66 -> 8571.2279 | U66: =M66/L66 -> 796.29389 | V66: 0.041 | W66: 45708 | X66: Office | Y66: Freehold | Z66: Asset Deal | AA66: 0.9157 | AB66: N/A | AC66: Mastern | AD66: Gravity AMC | AE66: The building is located in the prime GBD area and was acquired by a Gravity AMC backed by ISU Group (Strategic Investor). Mastern Investment Management has decided to sell the property five years after acquiring it from Pebblestone Asset Management in August 2018 for approximately KRW 183 billion. The generous ceiling height of 4.5 meters provides a sense of openness and enhances spatial efficiency and buyer is planning further renovations in the building.
A67: Namsan Square Building | B67: Jung-gu | C67: CBD | D67: =CONCATENATE(B67&" - "&C67) -> Jung-gu - CBD | E67: 28712 | F67: =($E$5-E67)/365 -> 47.668493 | G67: =YEAR(E67) -> 1978 | H67: 43 years (Built in 1978, Renovated in 2011) | I67: =J67*0.3025 -> 22763.866 | J67: 75252.45 | K67: 75,252 sq. m. (22,764 py) | L67: =J67*10.7639 -> 810009.85 | M67: =(N67*1000000000)/1331.74 -> 4.3588013e+08 | N67: 580.479 | O67: =N67*0.001015*1000 -> 589.18619 | P67: =M67/I67 -> 19147.895 | Q67: =(N67*1000000000)/I67 -> 25500018 | R67: =(N67*1000000000)/J67 -> 7713755.5 | S67: =Q67/1000000 -> 25.500018 | T67: =M67/J67 -> 5792.2383 | U67: =M67/L67 -> 538.11707 | V67: 0.045 | W67: 45714 | X67: Office | Y67: Freehold | Z67: Asset Deal | AA67: 0.99 | AB67: N/A | AC67: IGIS (KKR) | AD67: HDC AMC | AE67: The building is located in the outskirts of the CBD. An additional annex for office use can be constructed, allowing for potential value-add strategies in the future. Major public institutions and large corporations, such as the Korea Healthy Family Support Center, Korea Workers’ Compensation & Welfare Service, and Xi S&D, are current tenants of Namsan Square. The vacancy rate remains at approximately 1%
A68: Jeongan Building | B68: Jung-gu | C68: CBD | D68: =CONCATENATE(B68&" - "&C68) -> Jung-gu - CBD | E68: 35409 | F68: =($E$5-E68)/365 -> 29.320548 | G68: =YEAR(E68) -> 1996 | H68: 29 years (Built in 1996) | I68: =J68*0.3025 -> 4765.8996 | J68: 15755.04 | K68: 15,755 sq. m. (4,766 py) | L68: =J68*10.7639 -> 169585.68 | M68: =(N68*1000000000)/1331.74 -> 98795561 | N68: 131.57 | O68: =N68*0.001015*1000 -> 133.54355 | P68: =M68/I68 -> 20729.677 | Q68: =(N68*1000000000)/I68 -> 27606540 | R68: =(N68*1000000000)/J68 -> 8350978.5 | S68: =Q68/1000000 -> 27.60654 | T68: =M68/J68 -> 6270.7274 | U68: =M68/L68 -> 582.5702 | V68: 4.3% (*Estimated) | W68: 45716 | X68: Office | Y68: Freehold | Z68: Asset Deal | AA68: 1 | AB68: N/A | AC68: United Asset Management Company (UAMCO) | AD68: Eden AMC | AE68: The building is located in the Seosomun area of the CBD. The acquirer is planning the execute a 'Value-add' strategy post acquisition. | AF68: https://news.nate.com/view/20250326n46250
A69: Yeouido Hyundai Motors Securities Building | B69: Yeongdeungpo-gu | C69: YBD | D69: =CONCATENATE(B69&" - "&C69) -> Yeongdeungpo-gu - YBD | E69: 34397 | F69: =($E$5-E69)/365 -> 32.093151 | G69: =YEAR(E69) -> 1994 | H69: 31 years (Built in 1994) | I69: =J69*0.3025 -> 12233.094 | J69: 40439.98 | K69: 40,440 sq. m. (12,233 py) | L69: =J69*10.7639 -> 435291.9 | M69: =(N69*1000000000)/1331.74 -> 2.6638833e+08 | N69: 354.76 | O69: =N69*0.001015*1000 -> 360.0814 | P69: =M69/I69 -> 21776.039 | Q69: =(N69*1000000000)/I69 -> 29000023 | R69: =(N69*1000000000)/J69 -> 8772506.8 | S69: =Q69/1000000 -> 29.000023 | T69: =M69/J69 -> 6587.2519 | U69: =M69/L69 -> 611.97632 | V69: 4.2% (*Estimated) | W69: 45747 | X69: Office | Y69: Freehold | Z69: Share Deal | AA69: 0.99 | AB69: N/A | AC69: Hyundai Automobile Securities | AD69: KORAMCO AMC | AE69: The Hyundai Motor Securities Building, currently leased by tenants including Hyundai Motor Securities and Shinhan Fund Partners, was sold by KB Asset Management to Koramco in October 2020 for KRW 266.6 billion. With the Yeouido Financial District Master Plan allowing FAR increases up to 1,600%, the property presents redevelopment potential if reconstruction proceeds. | AF69: https://dealbook.co.kr/yeoyido-hyeondaecajeunggweonbilding-koramkounyong-pumeuro-doedolaon-sayeon/
A70: Gangnam Taegwang Tower | B70: Gangnam-gu | C70: GBD | D70: =CONCATENATE(B70&" - "&C70) -> Gangnam-gu - GBD | E70: 42404 | F70: =($E$5-E70)/365 -> 10.156164 | G70: =YEAR(E70) -> 2016 | H70: 9 years (Built in 2016) | I70: =J70*0.3025 -> 5262.3505 | J70: 17396.2 | K70: 17,396 sq. m. (5,262 py) | L70: =J70*10.7639 -> 187250.96 | M70: =(N70*1000000000)/1331.74 -> 1.3140703e+08 | N70: 175 | O70: =N70*0.001015*1000 -> 177.625 | P70: =M70/I70 -> 24971.167 | Q70: =(N70*1000000000)/I70 -> 33255101 | R70: =(N70*1000000000)/J70 -> 10059668 | S70: =Q70/1000000 -> 33.255101 | T70: =M70/J70 -> 7553.7779 | U70: =M70/L70 -> 701.76961 | V70: 3.9% (*Quoted) | W70: 45758 | X70: Office | Y70: Freehold | Z70: Asset Deal | AA70: N/A | AB70: N/A | AC70: Hana Asset Trust | AD70: Taegwang Development | AE70: The property serves as the headquarters for Taekwang Development and its affiliates, including Taekwang Asset and AMPM. It is currently occupied by several tenants such as Min & Je, Hecto Innovation, and Hecto Financial. | AF70: https://dealbook.co.kr/hanaopiseuyeogsamriceu-taegwangtaweo-maeibjageum-1940eog-jodal-bagca/
A71: Crescendo Building | B71: Jongro-gu | C71: CBD | D71: =CONCATENATE(B71&" - "&C71) -> Jongro-gu - CBD | E71: 36850 | F71: =($E$5-E71)/365 -> 25.372603 | G71: =YEAR(E71) -> 2000 | H71: 25 years (Built in 2000) | I71: =J71*0.3025 -> 16538.377 | J71: 54672.32 | K71: 54,672 sq. m. (16,538 py) | L71: =J71*10.7639 -> 588487.39 | M71: =(N71*1000000000)/1331.74 -> 4.1801628e+08 | N71: 556.689 | O71: =N71*0.001015*1000 -> 565.03934 | P71: =M71/I71 -> 25275.532 | Q71: =(N71*1000000000)/I71 -> 33660438 | R71: =(N71*1000000000)/J71 -> 10182282 | S71: =Q71/1000000 -> 33.660438 | T71: =M71/J71 -> 7645.8486 | U71: =M71/L71 -> 710.32326 | V71: 4.1% (*Quoted) | W71: 45765 | X71: Office | Y71: Freehold | Z71: Asset Deal | AA71: 0.99 | AB71: N/A | AC71: KORAMCO Asset Trust | AD71: DWS AMC | AE71: The asset is fully leased to Kim & Chang, Korea’s largest law firm, under a single-tenant agreement through November 2029. While the seller aimed for a price in line with the nearby Concordian Building (KRW 34.5 million per pyeong, transacted last year), market uncertainties led to the selection of a preferred bidder at a lower price. The subdued pricing of the SFC building also appears to have influenced the valuation of the Crescendo Building. | AF71: https://www.mk.co.kr/news/stock/11295367
A72: KDB Life Tower | B72: Yongsan-gu | C72: CBD | D72: =CONCATENATE(B72&" - "&C72) -> Yongsan-gu - CBD | E72: 41526 | F72: =($E$5-E72)/365 -> 12.561644 | G72: =YEAR(E72) -> 2013 | H72: 12 years (Built in 2013) | I72: =J72*0.3025 -> 24936.442 | J72: 82434.52 | K72: 82,435 sq. m. (24,936 py) | L72: =J72*10.7639 -> 887316.93 | M72: =(N72*1000000000)/1331.74 -> 5.0640884e+08 | N72: 674.40491 | O72: =N72*0.001015*1000 -> 684.52099 | P72: =M72/I72 -> 20307.983 | Q72: =(N72*1000000000)/I72 -> 27044953 | R72: =(N72*1000000000)/J72 -> 8181098.3 | S72: =Q72/1000000 -> 27.044953 | T72: =M72/J72 -> 6143.1648 | U72: =M72/L72 -> 570.71924 | V72: 3.9% (*Quoted) | W72: 45807 | X72: Office | Y72: Freehold | Z72: Asset Deal | AA72: N/A | AB72: N/A | AC72: CJ Oliveyoung | AD72: KB AMC | AE72: The asset comprises an office property with street-level retail components and was acquired for occupancy purposes. The primary tenants include KDB Life Insurance, which operates its headquarters at the site, and CJ Olive Young. The property was previously transacted in June 2018 at a consideration of KRW 422.3 billion. The fund associated with the asset is scheduled to mature in June 2025. | AF72: https://www.hankyung.com/article/2025051685761
A73: BNK Digital Tower | B73: Gangnam-gu | C73: GBD | D73: =CONCATENATE(B73&" - "&C73) -> Gangnam-gu - GBD | E73: 35608 | F73: =($E$5-E73)/365 -> 28.775342 | G73: =YEAR(E73) -> 1997 | H73: 28 years (Built in 1997) | I73: =J73*0.3025 -> 11247.628 | J73: 37182.24 | K73: 37,182 sq. m. (11,248 py) | L73: =J73*10.7639 -> 400225.91 | M73: =(N73*1000000000)/1331.74 -> 3.4376079e+08 | N73: 457.8 | O73: =N73*0.001015*1000 -> 464.667 | P73: =M73/I73 -> 30562.96 | Q73: =(N73*1000000000)/I73 -> 40701917 | R73: =(N73*1000000000)/J73 -> 12312330 | S73: =Q73/1000000 -> 40.701917 | T73: =M73/J73 -> 9245.2954 | U73: =M73/L73 -> 858.91688 | V73: 3.6% (*Estimated) | W73: 45833 | X73: Office | Y73: Freehold | Z73: Asset Deal | AA73: 0.97 | AB73: N/A | AC73: Shinhan Alpha REITs | AD73: BNK AMC | AE73: The BNK Digital Tower, with a gross floor area of around 10,000 pyeong, is one of the most sought-after office assets in the Gangnam Business District. Its 228 parking spaces—about 1.5 times the norm—make it ideal for firms with large sales teams. The building underwent major renovations in 2011 and 2022, enhancing its value, and holds a LEED O+M Gold certification for sustainable operations. It is currently leased to high-quality tenants in finance, professional services, and IT, with a stable occupancy rate above 95%. | AF73: https://www.chosun.com/economy/money/2025/06/26/DES4ZPYHXI477M43BCKNL2XKPY/
A74: Seoul International (SI) Tower (ex ING Tower) | B74: Gangnam-gu | C74: GBD | D74: =CONCATENATE(B74&" - "&C74) -> Gangnam-gu - GBD | E74: 36488 | F74: =($E$5-E74)/365 -> 26.364384 | G74: =YEAR(E74) -> 1999 | H74: 26 years (Built in 1999) | I74: =J74*0.3025 -> 20026.223 | J74: 66202.39 | K74: 66,202 sq. m. (20,026 py) | L74: =J74*10.7639 -> 712595.91 | M74: =(N74*1000000000)/1331.74 -> 6.7365477e+08 | N74: 897.133 | O74: =N74*0.001015*1000 -> 910.59 | P74: =M74/I74 -> 33638.633 | Q74: =(N74*1000000000)/I74 -> 44797913 | R74: =(N74*1000000000)/J74 -> 13551369 | S74: =Q74/1000000 -> 44.797913 | T74: =M74/J74 -> 10175.687 | U74: =M74/L74 -> 945.35313 | V74: N/A | W74: 45835 | X74: Office | Y74: Freehold | Z74: Share Deal | AA74: 1 | AB74: N/A | AC74: IGIS AMC | AD74: KB AMC | AE74: The SI Tower, serving as Hyundai Mobis’s headquarters, was acquired by Hyundai Motor Group through a share deal after a planned public sale was withdrawn. Samsung Fire & Marine Insurance holds a major beneficiary interest in the asset. Around 70% of the building is leased long-term to Hyundai Mobis, ensuring stable rental income. Other tenants include Nokia, Santen Pharmaceutical Korea, and Seoul Guarantee Insurance. With only minor vacancies on the 15th and 24th floors, the property maintains a strong occupancy and stable cash flow. | AF74: https://www.mk.co.kr/economy/view.php?sc=50000001&year=2025&no=202364
A75: Gangnam N Tower | B75: Gangnam-gu | C75: GBD | D75: Gangnam-gu - GBD | E75: 43313 | F75: =($E$5-E75)/365 -> 7.6657534 | G75: =YEAR(E75) -> 2018 | H75: 7 years (Built in 2018) | I75: =J75*0.3025 -> 7732.8544 | J75: 25563.155 | K75: =CONCATENATE(J75, I75) -> 25563.1557732.8543875 | L75: =J75*10.7639 -> 275159.24 | M75: =(N75*1000000000)/1331.74 -> 5.1098563e+08 | N75: 680.5 | O75: =N75*0.001015*1000 -> 690.7075 | P75: =M75/I75 -> 66079.82 | Q75: =(N75*1000000000)/I75 -> 88001140 | R75: =(N75*1000000000)/J75 -> 26620345 | S75: =Q75/1000000 -> 88.00114 | T75: =M75/J75 -> 19989.146 | U75: =M75/L75 -> 1857.0542 | V75: 0.031 | W75: 45835 | X75: Office | Y75: Freehold | Z75: Share Deal | AA75: 0.97 | AB75: N/A | AC75: Bitthumb | AD75: KB AMC | AE75: The Gangnam N Tower, a prime office completed six years ago, benefits from its Teheran-ro frontage and “double station” location between Gangnam and Yeoksam Stations. The 31-story building (7 basement, 24 above-ground) is about 97% occupied. KB Real Estate Trust, its former headquarters tenant, is relocating to the new Yangjae KB Life Tower. | AF75: https://biz.chosun.com/real_estate/real_estate_general/2025/05/23/CJDAE3WR7BHVVNAXK2FRP3THKI/
A76: Hyundai Group Yeonji-dong HQ | B76: Jongno-gu | C76: CBD | D76: Jongno-gu - CBD | E76: 33912 | F76: =($E$5-E76)/365 -> 33.421918 | G76: =YEAR(E76) -> 1992 | H76: 33 years (Built in 1992) | I76: =J76*0.3025 -> 15874.084 | J76: 52476.31 | K76: =CONCATENATE(J76, I76) -> 52476.3115874.083775 | L76: =J76*10.7639 -> 564849.75 | M76: =(N76*1000000000)/1331.74 -> 3.379038e+08 | N76: 450 | O76: =N76*0.001015*1000 -> 456.75 | P76: =M76/I76 -> 21286.507 | Q76: =(N76*1000000000)/I76 -> 28348093 | R76: =(N76*1000000000)/J76 -> 8575298.1 | S76: =Q76/1000000 -> 28.348093 | T76: =M76/J76 -> 6439.1684 | U76: =M76/L76 -> 598.21889 | V76: N/A | W76: 45926 | X76: Office | Y76: Freehold | Z76: Asset Deal | AA76: N/A | AB76: N/A | AC76: Vault AMC | AD76: Hyundai Group | AE76: Hyundai Group plans to divest its Yeonji-dong headquarters through a sale-and-leaseback transaction, ensuring that Hyundai Elevator and other key affiliates will continue to occupy and operate from the premises after the sale. | AF76: https://www.digitaltoday.co.kr/news/articleView.html?idxno=593874
A77: Pacific Tower | B77: Jung-gu | C77: CBD | D77: Jung-gu - CBD | E77: 37383 | F77: =($E$5-E77)/365 -> 23.912329 | G77: =YEAR(E77) -> 2002 | H77: 23 years (Built in 2002) | I77: =J77*0.3025 -> 17998.88 | J77: 59500.43 | K77: =CONCATENATE(J77, I77) -> 59500.4317998.880075 | L77: =J77*10.7639 -> 640456.68 | M77: =(N77*1000000000)/1331.74 -> 4.3552045e+08 | N77: 580 | O77: =N77*0.001015*1000 -> 588.7 | P77: =M77/I77 -> 24197.086 | Q77: =(N77*1000000000)/I77 -> 32224227 | R77: =(N77*1000000000)/J77 -> 9747828.7 | S77: =Q77/1000000 -> 32.224227 | T77: =M77/J77 -> 7319.6185 | U77: =M77/L77 -> 680.01547 | V77: N/A | W77: 45863 | X77: Office | Y77: Freehold | Z77: Share Deal | AA77: 1 | AB77: N/A | AC77: Abrdeen | AD77: Pebblestone | AE77: After refinancing and extending fund maturity in March, Pebblestone Asset Management relaunched the Pacific Tower sale, drawing interest from Aberdeen, another foreign investor, and IGIS. Fully occupied by 15 tenants such as Chanel, Huawei, and Kyobo Life, the tower’s below-market rents offer clear upside for future growth. | AF77: https://biz.chosun.com/stock/stock_general/2025/07/28/PVUFE5EMCJAOJA3SFCPR24ZZQE/
A78: NC Tower 1 | B78: Gangnam-gu | C78: GBD | D78: Gangnam-gu - GBD | E78: 39535 | F78: =($E$5-E78)/365 -> 18.016438 | G78: =YEAR(E78) -> 2008 | H78: 18 years (Built in 2008) | I78: =J78*0.3025 -> 9351.1674 | J78: 30912.95 | K78: =CONCATENATE(J78, I78) -> 30912.959351.167375 | L78: =J78*10.7639 -> 332743.9 | M78: =(N78*1000000000)/1331.74 -> 3.3302296e+08 | N78: 443.5 | O78: =N78*0.001015*1000 -> 450.1525 | P78: =M78/I78 -> 35612.983 | Q78: =(N78*1000000000)/I78 -> 47427234 | R78: =(N78*1000000000)/J78 -> 14346738 | S78: =Q78/1000000 -> 47.427234 | T78: =M78/J78 -> 10772.927 | U78: =M78/L78 -> 1000.8387 | V78: 0.034 | W78: 45880 | X78: Office | Y78: Freehold | Z78: Asset Deal | AA78: N/A | AB78: N/A | AC78: Pacific AMC (SEMA) | AD78: NC Soft | AE78: 111Percent, still targeting a Gangnam HQ after last year’s failed Koreit Tower bid, joined Mirae Asset in the process. Other bidders included Kiwoom, Hana Alternative, Korea Investment & Real Asset, HL REITs, Pacific, Keppel, and the Hyunsong Foundation. | AF78: https://www.investchosun.com/site/data/html_dir/2025/02/05/2025020580208.html
A79: Ferrum Tower | B79: Jung-gu | C79: CBD | D79: Jung-gu - CBD | E79: 40380 | F79: =($E$5-E79)/365 -> 15.70137 | G79: =YEAR(E79) -> 2010 | H79: 15 years (Built in 2010) | I79: =J79*0.3025 -> 16847.623 | J79: 55694.62 | K79: =CONCATENATE(J79, I79) -> 55694.6216847.62255 | L79: =J79*10.7639 -> 599491.32 | M79: =(N79*1000000000)/1331.74 -> 4.8437383e+08 | N79: 645.06 | O79: =N79*0.001015*1000 -> 654.7359 | P79: =M79/I79 -> 28750.278 | Q79: =(N79*1000000000)/I79 -> 38287895 | R79: =(N79*1000000000)/J79 -> 11582088 | S79: =Q79/1000000 -> 38.287895 | T79: =M79/J79 -> 8696.959 | U79: =M79/L79 -> 807.97471 | V79: 0.037 | W79: 45897 | X79: Office | Y79: Freehold | Z79: Asset Deal | AA79: N/A | AB79: N/A | AC79: Dongkuk Steel | AD79: Samsung Life Insurance Co., Ltd. | AE79: The subject CBD office with ground-floor retail last traded in May 2015 for KRW 420.0 billion. The current sale is via a pre-agreed purchase option under a negotiated contract, not a competitive bid. | AF79: https://www.chosun.com/economy/industry-company/2025/07/25/UIXMB6RG4ZEHXGQPGCYBANGBPE/
A80: WeWork Building | B80: Gangnam-gu | C80: GBD | D80: Gangnam-gu - GBD | E80: 34333 | F80: =($E$5-E80)/365 -> 32.268493 | G80: =YEAR(E80) -> 1993 | H80: 32 years (Built in 1993) | I80: =J80*0.3025 -> 6088.2481 | J80: 20126.44 | K80: =CONCATENATE(J80, I80) -> 20126.446088.2481 | L80: =J80*10.7639 -> 216638.99 | M80: =(N80*1000000000)/1331.74 -> 1.5956568e+08 | N80: 212.5 | O80: =N80*0.001015*1000 -> 215.6875 | P80: =M80/I80 -> 26208.801 | Q80: =(N80*1000000000)/I80 -> 34903308 | R80: =(N80*1000000000)/J80 -> 10558251 | S80: =Q80/1000000 -> 34.903308 | T80: =M80/J80 -> 7928.1622 | U80: =M80/L80 -> 736.55108 | V80: 0.03 | W80: 45898 | X80: Office | Y80: Freehold | Z80: Asset Deal | AA80: N/A | AB80: N/A | AC80: Asia Property | AD80: Hana Alternative Asset Management Co., Ltd. | AE80: Asia Property and its affiliate Urban Asset Management have completed the acquisition of the WeWork Building in Samseong-dong, Seoul. After deliberation between asset deal (transfer of property ownership) and share deal (transfer of equity), the transaction was finalized as an asset deal. | AF80: https://www.mk.co.kr/news/stock/11281840
A81: Namsan N Tower | B81: Jung-gu | C81: CBD | D81: Jung-gu - CBD | E81: 46022 | F81: =($E$5-E81)/365 -> 0.24383562 | G81: =YEAR(E81) -> 2025 | H81: *Under construction | I81: =J81*0.3025 -> 6312.4793 | J81: 20867.7 | K81: =CONCATENATE(J81, I81) -> 20867.76312.47925 | L81: =J81*10.7639 -> 224617.84 | M81: =(N81*1000000000)/1331.74 -> 1.7045369e+08 | N81: 227 | O81: =N81*0.001015*1000 -> 230.405 | P81: =M81/I81 -> 27002.654 | Q81: =(N81*1000000000)/I81 -> 35960514 | R81: =(N81*1000000000)/J81 -> 10878056 | S81: =Q81/1000000 -> 35.960514 | T81: =M81/J81 -> 8168.3028 | U81: =M81/L81 -> 758.8609 | V81: N/A | W81: 45918 | X81: Office | Y81: Freehold | Z81: Asset Deal | AA81: N/A | AB81: N/A | AC81: Samyang Foods | AD81: Namsan PFV Co | AE81: Samyang Foods is acquiring Namsan N Tower in Jung-gu, Seoul for about KRW 227 billion (KRW 36m per 3.3㎡). Developed by Namsan PFV with 6 basement and 15 above-ground floors (GFA 20,867㎡), the building will complete in August and serve as Samyang’s new headquarters. | AF81: https://www.corebeat.co.kr/article/816
A82: Centerpoint Gwanghwamun | B82: Jongno-gu | C82: CBD | D82: Jongno-gu - CBD | E82: 41516 | F82: =($E$5-E82)/365 -> 12.589041 | G82: =YEAR(E82) -> 2013 | H82: 12 years (Built in 2013) | I82: =J82*0.3025 -> 11781.322 | J82: 38946.52 | K82: 38,947 sq. m. (11,781 py) | L82: =J82*10.7639 -> 419216.45 | M82: =(N82*1000000000)/1331.74 -> 3.2438764e+08 | N82: 432 | O82: =N82*0.001015*1000 -> 438.48 | P82: =M82/I82 -> 27534.061 | Q82: =(N82*1000000000)/I82 -> 36668210 | R82: =(N82*1000000000)/J82 -> 11092134 | S82: =Q82/1000000 -> 36.66821 | T82: =M82/J82 -> 8329.0534 | U82: =M82/L82 -> 773.79513 | V82: 0.037 | W82: 45945 | X82: Office | Y82: Freehold | Z82: Share Deal | AA82: 1 | AB82: N/A | AC82: Kyobo AIM Asset Management Co., Ltd. | AD82: Koramco Asset Trust Co., Ltd. | AE82: Centerpoint Gwanghwamun, held via KOCREF No.36 REIT, was sold to Kyobo AIM Asset Management at KRW 36.7 million per pyeong, implying a total value of KRW 432.0 billion. The transaction achieved a record-low 3.7% cap rate, among the strongest pricing in the Seoul CBD office market. Structured as a share deal, the sale involved a change in REIT shareholders rather than a direct asset transfer. The property is a prime CBD office building, largely leased (c.80%) to Kim & Chang under a long-term lease, providing highly stable cash flows despite a challenging transaction environment. | AF82: https://news.einfomax.co.kr/news/articleView.html?idxno=4377351
A83: Samsung Dong Building (Interpark Building) | B83: Gangnam-gu | C83: GBD | D83: Gangnam-gu - GBD | E83: 40242 | F83: =($E$5-E83)/365 -> 16.079452 | G83: =YEAR(E83) -> 2010 | H83: 16 years (Built in 2010) | I83: =J83*0.3025 -> 9279.3539 | J83: 30675.55 | K83: 30,676 sq. m. (9,279 py) | L83: =J83*10.7639 -> 330188.55 | M83: =(N83*1000000000)/1331.74 -> 2.6281406e+08 | N83: 350 | O83: =N83*0.001015*1000 -> 355.25 | P83: =M83/I83 -> 28322.453 | Q83: =(N83*1000000000)/I83 -> 37718143 | R83: =(N83*1000000000)/J83 -> 11409738 | S83: =Q83/1000000 -> 37.718143 | T83: =M83/J83 -> 8567.542 | U83: =M83/L83 -> 795.95147 | V83: 0.039 | W83: 45966 | X83: Office | Y83: Freehold | Z83: Share Deal | AA83: N/A | AB83: N/A | AC83: KITRUST | AD83: Kyobo Asset Trust | AE83: The property offers an immediately available exclusive area of 1,400 pyeong, which is expected to draw strong interest from companies seeking a new headquarters in Gangnam. Currently, more than half of the space is occupied by high-quality tenants such as Kolon Industries and iMarketKorea. The transaction was structured as a share deal, involving both a capital reduction (repurchase of existing shareholders’ stakes) and a capital increase (issuance of new shares to incoming investors), effectively transferring control of the REIT. | AF83: https://dealsite.co.kr/articles/151289
A84: Signature Tower | B84: Jung-gu | C84: CBD | D84: Jung-gu - CBD | E84: 40723 | F84: =($E$5-E84)/365 -> 14.761644 | G84: =YEAR(E84) -> 2011 | H84: 14 years (Built in 2011) | I84: =J84*0.3025 -> 30249.123 | J84: 99997.1 | K84: 99,997 sq. m. (30,249 py) | L84: =J84*10.7639 -> 1076358.8 | M84: =(N84*1000000000)/1331.74 -> 7.7687837e+08 | N84: 1034.6 | O84: =N84*0.001015*1000 -> 1050.119 | P84: =M84/I84 -> 25682.674 | Q84: =(N84*1000000000)/I84 -> 34202645 | R84: =(N84*1000000000)/J84 -> 10346300 | S84: =Q84/1000000 -> 34.202645 | T84: =M84/J84 -> 7769.009 | U84: =M84/L84 -> 721.76525 | V84: 0.047 | W84: 45985 | X84: Office | Y84: Freehold | Z84: Share Deal | AA84: 1 | AB84: N/A | AC84: KB Asset Management, Kumho Petrochemical, KB Securities Co Ltd | AD84: IGIS, NPS | AE84: Signature Tower, a prime Seoul CBD office, was sold for KRW 1.035 trillion in a structured share deal led by KB Asset Management, combining beneficiary interest transfers and refinancing, including ABCP-backed debt. The asset is nearly 100,000 sq.m., fully leased with long-term tenants, supporting stable cash flows. Acquired by IGIS in 2017 for KRW 720 billion, the sale delivered a gain of over KRW 300 billion, highlighting continued demand for core CBD offices. | AF84: https://dealsite.co.kr/articles/152050
A85: Premier Place | B85: Jung-gu | C85: CBD | D85: Jung-gu - CBD | E85: 33847 | F85: =($E$5-E85)/365 -> 33.6 | G85: =YEAR(E85) -> 1992 | H85: 33 years (Built in 1992) | I85: =J85*0.3025 -> 4974.3705 | J85: 16444.2 | K85: 16,444 sq. m. (4,974 py) | L85: =J85*10.7639 -> 177003.72 | M85: =(N85*1000000000)/1331.74 -> 1.2539985e+08 | N85: 167 | O85: =N85*0.001015*1000 -> 169.505 | P85: =M85/I85 -> 25209.19 | Q85: =(N85*1000000000)/I85 -> 33572087 | R85: =(N85*1000000000)/J85 -> 10155556 | S85: =Q85/1000000 -> 33.572087 | T85: =M85/J85 -> 7625.7801 | U85: =M85/L85 -> 708.45884 | V85: N/A | W85: 45989 | X85: Office | Y85: Freehold | Z85: Asset Deal | AA85: N/A | AB85: N/A | AC85: Money Today | AD85: GIC | AE85: Premier Place is a mid-sized office building at 8 Cheonggyecheon-ro, Jung-gu, Seoul, completed in 1992 and adjacent to Gwanghwamun Station (Line 5). About two-thirds is leased to the Seoul Metropolitan Government, with the balance occupied by private tenants. The seller, GIC, which built its Gwanghwamun office portfolio post-1997, is accelerating divestments in the area following the sale of The Exchange Seoul. | AF85: https://www.investchosun.com/site/data/html_dir/2025/09/26/2025092680169.html
A86: S1310 Building | B86: Seocho-gu | C86: GBD | D86: Seocho-gu - GBD | E86: 45917 | F86: =($E$5-E86)/365 -> 0.53150685 | G86: =YEAR(E86) -> 2025 | H86: 0.2 years (Built in 2025) | I86: =J86*0.3025 -> 4160.2371 | J86: 13752.85 | K86: 13,753 sq. m. (4,160 py) | L86: =J86*10.7639 -> 148034.3 | M86: =(N86*1000000000)/1331.74 -> 1.3463589e+08 | N86: 179.3 | O86: =N86*0.001015*1000 -> 181.9895 | P86: =M86/I86 -> 32362.552 | Q86: =(N86*1000000000)/I86 -> 43098505 | R86: =(N86*1000000000)/J86 -> 13037298 | S86: =Q86/1000000 -> 43.098505 | T86: =M86/J86 -> 9789.672 | U86: =M86/L86 -> 909.49116 | V86: N/A | W86: 45989 | X86: Office | Y86: Freehold | Z86: Asset Deal | AA86: N/A | AB86: N/A | AC86: Shinhan Investment & Securities, HAIM Asset Management | AD86: Edn Investment Management, KT&G, Korea D&I Co | AE86: Hyundai Alternative Asset Management acquired a Gangnam Station office from KT&G for KRW 179.3 billion. Gamechanger ShiftUp invested as an SI and signed a 10-year master lease to use the building as its headquarters. The newly completed office is located in Seocho-dong, Gangnam area. | AF86: https://www.corebeat.co.kr/article/1576
A87: LG Gwanghwamun Building | B87: Jongno-gu | C87: CBD | D87: Jongno-gu - CBD | E87: 40452 | F87: =($E$5-E87)/365 -> 15.50411 | G87: =YEAR(E87) -> 2010 | H87: 15 years (Built in 2010) | I87: =J87*0.3025 -> 15521.992 | J87: 51312.37 | K87: 51,312 sq. m. (15,522 py) | L87: =J87*10.7639 -> 552321.22 | M87: =(N87*1000000000)/1331.74 -> 3.8445943e+08 | N87: 512 | O87: =N87*0.001015*1000 -> 519.68 | P87: =M87/I87 -> 24768.691 | Q87: =(N87*1000000000)/I87 -> 32985457 | R87: =(N87*1000000000)/J87 -> 9978100.8 | S87: =Q87/1000000 -> 32.985457 | T87: =M87/J87 -> 7492.5292 | U87: =M87/L87 -> 696.07941 | V87: N/A | W87: 46022 | X87: Office | Y87: Freehold | Z87: Asset Deal | AA87: N/A | AB87: N/A | AC87: LX Holdings | AD87: LG Corp. | AE87: The building is occupied by LX Holdings and key affiliates, which had been paying about KRW 17.7 billion annually in rent. Owner-occupation will eliminate this cost and improve financial efficiency. The transaction is seen not as a non-core asset sale by LG, but as a symbolic step finalizing the groups’ independent management structures. | AF87: https://www.chosun.com/economy/industry-company/2025/10/24/FK42GVDBQVEOBAGRBGFALBDAWA/#:~:text=%EC%A7%80%EC%A3%BC%EC%82%AC%EC%9D%B8%20LX%ED%99%80%EB%94%A9%EC%8A%A4%EC%99%80,12%EC%9B%94%2031%EC%9D%BC%EC%9E%85%EB%8B%88%EB%8B%A4.

Sheet Key Government Policies
A1: Seoul Key Government Policies
A3: According to the Seoul City's recent announcement ('Seoul City Planning 2040') on 3rd March 2022, deregulation in CBD, GBD, and YBD were planned. (*'Seoul City Planning 2040' is the highest legal order regarding city planning and is legally binding) :Seoul Metropolitan Government made an announcement in th 5th of January that the ratio of non-residential facilities in commercial and semi-residential areas will be abolished and eased. In the case of commercial areas, the urban planning ordinance will be revised in the first half of this year to lower the ratio from 20 percent of total floor area to 10 percent, and the 10 percent floor area ratio regulation for semi-residential areas that are not affected by the ordinance will be immediately abolished by revising the city district unit planning standard this month. When introducing rental housing or public dormitories in general and neighboring commercial areas, the government will also allow single apartment houses with 100 percent housing, not residential and commercial complexes. :The Seoul Metropolitan Government has initiated an organizational reform to enhance the expertise of its real estate policies. This measure comes in response to confusion caused by the recent lifting and subsequent expansion of land transaction permit zones. On March 27, the city announced that it is in the process of formulating an improvement plan aimed at strengthening the pre-assessment system for major real estate policies—such as the designation and cancellation of land transaction permit zones—that could significantly impact the lives and economy of Seoul citizens. As part of this initiative, the city plans to reorganize and expand its existing department into a dedicated unit focused on analyzing real estate policies and market trends. (2025 Q1) : No particular updates in 2025 Q4 CBD : Seoul City is planning to ease floor-height regulations, floor area ratio, and development methods. : The Seoul Mayor announced the 'Yongsan International Business District Development Plan' on February 5th 2024. The plan is composed of three zones: International Business Zone, Office Complex Zone,and Business Support Zone. A landmark tower the height of a 100 floor is planned in the International Business Zone, and hotels, terminals, parks and officetels are planned for the other two zones. GBD : The Seoul Metropolitan government has announced that it will introduce the time limit system for the apartment development plan to include the construction of the day care center for seniors in the Apgujeong district 2 -5 and Daechi apartment and Mido apartment. :Gangnam-gu, Seoul announced on the 17th that it has designated Garosu-gil (Sinsa-dong 667-13, 82,887㎡) as a special street area that has eased regulations on the right to sunlight. As a result, regulations on building height and right to sunlight will be eased or excluded, and existing buildings can be expanded or remodeled. YBD: : The Seoul Metropolitan government has announced that apartment development plan included in the Yeondeungpo district must construct a day care center for seniors and when excluded the development plan will be canceled.
C30: https://www.segye.com/newsView/20250929511083?OutUrl=naver
